Workbook

Sheet __FDSCACHE__
B1: This sheet contains FactSet XML data for use with this workbook's =FDS codes. Modifying the worksheet's contents may damage the workbook's =FDS functionality.

Sheet 통합명세부
A1: 순번 | B1: 국내/해외 | C1: 기준일자 | D1: 자산구분 | E1: 운용역 | F1: 펀드 | G1: 펀드명 | H1: 구분 | I1: 발행기관명 | J1: 종목 | K1: TICKER | L1: 종목명 | M1: 주수/계약수/액면 | N1: 취득가 | O1: 가격/종가 | P1: 평가손익 | Q1: 장부평가액 | R1: 시가평가액 | S1: 경과이자(선수) | T1: 누적이자 | U1: 순자산 | V1: 기준가격 | W1: 발행일 | X1: 상환일 | Y1: 이자구분 | Z1: 이자지급일 | AA1: 반영% | AB1: 표면% | AC1: 적용% | AD1: 매입% | AE1: 수익률 | AF1: 수탁사 | AG1: 듀레이션 | AH1: 신용등급 | AI1: 종목비중 | AJ1: 순자산비중 | AK1: Unnamed: 36
A2: 1 | B2: 국내 | C2: 45348 | D2: 주식 | E2: 정지영 | F2: 03V94 | G2: 한국투자글로벌채권솔루션증권모투자신탁(채권-재간접형) | H2: ETF(거래소)(채권) | I2: KINDEX 단기자금 증권 | J2: KR7190620005 | L2: ACE 단기통안채 | M2: 4000 | N2: 404586533 | O2: 100860 | P2: -1146533 | Q2: 404586533 | R2: 403440000 | S2: 0 | T2: 0 | U2: 14251350122 | V2: 906.66 | AA2: 0 | AB2: 0 | AC2: 0 | AD2: 0 | AE2: -0.28 | AF2: 신한은행 | AG2: 0 | AI2: 2.82 | AJ2: 2.83
A3: 2 | B3: 국내 | C3: 45348 | D3: 주식 | E3: 정지영 | F3: 03V94 | G3: 한국투자글로벌채권솔루션증권모투자신탁(채권-재간접형) | H3: ETF(거래소)(채권) | I3: 한국투자KINDEXKIS종합채권(AA- | J3: KR7356540005 | L3: ACE 종합채권(AA-이상)KIS액티브 | M3: 466 | N3: 45188853 | O3: 100030 | P3: 1425127 | Q3: 45188853 | R3: 46613980 | S3: 0 | T3: 0 | U3: 14251350122 | V3: 906.66 | AA3: 0 | AB3: 0 | AC3: 0 | AD3: 0 | AE3: 3.15 | AF3: 신한은행 | AG3: 0 | AI3: 0.33 | AJ3: 0.33
A4: 3 | B4: 국내 | C4: 45348 | D4: 현금 | E4: 정지영 | F4: 03V94 | G4: 한국투자글로벌채권솔루션증권모투자신탁(채권-재간접형) | H4: 보통예금 | I4: 공통 | J4: KR9999990000 | L4: 예금 | M4: 115195321 | N4: 115195321 | O4: 0 | P4: 0 | Q4: 115606468 | R4: 115606468 | S4: 0 | T4: 411147 | U4: 14251350122 | V4: 906.66 | Y4: 만기일시 | AA4: 2.97919 | AB4: 2.99 | AC4: 0 | AD4: 2.99 | AE4: 0 | AF4: 신한은행 | AG4: 0 | AI4: 0.81 | AJ4: 0.81
A5: 4 | B5: 국내 | C5: 45348 | D5: 기타자산 | E5: 정지영 | F5: 03V95 | G5: 한국투자글로벌주식솔루션증권모투자신탁(주식-재간접형) | H5: 계정코드 | J5: 1792100 | L5: 미수외국납부원천세환급액 | M5: 0 | N5: 0 | O5: 0 | P5: 0 | Q5: 16165030 | R5: 16165030 | S5: 0 | T5: 0 | U5: 5396698880 | V5: 1293.33 | AA5: 0 | AB5: 0 | AC5: 0 | AD5: 0 | AE5: 0 | AF5: 신한은행 | AG5: 0 | AI5: 0.3 | AJ5: 0.3
A6: 5 | B6: 국내 | C6: 45348 | D6: 현금 | E6: 정지영 | F6: 03V95 | G6: 한국투자글로벌주식솔루션증권모투자신탁(주식-재간접형) | H6: 보통예금 | I6: 공통 | J6: KR9999990000 | L6: 예금 | M6: 48609544 | N6: 48609544 | O6: 0 | P6: 0 | Q6: 48806859 | R6: 48806859 | S6: 0 | T6: 197315 | U6: 5396698880 | V6: 1293.33 | Y6: 만기일시 | AA6: 2.97792 | AB6: 2.99 | AC6: 0 | AD6: 2.99 | AE6: 0 | AF6: 신한은행 | AG6: 0 | AI6: 0.9 | AJ6: 0.9
A7: 6 | B7: 국내 | C7: 45348 | D7: 선물매도 | E7: 민상구 | F7: 05C02 | G7: 한국투자TDF알아서증권투자신탁(채권혼합-재간접형)(모) | H7: 달러선물 | I7: N/A | J7: KR4175V30009 | L7: 미국달러 F 202403 | M7: 760 | N7: 10098880000 | O7: 1330.5 | P7: -12920000 | Q7: 0 | R7: 10111800000 | S7: 0 | T7: 0 | U7: 177518001444 | V7: 1267.23 | W7: 44271 | X7: 45369 | Y7: N/A | Z7: 0000-01-01 | AA7: 0 | AB7: 0 | AC7: 0 | AD7: 0 | AE7: 0 | AF7: 우리은행 | AG7: 0 | AH7: N/A | AI7: 5.26 | AJ7: 5.7
A8: 7 | B8: 국내 | C8: 45348 | D8: 선물매도 | E8: 민상구 | F8: 05C02 | G8: 한국투자TDF알아서증권투자신탁(채권혼합-재간접형)(모) | H8: 달러선물 | I8: N/A | J8: KR4175V30009 | L8: 미국달러 F 202403 | M8: 230 | N8: 3056240000 | O8: 1330.5 | P8: -3910000 | Q8: 0 | R8: 3060150000 | S8: 0 | T8: 0 | U8: 177518001444 | V8: 1267.23 | W8: 44271 | X8: 45369 | Y8: N/A | Z8: 0000-01-01 | AA8: 0 | AB8: 0 | AC8: 0 | AD8: 0 | AE8: 0 | AF8: 우리은행 | AG8: 0 | AH8: N/A | AI8: 1.59 | AJ8: 1.72
A9: 8 | B9: 국내 | C9: 45348 | D9: 주식 | E9: 민상구 | F9: 05C02 | G9: 한국투자TDF알아서증권투자신탁(채권혼합-재간접형)(모) | H9: ETF(거래소)(채권) | I9: 한국투자KINDEXKIS종합채권(AA- | J9: KR7356540005 | L9: ACE 종합채권(AA-이상)KIS액티브 | M9: 112474 | N9: 10439078724 | O9: 100030 | P9: 811695496 | Q9: 10439078724 | R9: 11250774220 | S9: 0 | T9: 0 | U9: 177518001444 | V9: 1267.23 | AA9: 0 | AB9: 0 | AC9: 0 | AD9: 0 | AE9: 7.78 | AF9: 우리은행 | AG9: 0 | AI9: 5.86 | AJ9: 6.34
A10: 9 | B10: 국내 | C10: 45348 | D10: 현금 | E10: 민상구 | F10: 05C02 | G10: 한국투자TDF알아서증권투자신탁(채권혼합-재간접형)(모) | H10: 보통예금 | I10: 공통 | J10: KR9999990000 | L10: 예금 | M10: 2806116755 | N10: 2806116755 | O10: 0 | P10: 0 | Q10: 2810933720 | R10: 2810933720 | S10: 0 | T10: 4816965 | U10: 177518001444 | V10: 1267.23 | Y10: 만기일시 | AA10: 2.98488 | AB10: 2.99 | AC10: 0 | AD10: 2.99 | AE10: 0 | AF10: 우리은행 | AG10: 0 | AI10: 1.46 | AJ10: 1.58
A11: 10 | B11: 국내 | C11: 45348 | D11: 현금 | E11: 민상구 | F11: 05C02 | G11: 한국투자TDF알아서증권투자신탁(채권혼합-재간접형)(모) | H11: 콜론 | I11: 한국증권금융 | J11: KR9E22680009 | L11: 증권금융(콜론) | M11: 1586980000 | N11: 1586980000 | O11: 0 | P11: 0 | Q11: 1587131307 | R11: 1587131307 | S11: 0 | T11: 151307 | U11: 177518001444 | V11: 1267.23 | W11: 45348 | X11: 45349 | Y11: 만기일시 | AA11: 3.47968 | AB11: 3.48 | AC11: 0 | AD11: 3.48 | AE11: 0 | AF11: 우리은행 | AG11: 0 | AI11: 0.83 | AJ11: 0.89
A12: 11 | B12: 국내 | C12: 45348 | D12: 현금 | E12: 민상구 | F12: 05C02 | G12: 한국투자TDF알아서증권투자신탁(채권혼합-재간접형)(모) | H12: 콜론 | I12: 삼성증권 | J12: KR9E22680023 | L12: 삼성증권(콜론) | M12: 1102640000 | N12: 1102640000 | O12: 0 | P12: 0 | Q12: 1102750868 | R12: 1102750868 | S12: 0 | T12: 110868 | U12: 177518001444 | V12: 1267.23 | W12: 45348 | X12: 45349 | Y12: 만기일시 | AA12: 3.66962 | AB12: 3.67 | AC12: 0 | AD12: 3.67 | AE12: 0 | AF12: 우리은행 | AG12: 0 | AI12: 0.57 | AJ12: 0.62
A13: 12 | B13: 국내 | C13: 45348 | D13: 현금 | E13: 민상구 | F13: 05C02 | G13: 한국투자TDF알아서증권투자신탁(채권혼합-재간접형)(모) | H13: 현금위탁증거금 | I13: 신한투자증권 | J13: 000002000000 | L13: 신한금융투자(증거금) | M13: 146271140 | N13: 146271140 | O13: 0 | P13: 0 | Q13: 146271140 | R13: 146271140 | S13: 0 | T13: 0 | U13: 177518001444 | V13: 1267.23 | Y13: 만기일시 | AA13: 0 | AB13: 0 | AC13: 0 | AD13: 0 | AE13: 0 | AF13: 우리은행 | AG13: 0 | AI13: 0.08 | AJ13: 0.08
A14: 13 | B14: 국내 | C14: 45348 | D14: 현금 | E14: 민상구 | F14: 05C02 | G14: 한국투자TDF알아서증권투자신탁(채권혼합-재간접형)(모) | H14: 현금위탁증거금 | I14: 한국투자증권 | J14: 000003000000 | L14: 한국투자증권(증거금) | M14: 470375400 | N14: 470375400 | O14: 0 | P14: 0 | Q14: 470375400 | R14: 470375400 | S14: 0 | T14: 0 | U14: 177518001444 | V14: 1267.23 | Y14: 만기일시 | AA14: 0 | AB14: 0 | AC14: 0 | AD14: 0 | AE14: 0 | AF14: 우리은행 | AG14: 0 | AI14: 0.25 | AJ14: 0.26
A15: 14 | B15: 국내 | C15: 45348 | D15: 기타자산 | E15: 민상구 | F15: 05C03 | G15: 한국투자TDF알아서증권투자신탁(채권혼합-재간접형)(A) | H15: 계정코드 | J15: 1711700 | L15: 집합투자증권매도미수금 | M15: 0 | N15: 0 | O15: 0 | P15: 0 | Q15: 0 | R15: 0 | S15: 0 | T15: 0 | U15: 1220059502 | V15: 1243 | AA15: 0 | AB15: 0 | AC15: 0 | AD15: 0 | AE15: 0 | AF15: 우리은행 | AG15: 0 | AI15: 0 | AJ15: 0
A16: 15 | B16: 국내 | C16: 45348 | D16: 집합증권 | E16: 민상구 | F16: 05C03 | G16: 한국투자TDF알아서증권투자신탁(채권혼합-재간접형)(A) | H16: 종류형모펀드 | I16: 한국투자신탁운용 | J16: 032280005C02 | L16: 한국투자TDF알아서증권투자신탁(채권혼합-재간접형)(모) | M16: 962835843 | N16: 1234647262 | O16: 1267.23 | P16: -14512053 | Q16: 1220135209 | R16: 1220135209 | S16: 0 | T16: 0 | U16: 1220059502 | V16: 1243 | W16: 42788 | X16: 0000-01-01 | Y16: N/A | Z16: 45343 | AA16: 0 | AB16: 0 | AC16: 0 | AD16: 0 | AE16: 0 | AF16: 우리은행 | AG16: 0 | AH16: N/A | AI16: 100 | AJ16: 100.01
A17: 16 | B17: 국내 | C17: 45348 | D17: 현금 | E17: 민상구 | F17: 05C03 | G17: 한국투자TDF알아서증권투자신탁(채권혼합-재간접형)(A) | H17: 보통예금 | I17: 공통 | J17: KR9999990000 | L17: 예금 | M17: 0 | N17: 0 | O17: 0 | P17: 0 | Q17: 0 | R17: 0 | S17: 0 | T17: 0 | U17: 1220059502 | V17: 1243 | Y17: 만기일시 | AA17: 0 | AB17: 2.99 | AC17: 0 | AD17: 2.99 | AE17: 0 | AF17: 우리은행 | AG17: 0 | AI17: 0 | AJ17: 0
A18: 17 | B18: 국내 | C18: 45348 | D18: 기타자산 | E18: 민상구 | F18: 05C04 | G18: 한국투자TDF알아서증권투자신탁(채권혼합-재간접형)(A-e) | H18: 계정코드 | J18: 1711700 | L18: 집합투자증권매도미수금 | M18: 0 | N18: 0 | O18: 0 | P18: 0 | Q18: 5322875 | R18: 5322875 | S18: 0 | T18: 0 | U18: 540990684 | V18: 1200.74 | AA18: 0 | AB18: 0 | AC18: 0 | AD18: 0 | AE18: 0 | AF18: 우리은행 | AG18: 0 | AI18: 0.97 | AJ18: 0.98
A19: 18 | B19: 국내 | C19: 45348 | D19: 집합증권 | E19: 민상구 | F19: 05C04 | G19: 한국투자TDF알아서증권투자신탁(채권혼합-재간접형)(A-e) | H19: 종류형모펀드 | I19: 한국투자신탁운용 | J19: 032280005C02 | L19: 한국투자TDF알아서증권투자신탁(채권혼합-재간접형)(모) | M19: 426928443 | N19: 534907748 | O19: 1267.23 | P19: 6109113 | Q19: 541016861 | R19: 541016861 | S19: 0 | T19: 0 | U19: 540990684 | V19: 1200.74 | W19: 42788 | X19: 0000-01-01 | Y19: N/A | Z19: 45343 | AA19: 0 | AB19: 0 | AC19: 0 | AD19: 0 | AE19: 0 | AF19: 우리은행 | AG19: 0 | AH19: N/A | AI19: 99.03 | AJ19: 100
A20: 19 | B20: 국내 | C20: 45348 | D20: 현금 | E20: 민상구 | F20: 05C04 | G20: 한국투자TDF알아서증권투자신탁(채권혼합-재간접형)(A-e) | H20: 보통예금 | I20: 공통 | J20: KR9999990000 | L20: 예금 | M20: 0 | N20: 0 | O20: 0 | P20: 0 | Q20: 0 | R20: 0 | S20: 0 | T20: 0 | U20: 540990684 | V20: 1200.74 | Y20: 만기일시 | AA20: 0 | AB20: 2.99 | AC20: 0 | AD20: 2.99 | AE20: 0 | AF20: 우리은행 | AG20: 0 | AI20: 0 | AJ20: 0
A21: 20 | B21: 국내 | C21: 45348 | D21: 집합증권 | E21: 민상구 | F21: 05C05 | G21: 한국투자TDF알아서증권투자신탁(채권혼합-재간접형)(C) | H21: 종류형모펀드 | I21: 한국투자신탁운용 | J21: 032280005C02 | L21: 한국투자TDF알아서증권투자신탁(채권혼합-재간접형)(모) | M21: 395631498 | N21: 508674973 | O21: 1267.23 | P21: -7318564 | Q21: 501356409 | R21: 501356409 | S21: 0 | T21: 0 | U21: 501302206 | V21: 1173.67 | W21: 42788 | X21: 0000-01-01 | Y21: N/A | Z21: 45343 | AA21: 0 | AB21: 0 | AC21: 0 | AD21: 0 | AE21: 0 | AF21: 우리은행 | AG21: 0 | AH21: N/A | AI21: 100 | AJ21: 100.01
A22: 21 | B22: 국내 | C22: 45348 | D22: 현금 | E22: 민상구 | F22: 05C05 | G22: 한국투자TDF알아서증권투자신탁(채권혼합-재간접형)(C) | H22: 보통예금 | I22: 공통 | J22: KR9999990000 | L22: 예금 | M22: 0 | N22: 0 | O22: 0 | P22: 0 | Q22: 0 | R22: 0 | S22: 0 | T22: 0 | U22: 501302206 | V22: 1173.67 | Y22: 만기일시 | AA22: 0 | AB22: 2.99 | AC22: 0 | AD22: 2.99 | AE22: 0 | AF22: 우리은행 | AG22: 0 | AI22: 0 | AJ22: 0
A23: 22 | B23: 국내 | C23: 45348 | D23: 집합증권 | E23: 민상구 | F23: 05C06 | G23: 한국투자TDF알아서증권투자신탁(채권혼합-재간접형)(C-e) | H23: 종류형모펀드 | I23: 한국투자신탁운용 | J23: 032280005C02 | L23: 한국투자TDF알아서증권투자신탁(채권혼합-재간접형)(모) | M23: 310918297 | N23: 394318627 | O23: 1267.23 | P23: -313393 | Q23: 394005234 | R23: 394005234 | S23: 0 | T23: 0 | U23: 393977063 | V23: 1202.75 | W23: 42788 | X23: 0000-01-01 | Y23: N/A | Z23: 45343 | AA23: 0 | AB23: 0 | AC23: 0 | AD23: 0 | AE23: 0 | AF23: 우리은행 | AG23: 0 | AH23: N/A | AI23: 100 | AJ23: 100.01
A24: 23 | B24: 국내 | C24: 45348 | D24: 현금 | E24: 민상구 | F24: 05C06 | G24: 한국투자TDF알아서증권투자신탁(채권혼합-재간접형)(C-e) | H24: 보통예금 | I24: 공통 | J24: KR9999990000 | L24: 예금 | M24: 0 | N24: 0 | O24: 0 | P24: 0 | Q24: 0 | R24: 0 | S24: 0 | T24: 0 | U24: 393977063 | V24: 1202.75 | Y24: 만기일시 | AA24: 0 | AB24: 2.99 | AC24: 0 | AD24: 2.99 | AE24: 0 | AF24: 우리은행 | AG24: 0 | AI24: 0 | AJ24: 0
A25: 24 | B25: 국내 | C25: 45348 | D25: 기타자산 | E25: 민상구 | F25: 05C08 | G25: 한국투자TDF알아서증권투자신탁(채권혼합-재간접형)(C-P) | H25: 계정코드 | J25: 1711700 | L25: 집합투자증권매도미수금 | M25: 0 | N25: 0 | O25: 0 | P25: 0 | Q25: 193495923 | R25: 193495923 | S25: 0 | T25: 0 | U25: 25668361919 | V25: 1223.62 | AA25: 0 | AB25: 0 | AC25: 0 | AD25: 0 | AE25: 0 | AF25: 우리은행 | AG25: 0 | AI25: 0.75 | AJ25: 0.75
A26: 25 | B26: 국내 | C26: 45348 | D26: 집합증권 | E26: 민상구 | F26: 05C08 | G26: 한국투자TDF알아서증권투자신탁(채권혼합-재간접형)(C-P) | H26: 종류형모펀드 | I26: 한국투자신탁운용 | J26: 032280005C02 | L26: 한국투자TDF알아서증권투자신탁(채권혼합-재간접형)(모) | M26: 20257535212 | N26: 24133405039 | O26: 1267.23 | P26: 1537566963 | Q26: 25670972002 | R26: 25670972002 | S26: 0 | T26: 0 | U26: 25668361919 | V26: 1223.62 | W26: 42788 | X26: 0000-01-01 | Y26: N/A | Z26: 45343 | AA26: 0 | AB26: 0 | AC26: 0 | AD26: 0 | AE26: 0 | AF26: 우리은행 | AG26: 0 | AH26: N/A | AI26: 99.25 | AJ26: 100.01
A27: 26 | B27: 국내 | C27: 45348 | D27: 현금 | E27: 민상구 | F27: 05C08 | G27: 한국투자TDF알아서증권투자신탁(채권혼합-재간접형)(C-P) | H27: 보통예금 | I27: 공통 | J27: KR9999990000 | L27: 예금 | M27: 0 | N27: 0 | O27: 0 | P27: 0 | Q27: 0 | R27: 0 | S27: 0 | T27: 0 | U27: 25668361919 | V27: 1223.62 | Y27: 만기일시 | AA27: 0 | AB27: 2.99 | AC27: 0 | AD27: 2.99 | AE27: 0 | AF27: 우리은행 | AG27: 0 | AI27: 0 | AJ27: 0
A28: 27 | B28: 국내 | C28: 45348 | D28: 기타자산 | E28: 민상구 | F28: 05C09 | G28: 한국투자TDF알아서증권투자신탁(채권혼합-재간접형)(C-R) | H28: 계정코드 | J28: 1711700 | L28: 집합투자증권매도미수금 | M28: 0 | N28: 0 | O28: 0 | P28: 0 | Q28: 850735150 | R28: 850735150 | S28: 0 | T28: 0 | U28: 97314544246 | V28: 1230.87 | AA28: 0 | AB28: 0 | AC28: 0 | AD28: 0 | AE28: 0 | AF28: 우리은행 | AG28: 0 | AI28: 0.87 | AJ28: 0.87
A29: 28 | B29: 국내 | C29: 45348 | D29: 집합증권 | E29: 민상구 | F29: 05C09 | G29: 한국투자TDF알아서증권투자신탁(채권혼합-재간접형)(C-R) | H29: 종류형모펀드 | I29: 한국투자신탁운용 | J29: 032280005C02 | L29: 한국투자TDF알아서증권투자신탁(채권혼합-재간접형)(모) | M29: 76799834342 | N29: 92673428957 | O29: 1267.23 | P29: 4649684467 | Q29: 97323113424 | R29: 97323113424 | S29: 0 | T29: 0 | U29: 97314544246 | V29: 1230.87 | W29: 42788 | X29: 0000-01-01 | Y29: N/A | Z29: 45343 | AA29: 0 | AB29: 0 | AC29: 0 | AD29: 0 | AE29: 0 | AF29: 우리은행 | AG29: 0 | AH29: N/A | AI29: 99.13 | AJ29: 100.01
A30: 29 | B30: 국내 | C30: 45348 | D30: 현금 | E30: 민상구 | F30: 05C09 | G30: 한국투자TDF알아서증권투자신탁(채권혼합-재간접형)(C-R) | H30: 보통예금 | I30: 공통 | J30: KR9999990000 | L30: 예금 | M30: 0 | N30: 0 | O30: 0 | P30: 0 | Q30: 0 | R30: 0 | S30: 0 | T30: 0 | U30: 97314544246 | V30: 1230.87 | Y30: 만기일시 | AA30: 0 | AB30: 2.99 | AC30: 0 | AD30: 2.99 | AE30: 0 | AF30: 우리은행 | AG30: 0 | AI30: 0 | AJ30: 0
A31: 30 | B31: 국내 | C31: 45348 | D31: 집합증권 | E31: 민상구 | F31: 05C11 | G31: 한국투자TDF알아서증권투자신탁(채권혼합-재간접형)(C-W) | H31: 종류형모펀드 | I31: 한국투자신탁운용 | J31: 032280005C02 | L31: 한국투자TDF알아서증권투자신탁(채권혼합-재간접형)(모) | M31: 253446 | N31: 312697 | O31: 1267.23 | P31: 8478 | Q31: 321175 | R31: 321175 | S31: 0 | T31: 0 | U31: 321170 | V31: 1191.91 | W31: 42788 | X31: 0000-01-01 | Y31: N/A | Z31: 45343 | AA31: 0 | AB31: 0 | AC31: 0 | AD31: 0 | AE31: 0 | AF31: 우리은행 | AG31: 0 | AH31: N/A | AI31: 100 | AJ31: 100
A32: 31 | B32: 국내 | C32: 45348 | D32: 현금 | E32: 민상구 | F32: 05C11 | G32: 한국투자TDF알아서증권투자신탁(채권혼합-재간접형)(C-W) | H32: 보통예금 | I32: 공통 | J32: KR9999990000 | L32: 예금 | M32: 0 | N32: 0 | O32: 0 | P32: 0 | Q32: 0 | R32: 0 | S32: 0 | T32: 0 | U32: 321170 | V32: 1191.91 | Y32: 만기일시 | AA32: 0 | AB32: 2.99 | AC32: 0 | AD32: 2.99 | AE32: 0 | AF32: 우리은행 | AG32: 0 | AI32: 0 | AJ32: 0
A33: 32 | B33: 국내 | C33: 45348 | D33: 집합증권 | E33: 민상구 | F33: 05C12 | G33: 한국투자TDF알아서증권투자신탁(채권혼합-재간접형)(S) | H33: 종류형모펀드 | I33: 한국투자신탁운용 | J33: 032280005C02 | L33: 한국투자TDF알아서증권투자신탁(채권혼합-재간접형)(모) | M33: 36487051 | N33: 47267485 | O33: 1267.23 | P33: -1029971 | Q33: 46237514 | R33: 46237514 | S33: 0 | T33: 0 | U33: 46235417 | V33: 1167.64 | W33: 42788 | X33: 0000-01-01 | Y33: N/A | Z33: 45343 | AA33: 0 | AB33: 0 | AC33: 0 | AD33: 0 | AE33: 0 | AF33: 우리은행 | AG33: 0 | AH33: N/A | AI33: 100 | AJ33: 100
A34: 33 | B34: 국내 | C34: 45348 | D34: 현금 | E34: 민상구 | F34: 05C12 | G34: 한국투자TDF알아서증권투자신탁(채권혼합-재간접형)(S) | H34: 보통예금 | I34: 공통 | J34: KR9999990000 | L34: 예금 | M34: 0 | N34: 0 | O34: 0 | P34: 0 | Q34: 0 | R34: 0 | S34: 0 | T34: 0 | U34: 46235417 | V34: 1167.64 | Y34: 만기일시 | AA34: 0 | AB34: 2.99 | AC34: 0 | AD34: 2.99 | AE34: 0 | AF34: 우리은행 | AG34: 0 | AI34: 0 | AJ34: 0
A35: 34 | B35: 국내 | C35: 45348 | D35: 집합증권 | E35: 민상구 | F35: 05C13 | G35: 한국투자TDF알아서증권투자신탁(채권혼합-재간접형)(S-P) | H35: 종류형모펀드 | I35: 한국투자신탁운용 | J35: 032280005C02 | L35: 한국투자TDF알아서증권투자신탁(채권혼합-재간접형)(모) | M35: 150612470 | N35: 190390489 | O35: 1267.23 | P35: 470268 | Q35: 190860757 | R35: 190860757 | S35: 0 | T35: 0 | U35: 190852061 | V35: 1190.1 | W35: 42788 | X35: 0000-01-01 | Y35: N/A | Z35: 45343 | AA35: 0 | AB35: 0 | AC35: 0 | AD35: 0 | AE35: 0 | AF35: 우리은행 | AG35: 0 | AH35: N/A | AI35: 100 | AJ35: 100
A36: 35 | B36: 국내 | C36: 45348 | D36: 현금 | E36: 민상구 | F36: 05C13 | G36: 한국투자TDF알아서증권투자신탁(채권혼합-재간접형)(S-P) | H36: 보통예금 | I36: 공통 | J36: KR9999990000 | L36: 예금 | M36: 0 | N36: 0 | O36: 0 | P36: 0 | Q36: 0 | R36: 0 | S36: 0 | T36: 0 | U36: 190852061 | V36: 1190.1 | Y36: 만기일시 | AA36: 0 | AB36: 2.99 | AC36: 0 | AD36: 2.99 | AE36: 0 | AF36: 우리은행 | AG36: 0 | AI36: 0 | AJ36: 0
A37: 36 | B37: 국내 | C37: 45348 | D37: 주식 | E37: 민상구 | F37: 05C14 | G37: 한국투자TDF알아서2020증권모투자신탁(채권혼합-재간접형) | H37: ETF(거래소)(채권) | I37: 한국투자KINDEXKIS종합채권(AA- | J37: KR7356540005 | L37: ACE 종합채권(AA-이상)KIS액티브 | M37: 47190 | N37: 4386937817 | O37: 100030 | P37: 333477883 | Q37: 4386937817 | R37: 4720415700 | S37: 0 | T37: 0 | U37: 79799550687 | V37: 1254.34 | AA37: 0 | AB37: 0 | AC37: 0 | AD37: 0 | AE37: 7.6 | AF37: 우리은행 | AG37: 0 | AI37: 5.88 | AJ37: 5.92
A38: 37 | B38: 국내 | C38: 45348 | D38: 현금 | E38: 민상구 | F38: 05C14 | G38: 한국투자TDF알아서2020증권모투자신탁(채권혼합-재간접형) | H38: 보통예금 | I38: 공통 | J38: KR9999990000 | L38: 예금 | M38: 848972461 | N38: 848972461 | O38: 0 | P38: 0 | Q38: 850729617 | R38: 850729617 | S38: 0 | T38: 1757156 | U38: 79799550687 | V38: 1254.34 | Y38: 만기일시 | AA38: 2.98383 | AB38: 2.99 | AC38: 0 | AD38: 2.99 | AE38: 0 | AF38: 우리은행 | AG38: 0 | AI38: 1.06 | AJ38: 1.07
A39: 38 | B39: 국내 | C39: 45348 | D39: 현금 | E39: 민상구 | F39: 05C14 | G39: 한국투자TDF알아서2020증권모투자신탁(채권혼합-재간접형) | H39: 콜론 | I39: 한국증권금융 | J39: KR9E22680009 | L39: 증권금융(콜론) | M39: 480140000 | N39: 480140000 | O39: 0 | P39: 0 | Q39: 480185778 | R39: 480185778 | S39: 0 | T39: 45778 | U39: 79799550687 | V39: 1254.34 | W39: 45348 | X39: 45349 | Y39: 만기일시 | AA39: 3.47969 | AB39: 3.48 | AC39: 0 | AD39: 3.48 | AE39: 0 | AF39: 우리은행 | AG39: 0 | AI39: 0.6 | AJ39: 0.6
A40: 39 | B40: 국내 | C40: 45348 | D40: 현금 | E40: 민상구 | F40: 05C14 | G40: 한국투자TDF알아서2020증권모투자신탁(채권혼합-재간접형) | H40: 콜론 | I40: 삼성증권 | J40: KR9E22680023 | L40: 삼성증권(콜론) | M40: 333600000 | N40: 333600000 | O40: 0 | P40: 0 | Q40: 333633543 | R40: 333633543 | S40: 0 | T40: 33543 | U40: 79799550687 | V40: 1254.34 | W40: 45348 | X40: 45349 | Y40: 만기일시 | AA40: 3.66965 | AB40: 3.67 | AC40: 0 | AD40: 3.67 | AE40: 0 | AF40: 우리은행 | AG40: 0 | AI40: 0.42 | AJ40: 0.42
A41: 40 | B41: 국내 | C41: 45348 | D41: 기타자산 | E41: 민상구 | F41: 05C16 | G41: 한국투자TDF알아서2020증권자투자신탁(채권혼합-재간접형)(모) | H41: 계정코드 | J41: 1711700 | L41: 집합투자증권매도미수금 | M41: 0 | N41: 0 | O41: 0 | P41: 0 | Q41: 319538526 | R41: 319538526 | S41: 0 | T41: 0 | U41: 63578570895 | V41: 1329.98 | AA41: 0 | AB41: 0 | AC41: 0 | AD41: 0 | AE41: 0 | AF41: 우리은행 | AG41: 0 | AI41: 0.5 | AJ41: 0.5
A42: 41 | B42: 국내 | C42: 45348 | D42: 집합증권 | E42: 민상구 | F42: 05C16 | G42: 한국투자TDF알아서2020증권자투자신탁(채권혼합-재간접형)(모) | H42: 모펀드 | I42: 한국투자신탁운용 | J42: 032280005C14 | L42: 한국투자TDF알아서2020증권모투자신탁(채권혼합-재간접형) | M42: 50020742275 | N42: 59901510518 | O42: 1254.34 | P42: 2841718552 | Q42: 62743229070 | R42: 62743229070 | S42: 0 | T42: 0 | U42: 63578570895 | V42: 1329.98 | W42: 42954 | X42: 0000-01-01 | Y42: N/A | Z42: 45352 | AA42: 0 | AB42: 0 | AC42: 0 | AD42: 0 | AE42: 0 | AF42: 우리은행 | AG42: 0 | AH42: N/A | AI42: 98.21 | AJ42: 98.69
A43: 42 | B43: 국내 | C43: 45348 | D43: 현금 | E43: 민상구 | F43: 05C16 | G43: 한국투자TDF알아서2020증권자투자신탁(채권혼합-재간접형)(모) | H43: 보통예금 | I43: 공통 | J43: KR9999990000 | L43: 예금 | M43: 421396011 | N43: 421396011 | O43: 0 | P43: 0 | Q43: 422197448 | R43: 422197448 | S43: 0 | T43: 801437 | U43: 63578570895 | V43: 1329.98 | Y43: 만기일시 | AA43: 2.98434 | AB43: 2.99 | AC43: 0 | AD43: 2.99 | AE43: 0 | AF43: 우리은행 | AG43: 0 | AI43: 0.66 | AJ43: 0.66
A44: 43 | B44: 국내 | C44: 45348 | D44: 현금 | E44: 민상구 | F44: 05C16 | G44: 한국투자TDF알아서2020증권자투자신탁(채권혼합-재간접형)(모) | H44: 콜론 | I44: 한국증권금융 | J44: KR9E22680009 | L44: 증권금융(콜론) | M44: 238320000 | N44: 238320000 | O44: 0 | P44: 0 | Q44: 238342722 | R44: 238342722 | S44: 0 | T44: 22722 | U44: 63578570895 | V44: 1329.98 | W44: 45348 | X44: 45349 | Y44: 만기일시 | AA44: 3.47967 | AB44: 3.48 | AC44: 0 | AD44: 3.48 | AE44: 0 | AF44: 우리은행 | AG44: 0 | AI44: 0.37 | AJ44: 0.37
A45: 44 | B45: 국내 | C45: 45348 | D45: 현금 | E45: 민상구 | F45: 05C16 | G45: 한국투자TDF알아서2020증권자투자신탁(채권혼합-재간접형)(모) | H45: 콜론 | I45: 삼성증권 | J45: KR9E22680023 | L45: 삼성증권(콜론) | M45: 165590000 | N45: 165590000 | O45: 0 | P45: 0 | Q45: 165606650 | R45: 165606650 | S45: 0 | T45: 16650 | U45: 63578570895 | V45: 1329.98 | W45: 45348 | X45: 45349 | Y45: 만기일시 | AA45: 3.66969 | AB45: 3.67 | AC45: 0 | AD45: 3.67 | AE45: 0 | AF45: 우리은행 | AG45: 0 | AI45: 0.26 | AJ45: 0.26
A46: 45 | B46: 국내 | C46: 45348 | D46: 집합증권 | E46: 민상구 | F46: 05C17 | G46: 한국투자TDF알아서2020증권자투자신탁(채권혼합-재간접형)(A) | H46: 종류형모펀드 | I46: 한국투자신탁운용 | J46: 032280005C16 | L46: 한국투자TDF알아서2020증권자투자신탁(채권혼합-재간접형)(모) | M46: 74532283 | N46: 99198239 | O46: 1329.98 | P46: -71902 | Q46: 99126337 | R46: 99126337 | S46: 0 | T46: 0 | U46: 99025790 | V46: 1303.52 | W46: 42796 | X46: 0000-01-01 | Y46: N/A | Z46: 45352 | AA46: 0 | AB46: 0 | AC46: 0 | AD46: 0 | AE46: 0 | AF46: 우리은행 | AG46: 0 | AH46: N/A | AI46: 100 | AJ46: 100.1
A47: 46 | B47: 국내 | C47: 45348 | D47: 현금 | E47: 민상구 | F47: 05C17 | G47: 한국투자TDF알아서2020증권자투자신탁(채권혼합-재간접형)(A) | H47: 보통예금 | I47: 공통 | J47: KR9999990000 | L47: 예금 | M47: 0 | N47: 0 | O47: 0 | P47: 0 | Q47: 0 | R47: 0 | S47: 0 | T47: 0 | U47: 99025790 | V47: 1303.52 | Y47: 만기일시 | AA47: 0 | AB47: 2.99 | AC47: 0 | AD47: 2.99 | AE47: 0 | AF47: 우리은행 | AG47: 0 | AI47: 0 | AJ47: 0
A48: 47 | B48: 국내 | C48: 45348 | D48: 기타자산 | E48: 민상구 | F48: 05C18 | G48: 한국투자TDF알아서2020증권자투자신탁(채권혼합-재간접형)(A-e) | H48: 계정코드 | J48: 1711700 | L48: 집합투자증권매도미수금 | M48: 0 | N48: 0 | O48: 0 | P48: 0 | Q48: 954686 | R48: 954686 | S48: 0 | T48: 0 | U48: 66882770 | V48: 1244.06 | AA48: 0 | AB48: 0 | AC48: 0 | AD48: 0 | AE48: 0 | AF48: 우리은행 | AG48: 0 | AI48: 1.41 | AJ48: 1.43
A49: 48 | B49: 국내 | C49: 45348 | D49: 집합증권 | E49: 민상구 | F49: 05C18 | G49: 한국투자TDF알아서2020증권자투자신탁(채권혼합-재간접형)(A-e) | H49: 종류형모펀드 | I49: 한국투자신탁운용 | J49: 032280005C16 | L49: 한국투자TDF알아서2020증권자투자신탁(채권혼합-재간접형)(모) | M49: 50328026 | N49: 66392558 | O49: 1329.98 | P49: 542636 | Q49: 66935194 | R49: 66935194 | S49: 0 | T49: 0 | U49: 66882770 | V49: 1244.06 | W49: 42796 | X49: 0000-01-01 | Y49: N/A | Z49: 45352 | AA49: 0 | AB49: 0 | AC49: 0 | AD49: 0 | AE49: 0 | AF49: 우리은행 | AG49: 0 | AH49: N/A | AI49: 98.59 | AJ49: 100.08
A50: 49 | B50: 국내 | C50: 45348 | D50: 현금 | E50: 민상구 | F50: 05C18 | G50: 한국투자TDF알아서2020증권자투자신탁(채권혼합-재간접형)(A-e) | H50: 보통예금 | I50: 공통 | J50: KR9999990000 | L50: 예금 | M50: 0 | N50: 0 | O50: 0 | P50: 0 | Q50: 0 | R50: 0 | S50: 0 | T50: 0 | U50: 66882770 | V50: 1244.06 | Y50: 만기일시 | AA50: 0 | AB50: 2.99 | AC50: 0 | AD50: 2.99 | AE50: 0 | AF50: 우리은행 | AG50: 0 | AI50: 0 | AJ50: 0
A51: 50 | B51: 국내 | C51: 45348 | D51: 집합증권 | E51: 민상구 | F51: 05C19 | G51: 한국투자TDF알아서2020증권자투자신탁(채권혼합-재간접형)(C) | H51: 종류형모펀드 | I51: 한국투자신탁운용 | J51: 032280005C16 | L51: 한국투자TDF알아서2020증권자투자신탁(채권혼합-재간접형)(모) | M51: 20491258 | N51: 27235430 | O51: 1329.98 | P51: 17503 | Q51: 27252933 | R51: 27252933 | S51: 0 | T51: 0 | U51: 27203187 | V51: 1231.29 | W51: 42796 | X51: 0000-01-01 | Y51: N/A | Z51: 45352 | AA51: 0 | AB51: 0 | AC51: 0 | AD51: 0 | AE51: 0 | AF51: 우리은행 | AG51: 0 | AH51: N/A | AI51: 100 | AJ51: 100.18
A52: 51 | B52: 국내 | C52: 45348 | D52: 현금 | E52: 민상구 | F52: 05C19 | G52: 한국투자TDF알아서2020증권자투자신탁(채권혼합-재간접형)(C) | H52: 보통예금 | I52: 공통 | J52: KR9999990000 | L52: 예금 | M52: 0 | N52: 0 | O52: 0 | P52: 0 | Q52: 0 | R52: 0 | S52: 0 | T52: 0 | U52: 27203187 | V52: 1231.29 | Y52: 만기일시 | AA52: 0 | AB52: 2.99 | AC52: 0 | AD52: 2.99 | AE52: 0 | AF52: 우리은행 | AG52: 0 | AI52: 0 | AJ52: 0
A53: 52 | B53: 국내 | C53: 45348 | D53: 기타자산 | E53: 민상구 | F53: 05C20 | G53: 한국투자TDF알아서2020증권자투자신탁(채권혼합-재간접형)(C-e) | H53: 계정코드 | J53: 1711700 | L53: 집합투자증권매도미수금 | M53: 0 | N53: 0 | O53: 0 | P53: 0 | Q53: 0 | R53: 0 | S53: 0 | T53: 0 | U53: 107846403 | V53: 1231.1 | AA53: 0 | AB53: 0 | AC53: 0 | AD53: 0 | AE53: 0 | AF53: 우리은행 | AG53: 0 | AI53: 0 | AJ53: 0
A54: 53 | B54: 국내 | C54: 45348 | D54: 집합증권 | E54: 민상구 | F54: 05C20 | G54: 한국투자TDF알아서2020증권자투자신탁(채권혼합-재간접형)(C-e) | H54: 종류형모펀드 | I54: 한국투자신탁운용 | J54: 032280005C16 | L54: 한국투자TDF알아서2020증권자투자신탁(채권혼합-재간접형)(모) | M54: 81183362 | N54: 103614149 | O54: 1329.98 | P54: 4357980 | Q54: 107972129 | R54: 107972129 | S54: 0 | T54: 0 | U54: 107846403 | V54: 1231.1 | W54: 42796 | X54: 0000-01-01 | Y54: N/A | Z54: 45352 | AA54: 0 | AB54: 0 | AC54: 0 | AD54: 0 | AE54: 0 | AF54: 우리은행 | AG54: 0 | AH54: N/A | AI54: 100 | AJ54: 100.12
A55: 54 | B55: 국내 | C55: 45348 | D55: 현금 | E55: 민상구 | F55: 05C20 | G55: 한국투자TDF알아서2020증권자투자신탁(채권혼합-재간접형)(C-e) | H55: 보통예금 | I55: 공통 | J55: KR9999990000 | L55: 예금 | M55: 0 | N55: 0 | O55: 0 | P55: 0 | Q55: 0 | R55: 0 | S55: 0 | T55: 0 | U55: 107846403 | V55: 1231.1 | Y55: 만기일시 | AA55: 0 | AB55: 2.99 | AC55: 0 | AD55: 2.99 | AE55: 0 | AF55: 우리은행 | AG55: 0 | AI55: 0 | AJ55: 0
A56: 55 | B56: 국내 | C56: 45348 | D56: 기타자산 | E56: 민상구 | F56: 05C22 | G56: 한국투자TDF알아서2020증권자투자신탁(채권혼합-재간접형)(C-P) | H56: 계정코드 | J56: 1711700 | L56: 집합투자증권매도미수금 | M56: 0 | N56: 0 | O56: 0 | P56: 0 | Q56: 9854676 | R56: 9854676 | S56: 0 | T56: 0 | U56: 10242852876 | V56: 1282.71 | AA56: 0 | AB56: 0 | AC56: 0 | AD56: 0 | AE56: 0 | AF56: 우리은행 | AG56: 0 | AI56: 0.1 | AJ56: 0.1
A57: 56 | B57: 국내 | C57: 45348 | D57: 집합증권 | E57: 민상구 | F57: 05C22 | G57: 한국투자TDF알아서2020증권자투자신탁(채권혼합-재간접형)(C-P) | H57: 종류형모펀드 | I57: 한국투자신탁운용 | J57: 032280005C16 | L57: 한국투자TDF알아서2020증권자투자신탁(채권혼합-재간접형)(모) | M57: 7714692853 | N57: 9125738181 | O57: 1329.98 | P57: 1134637742 | Q57: 10260375923 | R57: 10260375923 | S57: 0 | T57: 0 | U57: 10242852876 | V57: 1282.71 | W57: 42796 | X57: 0000-01-01 | Y57: N/A | Z57: 45352 | AA57: 0 | AB57: 0 | AC57: 0 | AD57: 0 | AE57: 0 | AF57: 우리은행 | AG57: 0 | AH57: N/A | AI57: 99.9 | AJ57: 100.17
A58: 57 | B58: 국내 | C58: 45348 | D58: 현금 | E58: 민상구 | F58: 05C22 | G58: 한국투자TDF알아서2020증권자투자신탁(채권혼합-재간접형)(C-P) | H58: 보통예금 | I58: 공통 | J58: KR9999990000 | L58: 예금 | M58: 0 | N58: 0 | O58: 0 | P58: 0 | Q58: 0 | R58: 0 | S58: 0 | T58: 0 | U58: 10242852876 | V58: 1282.71 | Y58: 만기일시 | AA58: 0 | AB58: 2.99 | AC58: 0 | AD58: 2.99 | AE58: 0 | AF58: 우리은행 | AG58: 0 | AI58: 0 | AJ58: 0
A59: 58 | B59: 국내 | C59: 45348 | D59: 기타자산 | E59: 민상구 | F59: 05C23 | G59: 한국투자TDF알아서2020증권자투자신탁(채권혼합-재간접형)(C-R) | H59: 계정코드 | J59: 1711700 | L59: 집합투자증권매도미수금 | M59: 0 | N59: 0 | O59: 0 | P59: 0 | Q59: 88565922 | R59: 88565922 | S59: 0 | T59: 0 | U59: 25559697758 | V59: 1288.33 | AA59: 0 | AB59: 0 | AC59: 0 | AD59: 0 | AE59: 0 | AF59: 우리은행 | AG59: 0 | AI59: 0.34 | AJ59: 0.35
A60: 59 | B60: 국내 | C60: 45348 | D60: 집합증권 | E60: 민상구 | F60: 05C23 | G60: 한국투자TDF알아서2020증권자투자신탁(채권혼합-재간접형)(C-R) | H60: 종류형모펀드 | I60: 한국투자신탁운용 | J60: 032280005C16 | L60: 한국투자TDF알아서2020증권자투자신탁(채권혼합-재간접형)(모) | M60: 19246171872 | N60: 23827859085 | O60: 1329.98 | P60: 1769136445 | Q60: 25596995530 | R60: 25596995530 | S60: 0 | T60: 0 | U60: 25559697758 | V60: 1288.33 | W60: 42796 | X60: 0000-01-01 | Y60: N/A | Z60: 45352 | AA60: 0 | AB60: 0 | AC60: 0 | AD60: 0 | AE60: 0 | AF60: 우리은행 | AG60: 0 | AH60: N/A | AI60: 99.66 | AJ60: 100.15
A61: 60 | B61: 국내 | C61: 45348 | D61: 현금 | E61: 민상구 | F61: 05C23 | G61: 한국투자TDF알아서2020증권자투자신탁(채권혼합-재간접형)(C-R) | H61: 보통예금 | I61: 공통 | J61: KR9999990000 | L61: 예금 | M61: 0 | N61: 0 | O61: 0 | P61: 0 | Q61: 0 | R61: 0 | S61: 0 | T61: 0 | U61: 25559697758 | V61: 1288.33 | Y61: 만기일시 | AA61: 0 | AB61: 2.99 | AC61: 0 | AD61: 2.99 | AE61: 0 | AF61: 우리은행 | AG61: 0 | AI61: 0 | AJ61: 0
A62: 61 | B62: 국내 | C62: 45348 | D62: 집합증권 | E62: 민상구 | F62: 05C25 | G62: 한국투자TDF알아서2020증권자투자신탁(채권혼합-재간접형)(C-W) | H62: 종류형모펀드 | I62: 한국투자신탁운용 | J62: 032280005C16 | L62: 한국투자TDF알아서2020증권자투자신탁(채권혼합-재간접형)(모) | M62: 4770831 | N62: 6197173 | O62: 1329.98 | P62: 147930 | Q62: 6345103 | R62: 6345103 | S62: 0 | T62: 0 | U62: 6343824 | V62: 1181.55 | W62: 42796 | X62: 0000-01-01 | Y62: N/A | Z62: 45352 | AA62: 0 | AB62: 0 | AC62: 0 | AD62: 0 | AE62: 0 | AF62: 우리은행 | AG62: 0 | AH62: N/A | AI62: 100 | AJ62: 100.02
A63: 62 | B63: 국내 | C63: 45348 | D63: 현금 | E63: 민상구 | F63: 05C25 | G63: 한국투자TDF알아서2020증권자투자신탁(채권혼합-재간접형)(C-W) | H63: 보통예금 | I63: 공통 | J63: KR9999990000 | L63: 예금 | M63: 0 | N63: 0 | O63: 0 | P63: 0 | Q63: 0 | R63: 0 | S63: 0 | T63: 0 | U63: 6343824 | V63: 1181.55 | Y63: 만기일시 | AA63: 0 | AB63: 2.99 | AC63: 0 | AD63: 2.99 | AE63: 0 | AF63: 우리은행 | AG63: 0 | AI63: 0 | AJ63: 0
A64: 63 | B64: 국내 | C64: 45348 | D64: 집합증권 | E64: 민상구 | F64: 05C26 | G64: 한국투자TDF알아서2020증권자투자신탁(채권혼합-재간접형)(S) | H64: 종류형모펀드 | I64: 한국투자신탁운용 | J64: 032280005C16 | L64: 한국투자TDF알아서2020증권자투자신탁(채권혼합-재간접형)(모) | M64: 8091 | N64: 10965 | O64: 1329.98 | P64: -204 | Q64: 10761 | R64: 10761 | S64: 0 | T64: 0 | U64: 10761 | V64: 1000.65 | W64: 42796 | X64: 0000-01-01 | Y64: N/A | Z64: 45352 | AA64: 0 | AB64: 0 | AC64: 0 | AD64: 0 | AE64: 0 | AF64: 우리은행 | AG64: 0 | AH64: N/A | AI64: 100 | AJ64: 100
A65: 64 | B65: 국내 | C65: 45348 | D65: 현금 | E65: 민상구 | F65: 05C26 | G65: 한국투자TDF알아서2020증권자투자신탁(채권혼합-재간접형)(S) | H65: 보통예금 | I65: 공통 | J65: KR9999990000 | L65: 예금 | M65: 0 | N65: 0 | O65: 0 | P65: 0 | Q65: 0 | R65: 0 | S65: 0 | T65: 0 | U65: 10761 | V65: 1000.65 | Y65: 만기일시 | AA65: 0 | AB65: 2.99 | AC65: 0 | AD65: 2.99 | AE65: 0 | AF65: 우리은행 | AG65: 0 | AI65: 0 | AJ65: 0
A66: 65 | B66: 국내 | C66: 45348 | D66: 집합증권 | E66: 민상구 | F66: 05C27 | G66: 한국투자TDF알아서2020증권자투자신탁(채권혼합-재간접형)(S-P) | H66: 종류형모펀드 | I66: 한국투자신탁운용 | J66: 032280005C16 | L66: 한국투자TDF알아서2020증권자투자신탁(채권혼합-재간접형)(모) | M66: 28742259 | N66: 37470728 | O66: 1329.98 | P66: 755860 | Q66: 38226588 | R66: 38226588 | S66: 0 | T66: 0 | U66: 38197886 | V66: 1230.89 | W66: 42796 | X66: 0000-01-01 | Y66: N/A | Z66: 45352 | AA66: 0 | AB66: 0 | AC66: 0 | AD66: 0 | AE66: 0 | AF66: 우리은행 | AG66: 0 | AH66: N/A | AI66: 100 | AJ66: 100.08
A67: 66 | B67: 국내 | C67: 45348 | D67: 현금 | E67: 민상구 | F67: 05C27 | G67: 한국투자TDF알아서2020증권자투자신탁(채권혼합-재간접형)(S-P) | H67: 보통예금 | I67: 공통 | J67: KR9999990000 | L67: 예금 | M67: 0 | N67: 0 | O67: 0 | P67: 0 | Q67: 0 | R67: 0 | S67: 0 | T67: 0 | U67: 38197886 | V67: 1230.89 | Y67: 만기일시 | AA67: 0 | AB67: 2.99 | AC67: 0 | AD67: 2.99 | AE67: 0 | AF67: 우리은행 | AG67: 0 | AI67: 0 | AJ67: 0
A68: 67 | B68: 국내 | C68: 45348 | D68: 선물매도 | E68: 민상구 | F68: 05C30 | G68: 한국투자TDF알아서2025증권투자신탁(주식혼합-재간접형)(모) | H68: 달러선물 | I68: N/A | J68: KR4175V30009 | L68: 미국달러 F 202403 | M68: 180 | N68: 2391840000 | O68: 1330.5 | P68: -3060000 | Q68: 0 | R68: 2394900000 | S68: 0 | T68: 0 | U68: 136924705845 | V68: 1363.72 | W68: 44271 | X68: 45369 | Y68: N/A | Z68: 0000-01-01 | AA68: 0 | AB68: 0 | AC68: 0 | AD68: 0 | AE68: 0 | AF68: 우리은행 | AG68: 0 | AH68: N/A | AI68: 1.59 | AJ68: 1.75
A69: 68 | B69: 국내 | C69: 45348 | D69: 선물매도 | E69: 민상구 | F69: 05C30 | G69: 한국투자TDF알아서2025증권투자신탁(주식혼합-재간접형)(모) | H69: 달러선물 | I69: N/A | J69: KR4175V30009 | L69: 미국달러 F 202403 | M69: 692 | N69: 9195296000 | O69: 1330.5 | P69: -11764000 | Q69: 0 | R69: 9207060000 | S69: 0 | T69: 0 | U69: 136924705845 | V69: 1363.72 | W69: 44271 | X69: 45369 | Y69: N/A | Z69: 0000-01-01 | AA69: 0 | AB69: 0 | AC69: 0 | AD69: 0 | AE69: 0 | AF69: 우리은행 | AG69: 0 | AH69: N/A | AI69: 6.1 | AJ69: 6.72
A70: 69 | B70: 국내 | C70: 45348 | D70: 주식 | E70: 민상구 | F70: 05C30 | G70: 한국투자TDF알아서2025증권투자신탁(주식혼합-재간접형)(모) | H70: ETF(거래소)(채권) | I70: 한국투자KINDEXKIS종합채권(AA- | J70: KR7356540005 | L70: ACE 종합채권(AA-이상)KIS액티브 | M70: 75220 | N70: 7022608125 | O70: 100030 | P70: 501648475 | Q70: 7022608125 | R70: 7524256600 | S70: 0 | T70: 0 | U70: 136924705845 | V70: 1363.72 | AA70: 0 | AB70: 0 | AC70: 0 | AD70: 0 | AE70: 7.14 | AF70: 우리은행 | AG70: 0 | AI70: 4.98 | AJ70: 5.5
A71: 70 | B71: 국내 | C71: 45348 | D71: 주식 | E71: 민상구 | F71: 05C30 | G71: 한국투자TDF알아서2025증권투자신탁(주식혼합-재간접형)(모) | H71: ETF(거래소)(채권) | I71: KINDEX 국고채10년 | J71: KR7365780006 | L71: ACE 국고채10년 | M71: 4560 | N71: 398484141 | O71: 87380 | P71: -31341 | Q71: 398484141 | R71: 398452800 | S71: 0 | T71: 0 | U71: 136924705845 | V71: 1363.72 | AA71: 0 | AB71: 0 | AC71: 0 | AD71: 0 | AE71: -0.01 | AF71: 우리은행 | AG71: 0 | AI71: 0.26 | AJ71: 0.29
A72: 71 | B72: 국내 | C72: 45348 | D72: 현금 | E72: 민상구 | F72: 05C30 | G72: 한국투자TDF알아서2025증권투자신탁(주식혼합-재간접형)(모) | H72: 보통예금 | I72: 공통 | J72: KR9999990000 | L72: 예금 | M72: 3005747544 | N72: 3005747544 | O72: 0 | P72: 0 | Q72: 3009822158 | R72: 3009822158 | S72: 0 | T72: 4074614 | U72: 136924705845 | V72: 1363.72 | Y72: 만기일시 | AA72: 2.98595 | AB72: 2.99 | AC72: 0 | AD72: 2.99 | AE72: 0 | AF72: 우리은행 | AG72: 0 | AI72: 1.99 | AJ72: 2.2
A73: 72 | B73: 국내 | C73: 45348 | D73: 현금 | E73: 민상구 | F73: 05C30 | G73: 한국투자TDF알아서2025증권투자신탁(주식혼합-재간접형)(모) | H73: 콜론 | I73: 한국증권금융 | J73: KR9E22680009 | L73: 증권금융(콜론) | M73: 1699880000 | N73: 1699880000 | O73: 0 | P73: 0 | Q73: 1700042071 | R73: 1700042071 | S73: 0 | T73: 162071 | U73: 136924705845 | V73: 1363.72 | W73: 45348 | X73: 45349 | Y73: 만기일시 | AA73: 3.47967 | AB73: 3.48 | AC73: 0 | AD73: 3.48 | AE73: 0 | AF73: 우리은행 | AG73: 0 | AI73: 1.13 | AJ73: 1.24
A74: 73 | B74: 국내 | C74: 45348 | D74: 현금 | E74: 민상구 | F74: 05C30 | G74: 한국투자TDF알아서2025증권투자신탁(주식혼합-재간접형)(모) | H74: 콜론 | I74: 삼성증권 | J74: KR9E22680023 | L74: 삼성증권(콜론) | M74: 1181070000 | N74: 1181070000 | O74: 0 | P74: 0 | Q74: 1181188754 | R74: 1181188754 | S74: 0 | T74: 118754 | U74: 136924705845 | V74: 1363.72 | W74: 45348 | X74: 45349 | Y74: 만기일시 | AA74: 3.66963 | AB74: 3.67 | AC74: 0 | AD74: 3.67 | AE74: 0 | AF74: 우리은행 | AG74: 0 | AI74: 0.78 | AJ74: 0.86
A75: 74 | B75: 국내 | C75: 45348 | D75: 현금 | E75: 민상구 | F75: 05C30 | G75: 한국투자TDF알아서2025증권투자신탁(주식혼합-재간접형)(모) | H75: 현금위탁증거금 | I75: 신한투자증권 | J75: 000002000000 | L75: 신한금융투자(증거금) | M75: 114473070 | N75: 114473070 | O75: 0 | P75: 0 | Q75: 114473070 | R75: 114473070 | S75: 0 | T75: 0 | U75: 136924705845 | V75: 1363.72 | Y75: 만기일시 | AA75: 0 | AB75: 0 | AC75: 0 | AD75: 0 | AE75: 0 | AF75: 우리은행 | AG75: 0 | AI75: 0.08 | AJ75: 0.08
A76: 75 | B76: 국내 | C76: 45348 | D76: 현금 | E76: 민상구 | F76: 05C30 | G76: 한국투자TDF알아서2025증권투자신탁(주식혼합-재간접형)(모) | H76: 현금위탁증거금 | I76: 한국투자증권 | J76: 000003000000 | L76: 한국투자증권(증거금) | M76: 428289180 | N76: 428289180 | O76: 0 | P76: 0 | Q76: 428289180 | R76: 428289180 | S76: 0 | T76: 0 | U76: 136924705845 | V76: 1363.72 | Y76: 만기일시 | AA76: 0 | AB76: 0 | AC76: 0 | AD76: 0 | AE76: 0 | AF76: 우리은행 | AG76: 0 | AI76: 0.28 | AJ76: 0.31
A77: 76 | B77: 국내 | C77: 45348 | D77: 집합증권 | E77: 민상구 | F77: 05C31 | G77: 한국투자TDF알아서2025증권투자신탁(주식혼합-재간접형)(A) | H77: 종류형모펀드 | I77: 한국투자신탁운용 | J77: 032280005C30 | L77: 한국투자TDF알아서2025증권투자신탁(주식혼합-재간접형)(모) | M77: 1276038858 | N77: 1789122316 | O77: 1363.72 | P77: -48961929 | Q77: 1740160387 | R77: 1740160387 | S77: 0 | T77: 0 | U77: 1738356111 | V77: 1269.94 | W77: 42796 | X77: 0000-01-01 | Y77: N/A | Z77: 44256 | AA77: 0 | AB77: 0 | AC77: 0 | AD77: 0 | AE77: 0 | AF77: 우리은행 | AG77: 0 | AH77: N/A | AI77: 100 | AJ77: 100.1
A78: 77 | B78: 국내 | C78: 45348 | D78: 현금 | E78: 민상구 | F78: 05C31 | G78: 한국투자TDF알아서2025증권투자신탁(주식혼합-재간접형)(A) | H78: 보통예금 | I78: 공통 | J78: KR9999990000 | L78: 예금 | M78: 0 | N78: 0 | O78: 0 | P78: 0 | Q78: 0 | R78: 0 | S78: 0 | T78: 0 | U78: 1738356111 | V78: 1269.94 | Y78: 만기일시 | AA78: 0 | AB78: 2.99 | AC78: 0 | AD78: 2.99 | AE78: 0 | AF78: 우리은행 | AG78: 0 | AI78: 0 | AJ78: 0
A79: 78 | B79: 국내 | C79: 45348 | D79: 기타자산 | E79: 민상구 | F79: 05C32 | G79: 한국투자TDF알아서2025증권투자신탁(주식혼합-재간접형)(A-e) | H79: 계정코드 | J79: 1711700 | L79: 집합투자증권매도미수금 | M79: 0 | N79: 0 | O79: 0 | P79: 0 | Q79: 640573 | R79: 640573 | S79: 0 | T79: 0 | U79: 230247612 | V79: 1271.71 | AA79: 0 | AB79: 0 | AC79: 0 | AD79: 0 | AE79: 0 | AF79: 우리은행 | AG79: 0 | AI79: 0.28 | AJ79: 0.28
A80: 79 | B80: 국내 | C80: 45348 | D80: 집합증권 | E80: 민상구 | F80: 05C32 | G80: 한국투자TDF알아서2025증권투자신탁(주식혼합-재간접형)(A-e) | H80: 종류형모펀드 | I80: 한국투자신탁운용 | J80: 032280005C30 | L80: 한국투자TDF알아서2025증권투자신탁(주식혼합-재간접형)(모) | M80: 168971985 | N80: 231653382 | O80: 1363.72 | P80: -1222817 | Q80: 230430565 | R80: 230430565 | S80: 0 | T80: 0 | U80: 230247612 | V80: 1271.71 | W80: 42796 | X80: 0000-01-01 | Y80: N/A | Z80: 44256 | AA80: 0 | AB80: 0 | AC80: 0 | AD80: 0 | AE80: 0 | AF80: 우리은행 | AG80: 0 | AH80: N/A | AI80: 99.72 | AJ80: 100.08
A81: 80 | B81: 국내 | C81: 45348 | D81: 현금 | E81: 민상구 | F81: 05C32 | G81: 한국투자TDF알아서2025증권투자신탁(주식혼합-재간접형)(A-e) | H81: 보통예금 | I81: 공통 | J81: KR9999990000 | L81: 예금 | M81: 0 | N81: 0 | O81: 0 | P81: 0 | Q81: 0 | R81: 0 | S81: 0 | T81: 0 | U81: 230247612 | V81: 1271.71 | Y81: 만기일시 | AA81: 0 | AB81: 2.99 | AC81: 0 | AD81: 2.99 | AE81: 0 | AF81: 우리은행 | AG81: 0 | AI81: 0 | AJ81: 0
A82: 81 | B82: 국내 | C82: 45348 | D82: 집합증권 | E82: 민상구 | F82: 05C33 | G82: 한국투자TDF알아서2025증권투자신탁(주식혼합-재간접형)(C) | H82: 종류형모펀드 | I82: 한국투자신탁운용 | J82: 032280005C30 | L82: 한국투자TDF알아서2025증권투자신탁(주식혼합-재간접형)(모) | M82: 641634939 | N82: 881058297 | O82: 1363.72 | P82: -6047558 | Q82: 875010739 | R82: 875010739 | S82: 0 | T82: 0 | U82: 873410501 | V82: 1295.42 | W82: 42796 | X82: 0000-01-01 | Y82: N/A | Z82: 44256 | AA82: 0 | AB82: 0 | AC82: 0 | AD82: 0 | AE82: 0 | AF82: 우리은행 | AG82: 0 | AH82: N/A | AI82: 100 | AJ82: 100.18
A83: 82 | B83: 국내 | C83: 45348 | D83: 현금 | E83: 민상구 | F83: 05C33 | G83: 한국투자TDF알아서2025증권투자신탁(주식혼합-재간접형)(C) | H83: 보통예금 | I83: 공통 | J83: KR9999990000 | L83: 예금 | M83: 0 | N83: 0 | O83: 0 | P83: 0 | Q83: 0 | R83: 0 | S83: 0 | T83: 0 | U83: 873410501 | V83: 1295.42 | Y83: 만기일시 | AA83: 0 | AB83: 2.99 | AC83: 0 | AD83: 2.99 | AE83: 0 | AF83: 우리은행 | AG83: 0 | AI83: 0 | AJ83: 0
A84: 83 | B84: 국내 | C84: 45348 | D84: 집합증권 | E84: 민상구 | F84: 05C34 | G84: 한국투자TDF알아서2025증권투자신탁(주식혼합-재간접형)(C-e) | H84: 종류형모펀드 | I84: 한국투자신탁운용 | J84: 032280005C30 | L84: 한국투자TDF알아서2025증권투자신탁(주식혼합-재간접형)(모) | M84: 118004093 | N84: 159987582 | O84: 1363.72 | P84: 937022 | Q84: 160924604 | R84: 160924604 | S84: 0 | T84: 0 | U84: 160733586 | V84: 1270.95 | W84: 42796 | X84: 0000-01-01 | Y84: N/A | Z84: 44256 | AA84: 0 | AB84: 0 | AC84: 0 | AD84: 0 | AE84: 0 | AF84: 우리은행 | AG84: 0 | AH84: N/A | AI84: 100 | AJ84: 100.12
A85: 84 | B85: 국내 | C85: 45348 | D85: 현금 | E85: 민상구 | F85: 05C34 | G85: 한국투자TDF알아서2025증권투자신탁(주식혼합-재간접형)(C-e) | H85: 보통예금 | I85: 공통 | J85: KR9999990000 | L85: 예금 | M85: 0 | N85: 0 | O85: 0 | P85: 0 | Q85: 0 | R85: 0 | S85: 0 | T85: 0 | U85: 160733586 | V85: 1270.95 | Y85: 만기일시 | AA85: 0 | AB85: 2.99 | AC85: 0 | AD85: 2.99 | AE85: 0 | AF85: 우리은행 | AG85: 0 | AI85: 0 | AJ85: 0
A86: 85 | B86: 국내 | C86: 45348 | D86: 기타자산 | E86: 민상구 | F86: 05C36 | G86: 한국투자TDF알아서2025증권투자신탁(주식혼합-재간접형)(C-P) | H86: 계정코드 | J86: 1711700 | L86: 집합투자증권매도미수금 | M86: 0 | N86: 0 | O86: 0 | P86: 0 | Q86: 138634927 | R86: 138634927 | S86: 0 | T86: 0 | U86: 14551187359 | V86: 1315.49 | AA86: 0 | AB86: 0 | AC86: 0 | AD86: 0 | AE86: 0 | AF86: 우리은행 | AG86: 0 | AI86: 0.94 | AJ86: 0.95
A87: 86 | B87: 국내 | C87: 45348 | D87: 집합증권 | E87: 민상구 | F87: 05C36 | G87: 한국투자TDF알아서2025증권투자신탁(주식혼합-재간접형)(C-P) | H87: 종류형모펀드 | I87: 한국투자신탁운용 | J87: 032280005C30 | L87: 한국투자TDF알아서2025증권투자신탁(주식혼합-재간접형)(모) | M87: 10688434539 | N87: 12988658648 | O87: 1363.72 | P87: 1587378957 | Q87: 14576037605 | R87: 14576037605 | S87: 0 | T87: 0 | U87: 14551187359 | V87: 1315.49 | W87: 42796 | X87: 0000-01-01 | Y87: N/A | Z87: 44256 | AA87: 0 | AB87: 0 | AC87: 0 | AD87: 0 | AE87: 0 | AF87: 우리은행 | AG87: 0 | AH87: N/A | AI87: 99.06 | AJ87: 100.17
A88: 87 | B88: 국내 | C88: 45348 | D88: 현금 | E88: 민상구 | F88: 05C36 | G88: 한국투자TDF알아서2025증권투자신탁(주식혼합-재간접형)(C-P) | H88: 보통예금 | I88: 공통 | J88: KR9999990000 | L88: 예금 | M88: 0 | N88: 0 | O88: 0 | P88: 0 | Q88: 0 | R88: 0 | S88: 0 | T88: 0 | U88: 14551187359 | V88: 1315.49 | Y88: 만기일시 | AA88: 0 | AB88: 2.99 | AC88: 0 | AD88: 2.99 | AE88: 0 | AF88: 우리은행 | AG88: 0 | AI88: 0 | AJ88: 0
A89: 88 | B89: 국내 | C89: 45348 | D89: 기타자산 | E89: 민상구 | F89: 05C37 | G89: 한국투자TDF알아서2025증권투자신탁(주식혼합-재간접형)(C-R) | H89: 계정코드 | J89: 1711700 | L89: 집합투자증권매도미수금 | M89: 0 | N89: 0 | O89: 0 | P89: 0 | Q89: 194599717 | R89: 194599717 | S89: 0 | T89: 0 | U89: 62062283164 | V89: 1321.37 | AA89: 0 | AB89: 0 | AC89: 0 | AD89: 0 | AE89: 0 | AF89: 우리은행 | AG89: 0 | AI89: 0.31 | AJ89: 0.31
A90: 89 | B90: 국내 | C90: 45348 | D90: 집합증권 | E90: 민상구 | F90: 05C37 | G90: 한국투자TDF알아서2025증권투자신탁(주식혼합-재간접형)(C-R) | H90: 종류형모펀드 | I90: 한국투자신탁운용 | J90: 032280005C30 | L90: 한국투자TDF알아서2025증권투자신탁(주식혼합-재간접형)(모) | M90: 45576169550 | N90: 58383176944 | O90: 1363.72 | P90: 3769981110 | Q90: 62153158054 | R90: 62153158054 | S90: 0 | T90: 0 | U90: 62062283164 | V90: 1321.37 | W90: 42796 | X90: 0000-01-01 | Y90: N/A | Z90: 44256 | AA90: 0 | AB90: 0 | AC90: 0 | AD90: 0 | AE90: 0 | AF90: 우리은행 | AG90: 0 | AH90: N/A | AI90: 99.69 | AJ90: 100.15
A91: 90 | B91: 국내 | C91: 45348 | D91: 현금 | E91: 민상구 | F91: 05C37 | G91: 한국투자TDF알아서2025증권투자신탁(주식혼합-재간접형)(C-R) | H91: 보통예금 | I91: 공통 | J91: KR9999990000 | L91: 예금 | M91: 0 | N91: 0 | O91: 0 | P91: 0 | Q91: 0 | R91: 0 | S91: 0 | T91: 0 | U91: 62062283164 | V91: 1321.37 | Y91: 만기일시 | AA91: 0 | AB91: 2.99 | AC91: 0 | AD91: 2.99 | AE91: 0 | AF91: 우리은행 | AG91: 0 | AI91: 0 | AJ91: 0
A92: 91 | B92: 국내 | C92: 45348 | D92: 집합증권 | E92: 민상구 | F92: 05C39 | G92: 한국투자TDF알아서2025증권투자신탁(주식혼합-재간접형)(C-W) | H92: 종류형모펀드 | I92: 한국투자신탁운용 | J92: 032280005C30 | L92: 한국투자TDF알아서2025증권투자신탁(주식혼합-재간접형)(모) | M92: 1858226 | N92: 2415242 | O92: 1363.72 | P92: 118859 | Q92: 2534101 | R92: 2534101 | S92: 0 | T92: 0 | U92: 2532843 | V92: 1272.79 | W92: 42796 | X92: 0000-01-01 | Y92: N/A | Z92: 44256 | AA92: 0 | AB92: 0 | AC92: 0 | AD92: 0 | AE92: 0 | AF92: 우리은행 | AG92: 0 | AH92: N/A | AI92: 100 | AJ92: 100.05
A93: 92 | B93: 국내 | C93: 45348 | D93: 현금 | E93: 민상구 | F93: 05C39 | G93: 한국투자TDF알아서2025증권투자신탁(주식혼합-재간접형)(C-W) | H93: 보통예금 | I93: 공통 | J93: KR9999990000 | L93: 예금 | M93: 0 | N93: 0 | O93: 0 | P93: 0 | Q93: 0 | R93: 0 | S93: 0 | T93: 0 | U93: 2532843 | V93: 1272.79 | Y93: 만기일시 | AA93: 0 | AB93: 2.99 | AC93: 0 | AD93: 2.99 | AE93: 0 | AF93: 우리은행 | AG93: 0 | AI93: 0 | AJ93: 0
A94: 93 | B94: 국내 | C94: 45348 | D94: 집합증권 | E94: 민상구 | F94: 05C40 | G94: 한국투자TDF알아서2025증권투자신탁(주식혼합-재간접형)(S) | H94: 종류형모펀드 | I94: 한국투자신탁운용 | J94: 032280005C30 | L94: 한국투자TDF알아서2025증권투자신탁(주식혼합-재간접형)(모) | M94: 22495689 | N94: 30320284 | O94: 1363.72 | P94: 357549 | Q94: 30677833 | R94: 30677833 | S94: 0 | T94: 0 | U94: 30654236 | V94: 1229.13 | W94: 42796 | X94: 0000-01-01 | Y94: N/A | Z94: 44256 | AA94: 0 | AB94: 0 | AC94: 0 | AD94: 0 | AE94: 0 | AF94: 우리은행 | AG94: 0 | AH94: N/A | AI94: 100 | AJ94: 100.08
A95: 94 | B95: 국내 | C95: 45348 | D95: 현금 | E95: 민상구 | F95: 05C40 | G95: 한국투자TDF알아서2025증권투자신탁(주식혼합-재간접형)(S) | H95: 보통예금 | I95: 공통 | J95: KR9999990000 | L95: 예금 | M95: 0 | N95: 0 | O95: 0 | P95: 0 | Q95: 0 | R95: 0 | S95: 0 | T95: 0 | U95: 30654236 | V95: 1229.13 | Y95: 만기일시 | AA95: 0 | AB95: 2.99 | AC95: 0 | AD95: 2.99 | AE95: 0 | AF95: 우리은행 | AG95: 0 | AI95: 0 | AJ95: 0
A96: 95 | B96: 국내 | C96: 45348 | D96: 집합증권 | E96: 민상구 | F96: 05C41 | G96: 한국투자TDF알아서2025증권투자신탁(주식혼합-재간접형)(S-P) | H96: 종류형모펀드 | I96: 한국투자신탁운용 | J96: 032280005C30 | L96: 한국투자TDF알아서2025증권투자신탁(주식혼합-재간접형)(모) | M96: 33128802 | N96: 43943384 | O96: 1363.72 | P96: 1235043 | Q96: 45178427 | R96: 45178427 | S96: 0 | T96: 0 | U96: 45144493 | V96: 1186.44 | W96: 42796 | X96: 0000-01-01 | Y96: N/A | Z96: 44256 | AA96: 0 | AB96: 0 | AC96: 0 | AD96: 0 | AE96: 0 | AF96: 우리은행 | AG96: 0 | AH96: N/A | AI96: 100 | AJ96: 100.08
A97: 96 | B97: 국내 | C97: 45348 | D97: 현금 | E97: 민상구 | F97: 05C41 | G97: 한국투자TDF알아서2025증권투자신탁(주식혼합-재간접형)(S-P) | H97: 보통예금 | I97: 공통 | J97: KR9999990000 | L97: 예금 | M97: 0 | N97: 0 | O97: 0 | P97: 0 | Q97: 0 | R97: 0 | S97: 0 | T97: 0 | U97: 45144493 | V97: 1186.44 | Y97: 만기일시 | AA97: 0 | AB97: 2.99 | AC97: 0 | AD97: 2.99 | AE97: 0 | AF97: 우리은행 | AG97: 0 | AI97: 0 | AJ97: 0
A98: 97 | B98: 국내 | C98: 45348 | D98: 집합증권 | E98: 민상구 | F98: 05C42 | G98: 한국투자TDF알아서2025증권투자신탁(주식혼합-재간접형)(S-R) | H98: 종류형모펀드 | I98: 한국투자신탁운용 | J98: 032280005C30 | L98: 한국투자TDF알아서2025증권투자신탁(주식혼합-재간접형)(모) | M98: 34521723 | N98: 46394517 | O98: 1363.72 | P98: 683465 | Q98: 47077982 | R98: 47077982 | S98: 0 | T98: 0 | U98: 47043938 | V98: 1135.05 | W98: 42796 | X98: 0000-01-01 | Y98: N/A | Z98: 44256 | AA98: 0 | AB98: 0 | AC98: 0 | AD98: 0 | AE98: 0 | AF98: 우리은행 | AG98: 0 | AH98: N/A | AI98: 100 | AJ98: 100.07
A99: 98 | B99: 국내 | C99: 45348 | D99: 현금 | E99: 민상구 | F99: 05C42 | G99: 한국투자TDF알아서2025증권투자신탁(주식혼합-재간접형)(S-R) | H99: 보통예금 | I99: 공통 | J99: KR9999990000 | L99: 예금 | M99: 0 | N99: 0 | O99: 0 | P99: 0 | Q99: 0 | R99: 0 | S99: 0 | T99: 0 | U99: 47043938 | V99: 1135.05 | Y99: 만기일시 | AA99: 0 | AB99: 2.99 | AC99: 0 | AD99: 2.99 | AE99: 0 | AF99: 우리은행 | AG99: 0 | AI99: 0 | AJ99: 0
A100: 99 | B100: 국내 | C100: 45348 | D100: 선물매도 | E100: 민상구 | F100: 05C44 | G100: 한국투자TDF알아서2030증권투자신탁(주식혼합-재간접형)(모) | H100: 달러선물 | I100: N/A | J100: KR4175V30009 | L100: 미국달러 F 202403 | M100: 1448 | N100: 19241024000 | O100: 1330.5 | P100: -24616000 | Q100: 0 | R100: 19265640000 | S100: 0 | T100: 0 | U100: 278591157635 | V100: 1447.07 | W100: 44271 | X100: 45369 | Y100: N/A | Z100: 0000-01-01 | AA100: 0 | AB100: 0 | AC100: 0 | AD100: 0 | AE100: 0 | AF100: 우리은행 | AG100: 0 | AH100: N/A | AI100: 6.33 | AJ100: 6.92
...

Sheet 펀드현황
B1: 멀티에셋운용부 주요펀드 수익률 현황 | S1: 자금 현황 | AB1: 억원 | AI1: 1만달러
G2: 62 | H2: 65 | I2: 12 | J2: 15 | K2: 18 | L2: 24 | M2: 27 | N2: 30 | O2: 45 | P2: 39 | Q2: 47 | V2: 순설정액 | Z2: 자금 | AB2: KRW | AH2: 자금 | AI2: USD
B3: 구분 | C3: 펀드코드 | D3: 펀드명 | E3: 설정액 | F3: 순자산 | G3: 최초설정일 | H3: 기준가격 | I3: 1개월 | J3: 3개월 | K3: 6개월 | L3: 1년 | M3: 2년 | N3: 3년 | O3: YTD | P3: 설정이후 | Q3: YTD 초과 | S3: 구분 | T3: 펀드코드 | V3: T0 | W3: T1 | X3: T2 | Z3: T0 | AB3: T1 | AC3: T2 | AD3: T3 | AE3: T4 | AF3: T5 | AH3: T0 | AI3: T1 | AJ3: T2 | AK3: T3 | AL3: T4 | AM3: T5
B4: ETF 포커스 | C4: 07M02 | D4: TIF포커스 | E4: =AVERAGEIFS(#REF!,#REF!,펀드현황!$C4)/100000000 -> #REF! | F4: =IFERROR(VLOOKUP($T4,자금총괄!$B:$E,4,0)/100000000,"") -> 70.407549 | G4: =VLOOKUP($C4,'MOS4110'!$A:$BP,펀드현황!G$2,0) -> 44839 | H4: =VLOOKUP($C4,'MOS4110'!$A:$BP,펀드현황!H$2,0) -> 1160.9 | I4: =VLOOKUP($C4,'MOS4110'!$A:$BP,펀드현황!I$2,0) -> 1.4312 | J4: =VLOOKUP($C4,'MOS4110'!$A:$BP,펀드현황!J$2,0) -> 6.3709 | K4: =VLOOKUP($C4,'MOS4110'!$A:$BP,펀드현황!K$2,0) -> 8.7833 | L4: =VLOOKUP($C4,'MOS4110'!$A:$BP,펀드현황!L$2,0) -> 13.0673 | O4: =VLOOKUP($C4,'MOS4110'!$A:$BP,펀드현황!O$2,0) -> 2.7709 | P4: =VLOOKUP($C4,'MOS4110'!$A:$BP,펀드현황!P$2,0) -> 16.7092 | S4: TDF ETF포커스 | T4: =C4 -> 07M02 | V4: =IFERROR( ( SUMIFS(설정해지!$G:$G, 설정해지!$B:$B,펀드현황!$C4,설정해지!$F:$F,"KRW")-SUMIFS(설정해지!$H:$H, 설정해지!$B:$B,펀드현황!$C4,설정해지!$F:$F,"KRW") ) /100000000,"") -> -0.03280307 | W4: =IFERROR( ( SUMIFS(설정해지!$I:$I, 설정해지!$B:$B,펀드현황!$C4,설정해지!$F:$F,"KRW")-SUMIFS(설정해지!$J:$J, 설정해지!$B:$B,펀드현황!$C4,설정해지!$F:$F,"KRW") ) /100000000,"") -> -0.55384553 | X4: =IFERROR( ( SUMIFS(설정해지!$K:$K, 설정해지!$B:$B,펀드현황!$C4,설정해지!$F:$F,"KRW")-SUMIFS(설정해지!$L:$L, 설정해지!$B:$B,펀드현황!$C4,설정해지!$F:$F,"KRW") ) /100000000,"") -> 0 | Z4: =IFERROR( ( SUMIFS(자금총괄!$G:$G, 자금총괄!$B:$B,펀드현황!$C4,자금총괄!$F:$F,$AB$2) ) /100000000,"") -> 2.4151214 | AA4: =Z4/F4 -> 0.034302024 | AB4: =IFERROR( ( SUMIFS(자금총괄!$I:$I, 자금총괄!$B:$B,펀드현황!$C4,자금총괄!$F:$F,$AB$2) ) /100000000,"") -> 1.669243 | AC4: =IFERROR( ( SUMIFS(자금총괄!$K:$K, 자금총괄!$B:$B,펀드현황!$C4,자금총괄!$F:$F,$AB$2) ) /100000000,"") -> 1.669243 | AD4: =IFERROR( ( SUMIFS(자금총괄!$M:$M, 자금총괄!$B:$B,펀드현황!$C4,자금총괄!$F:$F,$AB$2) ) /100000000,"") -> 1.6689395 | AE4: =IFERROR( ( SUMIFS(자금총괄!$O:$O, 자금총괄!$B:$B,펀드현황!$C4,자금총괄!$F:$F,$AB$2) ) /100000000,"") -> 1.6689395 | AF4: =IFERROR( ( SUMIFS(자금총괄!$Q:$Q, 자금총괄!$B:$B,펀드현황!$C4,자금총괄!$F:$F,$AB$2) ) /100000000,"") -> 1.657445 | AH4: =IFERROR( ( SUMIFS(자금총괄!$G:$G, 자금총괄!$B:$B,펀드현황!$C4,자금총괄!$F:$F,$AI$2)/10000 ),"") -> 1.068655 | AI4: =IFERROR( ( SUMIFS(자금총괄!$I:$I, 자금총괄!$B:$B,펀드현황!$C4,자금총괄!$F:$F,$AI$2)/10000 ),"") -> 1.402764 | AJ4: =IFERROR((SUMIFS(자금총괄!$K:$K,자금총괄!$B:$B,펀드현황!$C4,자금총괄!$F:$F,$AI$2)/10000),"") -> 1.402764 | AK4: =IFERROR((SUMIFS(자금총괄!$M:$M,자금총괄!$B:$B,펀드현황!$C4,자금총괄!$F:$F,$AI$2)/10000),"") -> 1.402764 | AL4: =IFERROR( ( SUMIFS(자금총괄!$O:$O, 자금총괄!$B:$B,펀드현황!$C4,자금총괄!$F:$F,$AI$2) /10000 ),"") -> 1.402764 | AM4: =IFERROR( ( SUMIFS(자금총괄!$Q:$Q, 자금총괄!$B:$B,펀드현황!$C4,자금총괄!$F:$F,$AI$2) /10000 ),"") -> 1.402764
C5: 07J66 | D5: TDF포커스 2030 | E5: =AVERAGEIFS(#REF!,#REF!,펀드현황!$C5)/100000000 -> #REF! | F5: =IFERROR(VLOOKUP($T5,자금총괄!$B:$E,4,0)/100000000,"") -> 233.53491 | G5: =VLOOKUP($C5,'MOS4110'!$A:$BP,펀드현황!G$2,0) -> 44839 | H5: =VLOOKUP($C5,'MOS4110'!$A:$BP,펀드현황!H$2,0) -> 1181.93 | I5: =VLOOKUP($C5,'MOS4110'!$A:$BP,펀드현황!I$2,0) -> 1.7686 | J5: =VLOOKUP($C5,'MOS4110'!$A:$BP,펀드현황!J$2,0) -> 7.4638 | K5: =VLOOKUP($C5,'MOS4110'!$A:$BP,펀드현황!K$2,0) -> 10.0453 | L5: =VLOOKUP($C5,'MOS4110'!$A:$BP,펀드현황!L$2,0) -> 15.8539 | O5: =VLOOKUP($C5,'MOS4110'!$A:$BP,펀드현황!O$2,0) -> 3.7591 | P5: =VLOOKUP($C5,'MOS4110'!$A:$BP,펀드현황!P$2,0) -> 19.0515 | T5: =C5 -> 07J66 | V5: =IFERROR( ( SUMIFS(설정해지!$G:$G, 설정해지!$B:$B,펀드현황!$C5,설정해지!$F:$F,"KRW")-SUMIFS(설정해지!$H:$H, 설정해지!$B:$B,펀드현황!$C5,설정해지!$F:$F,"KRW") ) /100000000,"") -> 0.74624513 | W5: =IFERROR( ( SUMIFS(설정해지!$I:$I, 설정해지!$B:$B,펀드현황!$C5,설정해지!$F:$F,"KRW")-SUMIFS(설정해지!$J:$J, 설정해지!$B:$B,펀드현황!$C5,설정해지!$F:$F,"KRW") ) /100000000,"") -> 0.61598837 | X5: =IFERROR( ( SUMIFS(설정해지!$K:$K, 설정해지!$B:$B,펀드현황!$C5,설정해지!$F:$F,"KRW")-SUMIFS(설정해지!$L:$L, 설정해지!$B:$B,펀드현황!$C5,설정해지!$F:$F,"KRW") ) /100000000,"") -> -0.00859354 | Z5: =IFERROR( ( SUMIFS(자금총괄!$G:$G, 자금총괄!$B:$B,펀드현황!$C5,자금총괄!$F:$F,$AB$2) ) /100000000,"") -> 9.0635073 | AA5: =Z5/F5 -> 0.038810075 | AB5: =IFERROR( ( SUMIFS(자금총괄!$I:$I, 자금총괄!$B:$B,펀드현황!$C5,자금총괄!$F:$F,$AB$2) ) /100000000,"") -> 9.6794957 | AC5: =IFERROR( ( SUMIFS(자금총괄!$K:$K, 자금총괄!$B:$B,펀드현황!$C5,자금총괄!$F:$F,$AB$2) ) /100000000,"") -> 9.6709022 | AD5: =IFERROR( ( SUMIFS(자금총괄!$M:$M, 자금총괄!$B:$B,펀드현황!$C5,자금총괄!$F:$F,$AB$2) ) /100000000,"") -> 7.5152604 | AE5: =IFERROR( ( SUMIFS(자금총괄!$O:$O, 자금총괄!$B:$B,펀드현황!$C5,자금총괄!$F:$F,$AB$2) ) /100000000,"") -> 7.4115072 | AF5: =IFERROR( ( SUMIFS(자금총괄!$Q:$Q, 자금총괄!$B:$B,펀드현황!$C5,자금총괄!$F:$F,$AB$2) ) /100000000,"") -> 7.3361716 | AH5: =IFERROR( ( SUMIFS(자금총괄!$G:$G, 자금총괄!$B:$B,펀드현황!$C5,자금총괄!$F:$F,$AI$2)/10000 ),"") -> 6.172508 | AI5: =IFERROR( ( SUMIFS(자금총괄!$I:$I, 자금총괄!$B:$B,펀드현황!$C5,자금총괄!$F:$F,$AI$2)/10000 ),"") -> 4.072394 | AJ5: =IFERROR((SUMIFS(자금총괄!$K:$K,자금총괄!$B:$B,펀드현황!$C5,자금총괄!$F:$F,$AI$2)/10000),"") -> 4.072394 | AK5: =IFERROR((SUMIFS(자금총괄!$M:$M,자금총괄!$B:$B,펀드현황!$C5,자금총괄!$F:$F,$AI$2)/10000),"") -> 4.072394 | AL5: =IFERROR( ( SUMIFS(자금총괄!$O:$O, 자금총괄!$B:$B,펀드현황!$C5,자금총괄!$F:$F,$AI$2) /10000 ),"") -> 4.072394 | AM5: =IFERROR( ( SUMIFS(자금총괄!$Q:$Q, 자금총괄!$B:$B,펀드현황!$C5,자금총괄!$F:$F,$AI$2) /10000 ),"") -> 4.072394
C6: 07J71 | D6: TDF포커스 2035 | E6: =AVERAGEIFS(#REF!,#REF!,펀드현황!$C6)/100000000 -> #REF! | F6: =IFERROR(VLOOKUP($T6,자금총괄!$B:$E,4,0)/100000000,"") -> 71.524681 | G6: =VLOOKUP($C6,'MOS4110'!$A:$BP,펀드현황!G$2,0) -> 44839 | H6: =VLOOKUP($C6,'MOS4110'!$A:$BP,펀드현황!H$2,0) -> 1190.14 | I6: =VLOOKUP($C6,'MOS4110'!$A:$BP,펀드현황!I$2,0) -> 1.886 | J6: =VLOOKUP($C6,'MOS4110'!$A:$BP,펀드현황!J$2,0) -> 7.8387 | K6: =VLOOKUP($C6,'MOS4110'!$A:$BP,펀드현황!K$2,0) -> 10.4724 | L6: =VLOOKUP($C6,'MOS4110'!$A:$BP,펀드현황!L$2,0) -> 17.1602 | O6: =VLOOKUP($C6,'MOS4110'!$A:$BP,펀드현황!O$2,0) -> 4.0632 | P6: =VLOOKUP($C6,'MOS4110'!$A:$BP,펀드현황!P$2,0) -> 19.9123 | T6: =C6 -> 07J71 | V6: =IFERROR( ( SUMIFS(설정해지!$G:$G, 설정해지!$B:$B,펀드현황!$C6,설정해지!$F:$F,"KRW")-SUMIFS(설정해지!$H:$H, 설정해지!$B:$B,펀드현황!$C6,설정해지!$F:$F,"KRW") ) /100000000,"") -> 0.04599013 | W6: =IFERROR( ( SUMIFS(설정해지!$I:$I, 설정해지!$B:$B,펀드현황!$C6,설정해지!$F:$F,"KRW")-SUMIFS(설정해지!$J:$J, 설정해지!$B:$B,펀드현황!$C6,설정해지!$F:$F,"KRW") ) /100000000,"") -> 0.03775624 | X6: =IFERROR( ( SUMIFS(설정해지!$K:$K, 설정해지!$B:$B,펀드현황!$C6,설정해지!$F:$F,"KRW")-SUMIFS(설정해지!$L:$L, 설정해지!$B:$B,펀드현황!$C6,설정해지!$F:$F,"KRW") ) /100000000,"") -> 0 | Z6: =IFERROR( ( SUMIFS(자금총괄!$G:$G, 자금총괄!$B:$B,펀드현황!$C6,자금총괄!$F:$F,$AB$2) ) /100000000,"") -> 2.0060568 | AA6: =Z6/F6 -> 0.028047057 | AB6: =IFERROR( ( SUMIFS(자금총괄!$I:$I, 자금총괄!$B:$B,펀드현황!$C6,자금총괄!$F:$F,$AB$2) ) /100000000,"") -> 1.7095927 | AC6: =IFERROR( ( SUMIFS(자금총괄!$K:$K, 자금총괄!$B:$B,펀드현황!$C6,자금총괄!$F:$F,$AB$2) ) /100000000,"") -> 1.7095927 | AD6: =IFERROR( ( SUMIFS(자금총괄!$M:$M, 자금총괄!$B:$B,펀드현황!$C6,자금총괄!$F:$F,$AB$2) ) /100000000,"") -> 1.7095927 | AE6: =IFERROR( ( SUMIFS(자금총괄!$O:$O, 자금총괄!$B:$B,펀드현황!$C6,자금총괄!$F:$F,$AB$2) ) /100000000,"") -> 1.7095927 | AF6: =IFERROR( ( SUMIFS(자금총괄!$Q:$Q, 자금총괄!$B:$B,펀드현황!$C6,자금총괄!$F:$F,$AB$2) ) /100000000,"") -> 1.7095927 | AH6: =IFERROR( ( SUMIFS(자금총괄!$G:$G, 자금총괄!$B:$B,펀드현황!$C6,자금총괄!$F:$F,$AI$2)/10000 ),"") -> 1.394757 | AI6: =IFERROR( ( SUMIFS(자금총괄!$I:$I, 자금총괄!$B:$B,펀드현황!$C6,자금총괄!$F:$F,$AI$2)/10000 ),"") -> 1.639727 | AJ6: =IFERROR((SUMIFS(자금총괄!$K:$K,자금총괄!$B:$B,펀드현황!$C6,자금총괄!$F:$F,$AI$2)/10000),"") -> 1.639727 | AK6: =IFERROR((SUMIFS(자금총괄!$M:$M,자금총괄!$B:$B,펀드현황!$C6,자금총괄!$F:$F,$AI$2)/10000),"") -> 1.639727 | AL6: =IFERROR( ( SUMIFS(자금총괄!$O:$O, 자금총괄!$B:$B,펀드현황!$C6,자금총괄!$F:$F,$AI$2) /10000 ),"") -> 1.639727 | AM6: =IFERROR( ( SUMIFS(자금총괄!$Q:$Q, 자금총괄!$B:$B,펀드현황!$C6,자금총괄!$F:$F,$AI$2) /10000 ),"") -> 1.639727
C7: 07J76 | D7: TDF포커스 2040 | E7: =AVERAGEIFS(#REF!,#REF!,펀드현황!$C7)/100000000 -> #REF! | F7: =IFERROR(VLOOKUP($T7,자금총괄!$B:$E,4,0)/100000000,"") -> 58.585821 | G7: =VLOOKUP($C7,'MOS4110'!$A:$BP,펀드현황!G$2,0) -> 44839 | H7: =VLOOKUP($C7,'MOS4110'!$A:$BP,펀드현황!H$2,0) -> 1197.62 | I7: =VLOOKUP($C7,'MOS4110'!$A:$BP,펀드현황!I$2,0) -> 2.058 | J7: =VLOOKUP($C7,'MOS4110'!$A:$BP,펀드현황!J$2,0) -> 8.3976 | K7: =VLOOKUP($C7,'MOS4110'!$A:$BP,펀드현황!K$2,0) -> 11.094 | L7: =VLOOKUP($C7,'MOS4110'!$A:$BP,펀드현황!L$2,0) -> 18.4963 | O7: =VLOOKUP($C7,'MOS4110'!$A:$BP,펀드현황!O$2,0) -> 4.5664 | P7: =VLOOKUP($C7,'MOS4110'!$A:$BP,펀드현황!P$2,0) -> 20.7714 | T7: =C7 -> 07J76 | V7: =IFERROR( ( SUMIFS(설정해지!$G:$G, 설정해지!$B:$B,펀드현황!$C7,설정해지!$F:$F,"KRW")-SUMIFS(설정해지!$H:$H, 설정해지!$B:$B,펀드현황!$C7,설정해지!$F:$F,"KRW") ) /100000000,"") -> 0.31869655 | W7: =IFERROR( ( SUMIFS(설정해지!$I:$I, 설정해지!$B:$B,펀드현황!$C7,설정해지!$F:$F,"KRW")-SUMIFS(설정해지!$J:$J, 설정해지!$B:$B,펀드현황!$C7,설정해지!$F:$F,"KRW") ) /100000000,"") -> 0.14520328 | X7: =IFERROR( ( SUMIFS(설정해지!$K:$K, 설정해지!$B:$B,펀드현황!$C7,설정해지!$F:$F,"KRW")-SUMIFS(설정해지!$L:$L, 설정해지!$B:$B,펀드현황!$C7,설정해지!$F:$F,"KRW") ) /100000000,"") -> -0.15317858 | Z7: =IFERROR( ( SUMIFS(자금총괄!$G:$G, 자금총괄!$B:$B,펀드현황!$C7,자금총괄!$F:$F,$AB$2) ) /100000000,"") -> 2.0613932 | AA7: =Z7/F7 -> 0.035185872 | AB7: =IFERROR( ( SUMIFS(자금총괄!$I:$I, 자금총괄!$B:$B,펀드현황!$C7,자금총괄!$F:$F,$AB$2) ) /100000000,"") -> 1.9178655 | AC7: =IFERROR( ( SUMIFS(자금총괄!$K:$K, 자금총괄!$B:$B,펀드현황!$C7,자금총괄!$F:$F,$AB$2) ) /100000000,"") -> 1.7646869 | AD7: =IFERROR( ( SUMIFS(자금총괄!$M:$M, 자금총괄!$B:$B,펀드현황!$C7,자금총괄!$F:$F,$AB$2) ) /100000000,"") -> 1.7646869 | AE7: =IFERROR( ( SUMIFS(자금총괄!$O:$O, 자금총괄!$B:$B,펀드현황!$C7,자금총괄!$F:$F,$AB$2) ) /100000000,"") -> 1.7546815 | AF7: =IFERROR( ( SUMIFS(자금총괄!$Q:$Q, 자금총괄!$B:$B,펀드현황!$C7,자금총괄!$F:$F,$AB$2) ) /100000000,"") -> 1.6311358 | AH7: =IFERROR( ( SUMIFS(자금총괄!$G:$G, 자금총괄!$B:$B,펀드현황!$C7,자금총괄!$F:$F,$AI$2)/10000 ),"") -> 0.993986 | AI7: =IFERROR( ( SUMIFS(자금총괄!$I:$I, 자금총괄!$B:$B,펀드현황!$C7,자금총괄!$F:$F,$AI$2)/10000 ),"") -> 0.968188 | AJ7: =IFERROR((SUMIFS(자금총괄!$K:$K,자금총괄!$B:$B,펀드현황!$C7,자금총괄!$F:$F,$AI$2)/10000),"") -> 0.968188 | AK7: =IFERROR((SUMIFS(자금총괄!$M:$M,자금총괄!$B:$B,펀드현황!$C7,자금총괄!$F:$F,$AI$2)/10000),"") -> 0.968188 | AL7: =IFERROR( ( SUMIFS(자금총괄!$O:$O, 자금총괄!$B:$B,펀드현황!$C7,자금총괄!$F:$F,$AI$2) /10000 ),"") -> 0.968188 | AM7: =IFERROR( ( SUMIFS(자금총괄!$Q:$Q, 자금총괄!$B:$B,펀드현황!$C7,자금총괄!$F:$F,$AI$2) /10000 ),"") -> 0.968188
C8: 07J81 | D8: TDF포커스 2045 | E8: =AVERAGEIFS(#REF!,#REF!,펀드현황!$C8)/100000000 -> #REF! | F8: =IFERROR(VLOOKUP($T8,자금총괄!$B:$E,4,0)/100000000,"") -> 60.365321 | G8: =VLOOKUP($C8,'MOS4110'!$A:$BP,펀드현황!G$2,0) -> 44839 | H8: =VLOOKUP($C8,'MOS4110'!$A:$BP,펀드현황!H$2,0) -> 1204.52 | I8: =VLOOKUP($C8,'MOS4110'!$A:$BP,펀드현황!I$2,0) -> 2.2036 | J8: =VLOOKUP($C8,'MOS4110'!$A:$BP,펀드현황!J$2,0) -> 8.8773 | K8: =VLOOKUP($C8,'MOS4110'!$A:$BP,펀드현황!K$2,0) -> 11.6834 | L8: =VLOOKUP($C8,'MOS4110'!$A:$BP,펀드현황!L$2,0) -> 19.6567 | O8: =VLOOKUP($C8,'MOS4110'!$A:$BP,펀드현황!O$2,0) -> 4.9974 | P8: =VLOOKUP($C8,'MOS4110'!$A:$BP,펀드현황!P$2,0) -> 21.5461 | T8: =C8 -> 07J81 | V8: =IFERROR( ( SUMIFS(설정해지!$G:$G, 설정해지!$B:$B,펀드현황!$C8,설정해지!$F:$F,"KRW")-SUMIFS(설정해지!$H:$H, 설정해지!$B:$B,펀드현황!$C8,설정해지!$F:$F,"KRW") ) /100000000,"") -> -0.32146014 | W8: =IFERROR( ( SUMIFS(설정해지!$I:$I, 설정해지!$B:$B,펀드현황!$C8,설정해지!$F:$F,"KRW")-SUMIFS(설정해지!$J:$J, 설정해지!$B:$B,펀드현황!$C8,설정해지!$F:$F,"KRW") ) /100000000,"") -> 0.39074346 | X8: =IFERROR( ( SUMIFS(설정해지!$K:$K, 설정해지!$B:$B,펀드현황!$C8,설정해지!$F:$F,"KRW")-SUMIFS(설정해지!$L:$L, 설정해지!$B:$B,펀드현황!$C8,설정해지!$F:$F,"KRW") ) /100000000,"") -> 0 | Z8: =IFERROR( ( SUMIFS(자금총괄!$G:$G, 자금총괄!$B:$B,펀드현황!$C8,자금총괄!$F:$F,$AB$2) ) /100000000,"") -> 1.8607045 | AA8: =Z8/F8 -> 0.030824064 | AB8: =IFERROR( ( SUMIFS(자금총괄!$I:$I, 자금총괄!$B:$B,펀드현황!$C8,자금총괄!$F:$F,$AB$2) ) /100000000,"") -> 2.1445821 | AC8: =IFERROR( ( SUMIFS(자금총괄!$K:$K, 자금총괄!$B:$B,펀드현황!$C8,자금총괄!$F:$F,$AB$2) ) /100000000,"") -> 2.1445821 | AD8: =IFERROR( ( SUMIFS(자금총괄!$M:$M, 자금총괄!$B:$B,펀드현황!$C8,자금총괄!$F:$F,$AB$2) ) /100000000,"") -> 2.0967957 | AE8: =IFERROR( ( SUMIFS(자금총괄!$O:$O, 자금총괄!$B:$B,펀드현황!$C8,자금총괄!$F:$F,$AB$2) ) /100000000,"") -> 2.0967957 | AF8: =IFERROR( ( SUMIFS(자금총괄!$Q:$Q, 자금총괄!$B:$B,펀드현황!$C8,자금총괄!$F:$F,$AB$2) ) /100000000,"") -> 2.0548771 | AH8: =IFERROR( ( SUMIFS(자금총괄!$G:$G, 자금총괄!$B:$B,펀드현황!$C8,자금총괄!$F:$F,$AI$2)/10000 ),"") -> 0.892059 | AI8: =IFERROR( ( SUMIFS(자금총괄!$I:$I, 자금총괄!$B:$B,펀드현황!$C8,자금총괄!$F:$F,$AI$2)/10000 ),"") -> 0.739509 | AJ8: =IFERROR((SUMIFS(자금총괄!$K:$K,자금총괄!$B:$B,펀드현황!$C8,자금총괄!$F:$F,$AI$2)/10000),"") -> 0.739509 | AK8: =IFERROR((SUMIFS(자금총괄!$M:$M,자금총괄!$B:$B,펀드현황!$C8,자금총괄!$F:$F,$AI$2)/10000),"") -> 0.739509 | AL8: =IFERROR( ( SUMIFS(자금총괄!$O:$O, 자금총괄!$B:$B,펀드현황!$C8,자금총괄!$F:$F,$AI$2) /10000 ),"") -> 0.739509 | AM8: =IFERROR( ( SUMIFS(자금총괄!$Q:$Q, 자금총괄!$B:$B,펀드현황!$C8,자금총괄!$F:$F,$AI$2) /10000 ),"") -> 0.739509
C9: 07J86 | D9: TDF포커스 2050 | E9: =AVERAGEIFS(#REF!,#REF!,펀드현황!$C9)/100000000 -> #REF! | F9: =IFERROR(VLOOKUP($T9,자금총괄!$B:$E,4,0)/100000000,"") -> 111.81497 | G9: =VLOOKUP($C9,'MOS4110'!$A:$BP,펀드현황!G$2,0) -> 44839 | H9: =VLOOKUP($C9,'MOS4110'!$A:$BP,펀드현황!H$2,0) -> 1211.24 | I9: =VLOOKUP($C9,'MOS4110'!$A:$BP,펀드현황!I$2,0) -> 2.3335 | J9: =VLOOKUP($C9,'MOS4110'!$A:$BP,펀드현황!J$2,0) -> 9.3443 | K9: =VLOOKUP($C9,'MOS4110'!$A:$BP,펀드현황!K$2,0) -> 12.239 | L9: =VLOOKUP($C9,'MOS4110'!$A:$BP,펀드현황!L$2,0) -> 20.8402 | O9: =VLOOKUP($C9,'MOS4110'!$A:$BP,펀드현황!O$2,0) -> 5.4169 | P9: =VLOOKUP($C9,'MOS4110'!$A:$BP,펀드현황!P$2,0) -> 22.318 | T9: =C9 -> 07J86 | V9: =IFERROR( ( SUMIFS(설정해지!$G:$G, 설정해지!$B:$B,펀드현황!$C9,설정해지!$F:$F,"KRW")-SUMIFS(설정해지!$H:$H, 설정해지!$B:$B,펀드현황!$C9,설정해지!$F:$F,"KRW") ) /100000000,"") -> 2.8095287 | W9: =IFERROR( ( SUMIFS(설정해지!$I:$I, 설정해지!$B:$B,펀드현황!$C9,설정해지!$F:$F,"KRW")-SUMIFS(설정해지!$J:$J, 설정해지!$B:$B,펀드현황!$C9,설정해지!$F:$F,"KRW") ) /100000000,"") -> 1.4686764 | X9: =IFERROR( ( SUMIFS(설정해지!$K:$K, 설정해지!$B:$B,펀드현황!$C9,설정해지!$F:$F,"KRW")-SUMIFS(설정해지!$L:$L, 설정해지!$B:$B,펀드현황!$C9,설정해지!$F:$F,"KRW") ) /100000000,"") -> -0.0608907 | Z9: =IFERROR( ( SUMIFS(자금총괄!$G:$G, 자금총괄!$B:$B,펀드현황!$C9,자금총괄!$F:$F,$AB$2) ) /100000000,"") -> 7.5579431 | AA9: =Z9/F9 -> 0.067593302 | AB9: =IFERROR( ( SUMIFS(자금총괄!$I:$I, 자금총괄!$B:$B,펀드현황!$C9,자금총괄!$F:$F,$AB$2) ) /100000000,"") -> 6.9585463 | AC9: =IFERROR( ( SUMIFS(자금총괄!$K:$K, 자금총괄!$B:$B,펀드현황!$C9,자금총괄!$F:$F,$AB$2) ) /100000000,"") -> 6.8976556 | AD9: =IFERROR( ( SUMIFS(자금총괄!$M:$M, 자금총괄!$B:$B,펀드현황!$C9,자금총괄!$F:$F,$AB$2) ) /100000000,"") -> 5.5652163 | AE9: =IFERROR( ( SUMIFS(자금총괄!$O:$O, 자금총괄!$B:$B,펀드현황!$C9,자금총괄!$F:$F,$AB$2) ) /100000000,"") -> 5.5049144 | AF9: =IFERROR( ( SUMIFS(자금총괄!$Q:$Q, 자금총괄!$B:$B,펀드현황!$C9,자금총괄!$F:$F,$AB$2) ) /100000000,"") -> 5.45818 | AH9: =IFERROR( ( SUMIFS(자금총괄!$G:$G, 자금총괄!$B:$B,펀드현황!$C9,자금총괄!$F:$F,$AI$2)/10000 ),"") -> 1.606253 | AI9: =IFERROR( ( SUMIFS(자금총괄!$I:$I, 자금총괄!$B:$B,펀드현황!$C9,자금총괄!$F:$F,$AI$2)/10000 ),"") -> 2.32099 | AJ9: =IFERROR((SUMIFS(자금총괄!$K:$K,자금총괄!$B:$B,펀드현황!$C9,자금총괄!$F:$F,$AI$2)/10000),"") -> 2.32099 | AK9: =IFERROR((SUMIFS(자금총괄!$M:$M,자금총괄!$B:$B,펀드현황!$C9,자금총괄!$F:$F,$AI$2)/10000),"") -> 2.32099 | AL9: =IFERROR( ( SUMIFS(자금총괄!$O:$O, 자금총괄!$B:$B,펀드현황!$C9,자금총괄!$F:$F,$AI$2) /10000 ),"") -> 2.32099 | AM9: =IFERROR( ( SUMIFS(자금총괄!$Q:$Q, 자금총괄!$B:$B,펀드현황!$C9,자금총괄!$F:$F,$AI$2) /10000 ),"") -> 2.32099
C10: 07J91 | D10: TDF포커스 2055 | E10: =AVERAGEIFS(#REF!,#REF!,펀드현황!$C10)/100000000 -> #REF! | F10: =IFERROR(VLOOKUP($T10,자금총괄!$B:$E,4,0)/100000000,"") -> 62.690552 | G10: =VLOOKUP($C10,'MOS4110'!$A:$BP,펀드현황!G$2,0) -> 44839 | H10: =VLOOKUP($C10,'MOS4110'!$A:$BP,펀드현황!H$2,0) -> 1218.19 | I10: =VLOOKUP($C10,'MOS4110'!$A:$BP,펀드현황!I$2,0) -> 2.4929 | J10: =VLOOKUP($C10,'MOS4110'!$A:$BP,펀드현황!J$2,0) -> 9.7686 | K10: =VLOOKUP($C10,'MOS4110'!$A:$BP,펀드현황!K$2,0) -> 12.7369 | L10: =VLOOKUP($C10,'MOS4110'!$A:$BP,펀드현황!L$2,0) -> 21.8882 | O10: =VLOOKUP($C10,'MOS4110'!$A:$BP,펀드현황!O$2,0) -> 5.832 | P10: =VLOOKUP($C10,'MOS4110'!$A:$BP,펀드현황!P$2,0) -> 23.0839 | T10: =C10 -> 07J91 | V10: =IFERROR( ( SUMIFS(설정해지!$G:$G, 설정해지!$B:$B,펀드현황!$C10,설정해지!$F:$F,"KRW")-SUMIFS(설정해지!$H:$H, 설정해지!$B:$B,펀드현황!$C10,설정해지!$F:$F,"KRW") ) /100000000,"") -> 0.5496819 | W10: =IFERROR( ( SUMIFS(설정해지!$I:$I, 설정해지!$B:$B,펀드현황!$C10,설정해지!$F:$F,"KRW")-SUMIFS(설정해지!$J:$J, 설정해지!$B:$B,펀드현황!$C10,설정해지!$F:$F,"KRW") ) /100000000,"") -> 0.14821533 | X10: =IFERROR( ( SUMIFS(설정해지!$K:$K, 설정해지!$B:$B,펀드현황!$C10,설정해지!$F:$F,"KRW")-SUMIFS(설정해지!$L:$L, 설정해지!$B:$B,펀드현황!$C10,설정해지!$F:$F,"KRW") ) /100000000,"") -> 0 | Z10: =IFERROR( ( SUMIFS(자금총괄!$G:$G, 자금총괄!$B:$B,펀드현황!$C10,자금총괄!$F:$F,$AB$2) ) /100000000,"") -> 2.3884554 | AA10: =Z10/F10 -> 0.038099128 | AB10: =IFERROR( ( SUMIFS(자금총괄!$I:$I, 자금총괄!$B:$B,펀드현황!$C10,자금총괄!$F:$F,$AB$2) ) /100000000,"") -> 2.1439133 | AC10: =IFERROR( ( SUMIFS(자금총괄!$K:$K, 자금총괄!$B:$B,펀드현황!$C10,자금총괄!$F:$F,$AB$2) ) /100000000,"") -> 2.1439133 | AD10: =IFERROR( ( SUMIFS(자금총괄!$M:$M, 자금총괄!$B:$B,펀드현황!$C10,자금총괄!$F:$F,$AB$2) ) /100000000,"") -> 2.1439133 | AE10: =IFERROR( ( SUMIFS(자금총괄!$O:$O, 자금총괄!$B:$B,펀드현황!$C10,자금총괄!$F:$F,$AB$2) ) /100000000,"") -> 2.1439133 | AF10: =IFERROR( ( SUMIFS(자금총괄!$Q:$Q, 자금총괄!$B:$B,펀드현황!$C10,자금총괄!$F:$F,$AB$2) ) /100000000,"") -> 2.1390011 | AH10: =IFERROR( ( SUMIFS(자금총괄!$G:$G, 자금총괄!$B:$B,펀드현황!$C10,자금총괄!$F:$F,$AI$2)/10000 ),"") -> 0.983533 | AI10: =IFERROR( ( SUMIFS(자금총괄!$I:$I, 자금총괄!$B:$B,펀드현황!$C10,자금총괄!$F:$F,$AI$2)/10000 ),"") -> 0.901686 | AJ10: =IFERROR((SUMIFS(자금총괄!$K:$K,자금총괄!$B:$B,펀드현황!$C10,자금총괄!$F:$F,$AI$2)/10000),"") -> 0.901686 | AK10: =IFERROR((SUMIFS(자금총괄!$M:$M,자금총괄!$B:$B,펀드현황!$C10,자금총괄!$F:$F,$AI$2)/10000),"") -> 0.901686 | AL10: =IFERROR( ( SUMIFS(자금총괄!$O:$O, 자금총괄!$B:$B,펀드현황!$C10,자금총괄!$F:$F,$AI$2) /10000 ),"") -> 0.901686 | AM10: =IFERROR( ( SUMIFS(자금총괄!$Q:$Q, 자금총괄!$B:$B,펀드현황!$C10,자금총괄!$F:$F,$AI$2) /10000 ),"") -> 0.901686
C11: 07J96 | D11: TDF포커스 2060 | E11: =AVERAGEIFS(#REF!,#REF!,펀드현황!$C11)/100000000 -> #REF! | F11: =IFERROR(VLOOKUP($T11,자금총괄!$B:$E,4,0)/100000000,"") -> 140.11785 | G11: =VLOOKUP($C11,'MOS4110'!$A:$BP,펀드현황!G$2,0) -> 44839 | H11: =VLOOKUP($C11,'MOS4110'!$A:$BP,펀드현황!H$2,0) -> 1220.89 | I11: =VLOOKUP($C11,'MOS4110'!$A:$BP,펀드현황!I$2,0) -> 2.5958 | J11: =VLOOKUP($C11,'MOS4110'!$A:$BP,펀드현황!J$2,0) -> 10.0734 | K11: =VLOOKUP($C11,'MOS4110'!$A:$BP,펀드현황!K$2,0) -> 13.1373 | L11: =VLOOKUP($C11,'MOS4110'!$A:$BP,펀드현황!L$2,0) -> 22.4488 | O11: =VLOOKUP($C11,'MOS4110'!$A:$BP,펀드현황!O$2,0) -> 6.1247 | P11: =VLOOKUP($C11,'MOS4110'!$A:$BP,펀드현황!P$2,0) -> 23.4271 | T11: =C11 -> 07J96 | V11: =IFERROR( ( SUMIFS(설정해지!$G:$G, 설정해지!$B:$B,펀드현황!$C11,설정해지!$F:$F,"KRW")-SUMIFS(설정해지!$H:$H, 설정해지!$B:$B,펀드현황!$C11,설정해지!$F:$F,"KRW") ) /100000000,"") -> 1.4790166 | W11: =IFERROR( ( SUMIFS(설정해지!$I:$I, 설정해지!$B:$B,펀드현황!$C11,설정해지!$F:$F,"KRW")-SUMIFS(설정해지!$J:$J, 설정해지!$B:$B,펀드현황!$C11,설정해지!$F:$F,"KRW") ) /100000000,"") -> 1.2556603 | X11: =IFERROR( ( SUMIFS(설정해지!$K:$K, 설정해지!$B:$B,펀드현황!$C11,설정해지!$F:$F,"KRW")-SUMIFS(설정해지!$L:$L, 설정해지!$B:$B,펀드현황!$C11,설정해지!$F:$F,"KRW") ) /100000000,"") -> -0.67666634 | Z11: =IFERROR( ( SUMIFS(자금총괄!$G:$G, 자금총괄!$B:$B,펀드현황!$C11,자금총괄!$F:$F,$AB$2) ) /100000000,"") -> 7.466445 | AA11: =Z11/F11 -> 0.053286896 | AB11: =IFERROR( ( SUMIFS(자금총괄!$I:$I, 자금총괄!$B:$B,펀드현황!$C11,자금총괄!$F:$F,$AB$2) ) /100000000,"") -> 6.8197958 | AC11: =IFERROR( ( SUMIFS(자금총괄!$K:$K, 자금총괄!$B:$B,펀드현황!$C11,자금총괄!$F:$F,$AB$2) ) /100000000,"") -> 6.1431295 | AD11: =IFERROR( ( SUMIFS(자금총괄!$M:$M, 자금총괄!$B:$B,펀드현황!$C11,자금총괄!$F:$F,$AB$2) ) /100000000,"") -> 6.1237522 | AE11: =IFERROR( ( SUMIFS(자금총괄!$O:$O, 자금총괄!$B:$B,펀드현황!$C11,자금총괄!$F:$F,$AB$2) ) /100000000,"") -> 6.0763419 | AF11: =IFERROR( ( SUMIFS(자금총괄!$Q:$Q, 자금총괄!$B:$B,펀드현황!$C11,자금총괄!$F:$F,$AB$2) ) /100000000,"") -> 5.6725649 | AH11: =IFERROR( ( SUMIFS(자금총괄!$G:$G, 자금총괄!$B:$B,펀드현황!$C11,자금총괄!$F:$F,$AI$2)/10000 ),"") -> 1.943294 | AI11: =IFERROR( ( SUMIFS(자금총괄!$I:$I, 자금총괄!$B:$B,펀드현황!$C11,자금총괄!$F:$F,$AI$2)/10000 ),"") -> 2.406327 | AJ11: =IFERROR((SUMIFS(자금총괄!$K:$K,자금총괄!$B:$B,펀드현황!$C11,자금총괄!$F:$F,$AI$2)/10000),"") -> 2.406327 | AK11: =IFERROR((SUMIFS(자금총괄!$M:$M,자금총괄!$B:$B,펀드현황!$C11,자금총괄!$F:$F,$AI$2)/10000),"") -> 2.406327 | AL11: =IFERROR( ( SUMIFS(자금총괄!$O:$O, 자금총괄!$B:$B,펀드현황!$C11,자금총괄!$F:$F,$AI$2) /10000 ),"") -> 2.406327 | AM11: =IFERROR( ( SUMIFS(자금총괄!$Q:$Q, 자금총괄!$B:$B,펀드현황!$C11,자금총괄!$F:$F,$AI$2) /10000 ),"") -> 2.406327
D12: TDF포커스 합계 | E12: =SUM(E4:E11) -> #REF! | F12: =SUM(F4:F11) -> 809.04165 | V12: =IFERROR( ( SUMIFS(설정해지!$G:$G, 설정해지!$B:$B,펀드현황!$C12,설정해지!$F:$F,"KRW")-SUMIFS(설정해지!$H:$H, 설정해지!$B:$B,펀드현황!$C12,설정해지!$F:$F,"KRW") ) /100000000,"") -> 0 | W12: =IFERROR( ( SUMIFS(설정해지!$I:$I, 설정해지!$B:$B,펀드현황!$C12,설정해지!$F:$F,"KRW")-SUMIFS(설정해지!$J:$J, 설정해지!$B:$B,펀드현황!$C12,설정해지!$F:$F,"KRW") ) /100000000,"") -> 0 | X12: =IFERROR( ( SUMIFS(설정해지!$K:$K, 설정해지!$B:$B,펀드현황!$C12,설정해지!$F:$F,"KRW")-SUMIFS(설정해지!$L:$L, 설정해지!$B:$B,펀드현황!$C12,설정해지!$F:$F,"KRW") ) /100000000,"") -> 0 | Z12: =IFERROR( ( SUMIFS(자금총괄!$G:$G, 자금총괄!$B:$B,펀드현황!$C12,자금총괄!$F:$F,$AB$2) ) /100000000,"") -> 0 | AB12: =IFERROR( ( SUMIFS(자금총괄!$I:$I, 자금총괄!$B:$B,펀드현황!$C12,자금총괄!$F:$F,$AB$2) ) /100000000,"") -> 0 | AC12: =IFERROR( ( SUMIFS(자금총괄!$K:$K, 자금총괄!$B:$B,펀드현황!$C12,자금총괄!$F:$F,$AB$2) ) /100000000,"") -> 0 | AD12: =IFERROR( ( SUMIFS(자금총괄!$M:$M, 자금총괄!$B:$B,펀드현황!$C12,자금총괄!$F:$F,$AB$2) ) /100000000,"") -> 0 | AE12: =IFERROR( ( SUMIFS(자금총괄!$O:$O, 자금총괄!$B:$B,펀드현황!$C12,자금총괄!$F:$F,$AB$2) ) /100000000,"") -> 0 | AF12: =IFERROR( ( SUMIFS(자금총괄!$Q:$Q, 자금총괄!$B:$B,펀드현황!$C12,자금총괄!$F:$F,$AB$2) ) /100000000,"") -> 0 | AH12: =IFERROR( ( SUMIFS(자금총괄!$G:$G, 자금총괄!$B:$B,펀드현황!$C12,자금총괄!$F:$F,$AI$2)/10000 ),"") -> 0 | AI12: =IFERROR( ( SUMIFS(자금총괄!$I:$I, 자금총괄!$B:$B,펀드현황!$C12,자금총괄!$F:$F,$AI$2)/10000 ),"") -> 0 | AJ12: =IFERROR((SUMIFS(자금총괄!$K:$K,자금총괄!$B:$B,펀드현황!$C12,자금총괄!$F:$F,$AI$2)/10000),"") -> 0 | AK12: =IFERROR((SUMIFS(자금총괄!$M:$M,자금총괄!$B:$B,펀드현황!$C12,자금총괄!$F:$F,$AI$2)/10000),"") -> 0 | AL12: =IFERROR( ( SUMIFS(자금총괄!$O:$O, 자금총괄!$B:$B,펀드현황!$C12,자금총괄!$F:$F,$AI$2) /10000 ),"") -> 0 | AM12: =IFERROR( ( SUMIFS(자금총괄!$Q:$Q, 자금총괄!$B:$B,펀드현황!$C12,자금총괄!$F:$F,$AI$2) /10000 ),"") -> 0
V13: =IFERROR( ( SUMIFS(설정해지!$G:$G, 설정해지!$B:$B,펀드현황!$C13,설정해지!$F:$F,"KRW")-SUMIFS(설정해지!$H:$H, 설정해지!$B:$B,펀드현황!$C13,설정해지!$F:$F,"KRW") ) /100000000,"") -> 0 | W13: =IFERROR( ( SUMIFS(설정해지!$I:$I, 설정해지!$B:$B,펀드현황!$C13,설정해지!$F:$F,"KRW")-SUMIFS(설정해지!$J:$J, 설정해지!$B:$B,펀드현황!$C13,설정해지!$F:$F,"KRW") ) /100000000,"") -> 0 | X13: =IFERROR( ( SUMIFS(설정해지!$K:$K, 설정해지!$B:$B,펀드현황!$C13,설정해지!$F:$F,"KRW")-SUMIFS(설정해지!$L:$L, 설정해지!$B:$B,펀드현황!$C13,설정해지!$F:$F,"KRW") ) /100000000,"") -> 0 | Z13: =IFERROR( ( SUMIFS(자금총괄!$G:$G, 자금총괄!$B:$B,펀드현황!$C13,자금총괄!$F:$F,$AB$2) ) /100000000,"") -> 0 | AB13: =IFERROR( ( SUMIFS(자금총괄!$I:$I, 자금총괄!$B:$B,펀드현황!$C13,자금총괄!$F:$F,$AB$2) ) /100000000,"") -> 0 | AC13: =IFERROR( ( SUMIFS(자금총괄!$K:$K, 자금총괄!$B:$B,펀드현황!$C13,자금총괄!$F:$F,$AB$2) ) /100000000,"") -> 0 | AD13: =IFERROR( ( SUMIFS(자금총괄!$M:$M, 자금총괄!$B:$B,펀드현황!$C13,자금총괄!$F:$F,$AB$2) ) /100000000,"") -> 0 | AE13: =IFERROR( ( SUMIFS(자금총괄!$O:$O, 자금총괄!$B:$B,펀드현황!$C13,자금총괄!$F:$F,$AB$2) ) /100000000,"") -> 0 | AF13: =IFERROR( ( SUMIFS(자금총괄!$Q:$Q, 자금총괄!$B:$B,펀드현황!$C13,자금총괄!$F:$F,$AB$2) ) /100000000,"") -> 0 | AH13: =IFERROR( ( SUMIFS(자금총괄!$G:$G, 자금총괄!$B:$B,펀드현황!$C13,자금총괄!$F:$F,$AI$2)/10000 ),"") -> 0 | AI13: =IFERROR( ( SUMIFS(자금총괄!$I:$I, 자금총괄!$B:$B,펀드현황!$C13,자금총괄!$F:$F,$AI$2)/10000 ),"") -> 0 | AJ13: =IFERROR((SUMIFS(자금총괄!$K:$K,자금총괄!$B:$B,펀드현황!$C13,자금총괄!$F:$F,$AI$2)/10000),"") -> 0 | AK13: =IFERROR((SUMIFS(자금총괄!$M:$M,자금총괄!$B:$B,펀드현황!$C13,자금총괄!$F:$F,$AI$2)/10000),"") -> 0 | AL13: =IFERROR( ( SUMIFS(자금총괄!$O:$O, 자금총괄!$B:$B,펀드현황!$C13,자금총괄!$F:$F,$AI$2) /10000 ),"") -> 0 | AM13: =IFERROR( ( SUMIFS(자금총괄!$Q:$Q, 자금총괄!$B:$B,펀드현황!$C13,자금총괄!$F:$F,$AI$2) /10000 ),"") -> 0
B14: TRP TDF | C14: 05C16 | D14: =VLOOKUP(C14,'MOS4110'!$A:$B,2,0) -> 한국투자TDF알아서2020증권자투자신탁(채권혼합-재간접형)(모) | E14: =AVERAGEIFS(#REF!,#REF!,펀드현황!$C14)/100000000 -> #REF! | F14: =IFERROR(VLOOKUP($T14,자금총괄!$B:$E,4,0)/100000000,"") -> 634.28726 | G14: =VLOOKUP($C14,'MOS4110'!$A:$BP,펀드현황!G$2,0) -> 42796 | H14: =VLOOKUP($C14,'MOS4110'!$A:$BP,펀드현황!H$2,0) -> 1329.98 | I14: =VLOOKUP($C14,'MOS4110'!$A:$BP,펀드현황!I$2,0) -> 1.3527 | J14: =VLOOKUP($C14,'MOS4110'!$A:$BP,펀드현황!J$2,0) -> 5.637 | K14: =VLOOKUP($C14,'MOS4110'!$A:$BP,펀드현황!K$2,0) -> 6.5382 | L14: =VLOOKUP($C14,'MOS4110'!$A:$BP,펀드현황!L$2,0) -> 9.0636 | M14: =VLOOKUP($C14,'MOS4110'!$A:$BP,펀드현황!M$2,0) -> 3.4143 | N14: =VLOOKUP($C14,'MOS4110'!$A:$BP,펀드현황!N$2,0) -> -0.6723 | ... P14: =VLOOKUP($C14,'MOS4110'!$A:$BP,펀드현황!P$2,0) -> 34.9304 | S14: TDF/TIF | T14: =C14 -> 05C16 | V14: =IFERROR( ( SUMIFS(설정해지!$G:$G, 설정해지!$B:$B,펀드현황!$C14,설정해지!$F:$F,"KRW")-SUMIFS(설정해지!$H:$H, 설정해지!$B:$B,펀드현황!$C14,설정해지!$F:$F,"KRW") ) /100000000,"") -> 0.02116263 | W14: =IFERROR( ( SUMIFS(설정해지!$I:$I, 설정해지!$B:$B,펀드현황!$C14,설정해지!$F:$F,"KRW")-SUMIFS(설정해지!$J:$J, 설정해지!$B:$B,펀드현황!$C14,설정해지!$F:$F,"KRW") ) /100000000,"") -> -0.02402604 | X14: =IFERROR( ( SUMIFS(설정해지!$K:$K, 설정해지!$B:$B,펀드현황!$C14,설정해지!$F:$F,"KRW")-SUMIFS(설정해지!$L:$L, 설정해지!$B:$B,펀드현황!$C14,설정해지!$F:$F,"KRW") ) /100000000,"") -> -1.4511601 | Z14: =IFERROR( ( SUMIFS(자금총괄!$G:$G, 자금총괄!$B:$B,펀드현황!$C14,자금총괄!$F:$F,$AB$2) ) /100000000,"") -> 8.2981852 | AA14: =Z14/F14 -> 0.013082693 | AB14: =IFERROR( ( SUMIFS(자금총괄!$I:$I, 자금총괄!$B:$B,펀드현황!$C14,자금총괄!$F:$F,$AB$2) ) /100000000,"") -> 8.3323115 | AC14: =IFERROR( ( SUMIFS(자금총괄!$K:$K, 자금총괄!$B:$B,펀드현황!$C14,자금총괄!$F:$F,$AB$2) ) /100000000,"") -> 7.5150821 | AD14: =IFERROR( ( SUMIFS(자금총괄!$M:$M, 자금총괄!$B:$B,펀드현황!$C14,자금총괄!$F:$F,$AB$2) ) /100000000,"") -> 7.5426212 | AE14: =IFERROR( ( SUMIFS(자금총괄!$O:$O, 자금총괄!$B:$B,펀드현황!$C14,자금총괄!$F:$F,$AB$2) ) /100000000,"") -> 7.5852505 | AF14: =IFERROR( ( SUMIFS(자금총괄!$Q:$Q, 자금총괄!$B:$B,펀드현황!$C14,자금총괄!$F:$F,$AB$2) ) /100000000,"") -> 7.6169705 | AH14: =IFERROR( ( SUMIFS(자금총괄!$G:$G, 자금총괄!$B:$B,펀드현황!$C14,자금총괄!$F:$F,$AI$2)/10000 ),"") -> 0 | AI14: =IFERROR( ( SUMIFS(자금총괄!$I:$I, 자금총괄!$B:$B,펀드현황!$C14,자금총괄!$F:$F,$AI$2)/10000 ),"") -> 0 | AJ14: =IFERROR((SUMIFS(자금총괄!$K:$K,자금총괄!$B:$B,펀드현황!$C14,자금총괄!$F:$F,$AI$2)/10000),"") -> 0 | AK14: =IFERROR((SUMIFS(자금총괄!$M:$M,자금총괄!$B:$B,펀드현황!$C14,자금총괄!$F:$F,$AI$2)/10000),"") -> 0 | AL14: =IFERROR( ( SUMIFS(자금총괄!$O:$O, 자금총괄!$B:$B,펀드현황!$C14,자금총괄!$F:$F,$AI$2) /10000 ),"") -> 0 | AM14: =IFERROR( ( SUMIFS(자금총괄!$Q:$Q, 자금총괄!$B:$B,펀드현황!$C14,자금총괄!$F:$F,$AI$2) /10000 ),"") -> 0
C15: 05K82 | D15: =VLOOKUP(C15,'MOS4110'!$A:$B,2,0) -> 한국투자신종개인연금TDF알아서2020증권자투자신탁(채권혼합-재 | E15: =AVERAGEIFS(#REF!,#REF!,펀드현황!$C15)/100000000 -> #REF! | F15: =IFERROR(VLOOKUP($T15,자금총괄!$B:$E,4,0)/100000000,"") -> 172.9328 | G15: =VLOOKUP($C15,'MOS4110'!$A:$BP,펀드현황!G$2,0) -> 42970 | H15: =VLOOKUP($C15,'MOS4110'!$A:$BP,펀드현황!H$2,0) -> 973.21 | I15: =VLOOKUP($C15,'MOS4110'!$A:$BP,펀드현황!I$2,0) -> 1.3528 | J15: =VLOOKUP($C15,'MOS4110'!$A:$BP,펀드현황!J$2,0) -> 5.6425 | K15: =VLOOKUP($C15,'MOS4110'!$A:$BP,펀드현황!K$2,0) -> 6.5469 | L15: =VLOOKUP($C15,'MOS4110'!$A:$BP,펀드현황!L$2,0) -> 9.0725 | M15: =VLOOKUP($C15,'MOS4110'!$A:$BP,펀드현황!M$2,0) -> 3.3779 | N15: =VLOOKUP($C15,'MOS4110'!$A:$BP,펀드현황!N$2,0) -> -0.727 | ... P15: =VLOOKUP($C15,'MOS4110'!$A:$BP,펀드현황!P$2,0) -> 27.7214 | T15: =C15 -> 05K82 | V15: =IFERROR( ( SUMIFS(설정해지!$G:$G, 설정해지!$B:$B,펀드현황!$C15,설정해지!$F:$F,"KRW")-SUMIFS(설정해지!$H:$H, 설정해지!$B:$B,펀드현황!$C15,설정해지!$F:$F,"KRW") ) /100000000,"") -> -0.00624195 | W15: =IFERROR( ( SUMIFS(설정해지!$I:$I, 설정해지!$B:$B,펀드현황!$C15,설정해지!$F:$F,"KRW")-SUMIFS(설정해지!$J:$J, 설정해지!$B:$B,펀드현황!$C15,설정해지!$F:$F,"KRW") ) /100000000,"") -> -0.80452006 | X15: =IFERROR( ( SUMIFS(설정해지!$K:$K, 설정해지!$B:$B,펀드현황!$C15,설정해지!$F:$F,"KRW")-SUMIFS(설정해지!$L:$L, 설정해지!$B:$B,펀드현황!$C15,설정해지!$F:$F,"KRW") ) /100000000,"") -> 0 | Z15: =IFERROR( ( SUMIFS(자금총괄!$G:$G, 자금총괄!$B:$B,펀드현황!$C15,자금총괄!$F:$F,$AB$2) ) /100000000,"") -> 2.2171244 | AA15: =Z15/F15 -> 0.012820728 | AB15: =IFERROR( ( SUMIFS(자금총괄!$I:$I, 자금총괄!$B:$B,펀드현황!$C15,자금총괄!$F:$F,$AB$2) ) /100000000,"") -> 2.244998 | AC15: =IFERROR( ( SUMIFS(자금총괄!$K:$K, 자금총괄!$B:$B,펀드현황!$C15,자금총괄!$F:$F,$AB$2) ) /100000000,"") -> 2.244998 | AD15: =IFERROR( ( SUMIFS(자금총괄!$M:$M, 자금총괄!$B:$B,펀드현황!$C15,자금총괄!$F:$F,$AB$2) ) /100000000,"") -> 2.244998 | AE15: =IFERROR( ( SUMIFS(자금총괄!$O:$O, 자금총괄!$B:$B,펀드현황!$C15,자금총괄!$F:$F,$AB$2) ) /100000000,"") -> 2.2459769 | AF15: =IFERROR( ( SUMIFS(자금총괄!$Q:$Q, 자금총괄!$B:$B,펀드현황!$C15,자금총괄!$F:$F,$AB$2) ) /100000000,"") -> 2.2463947 | AH15: =IFERROR( ( SUMIFS(자금총괄!$G:$G, 자금총괄!$B:$B,펀드현황!$C15,자금총괄!$F:$F,$AI$2)/10000 ),"") -> 0 | AI15: =IFERROR( ( SUMIFS(자금총괄!$I:$I, 자금총괄!$B:$B,펀드현황!$C15,자금총괄!$F:$F,$AI$2)/10000 ),"") -> 0 | AJ15: =IFERROR((SUMIFS(자금총괄!$K:$K,자금총괄!$B:$B,펀드현황!$C15,자금총괄!$F:$F,$AI$2)/10000),"") -> 0 | AK15: =IFERROR((SUMIFS(자금총괄!$M:$M,자금총괄!$B:$B,펀드현황!$C15,자금총괄!$F:$F,$AI$2)/10000),"") -> 0 | AL15: =IFERROR( ( SUMIFS(자금총괄!$O:$O, 자금총괄!$B:$B,펀드현황!$C15,자금총괄!$F:$F,$AI$2) /10000 ),"") -> 0 | AM15: =IFERROR( ( SUMIFS(자금총괄!$Q:$Q, 자금총괄!$B:$B,펀드현황!$C15,자금총괄!$F:$F,$AI$2) /10000 ),"") -> 0
C16: 05C30 | D16: =VLOOKUP(C16,'MOS4110'!$A:$B,2,0) -> 한국투자TDF알아서2025증권투자신탁(주식혼합-재간접형)(모) | E16: =AVERAGEIFS(#REF!,#REF!,펀드현황!$C16)/100000000 -> #REF! | F16: =IFERROR(VLOOKUP($T16,자금총괄!$B:$E,4,0)/100000000,"") -> 1367.042 | G16: =VLOOKUP($C16,'MOS4110'!$A:$BP,펀드현황!G$2,0) -> 42796 | H16: =VLOOKUP($C16,'MOS4110'!$A:$BP,펀드현황!H$2,0) -> 1363.72 | I16: =VLOOKUP($C16,'MOS4110'!$A:$BP,펀드현황!I$2,0) -> 1.462 | J16: =VLOOKUP($C16,'MOS4110'!$A:$BP,펀드현황!J$2,0) -> 5.8542 | K16: =VLOOKUP($C16,'MOS4110'!$A:$BP,펀드현황!K$2,0) -> 6.7742 | L16: =VLOOKUP($C16,'MOS4110'!$A:$BP,펀드현황!L$2,0) -> 9.6236 | M16: =VLOOKUP($C16,'MOS4110'!$A:$BP,펀드현황!M$2,0) -> 3.9481 | N16: =VLOOKUP($C16,'MOS4110'!$A:$BP,펀드현황!N$2,0) -> -0.5115 | ... P16: =VLOOKUP($C16,'MOS4110'!$A:$BP,펀드현황!P$2,0) -> 38.2916 | T16: =C16 -> 05C30 | V16: =IFERROR( ( SUMIFS(설정해지!$G:$G, 설정해지!$B:$B,펀드현황!$C16,설정해지!$F:$F,"KRW")-SUMIFS(설정해지!$H:$H, 설정해지!$B:$B,펀드현황!$C16,설정해지!$F:$F,"KRW") ) /100000000,"") -> -19.319884 | W16: =IFERROR( ( SUMIFS(설정해지!$I:$I, 설정해지!$B:$B,펀드현황!$C16,설정해지!$F:$F,"KRW")-SUMIFS(설정해지!$J:$J, 설정해지!$B:$B,펀드현황!$C16,설정해지!$F:$F,"KRW") ) /100000000,"") -> -0.32175583 | X16: =IFERROR( ( SUMIFS(설정해지!$K:$K, 설정해지!$B:$B,펀드현황!$C16,설정해지!$F:$F,"KRW")-SUMIFS(설정해지!$L:$L, 설정해지!$B:$B,펀드현황!$C16,설정해지!$F:$F,"KRW") ) /100000000,"") -> -3.6648606 | Z16: =IFERROR( ( SUMIFS(자금총괄!$G:$G, 자금총괄!$B:$B,펀드현황!$C16,자금총괄!$F:$F,$AB$2) ) /100000000,"") -> 38.793 | AA16: =Z16/F16 -> 0.028377329 | AB16: =IFERROR( ( SUMIFS(자금총괄!$I:$I, 자금총괄!$B:$B,펀드현황!$C16,자금총괄!$F:$F,$AB$2) ) /100000000,"") -> 38.471244 | AC16: =IFERROR( ( SUMIFS(자금총괄!$K:$K, 자금총괄!$B:$B,펀드현황!$C16,자금총괄!$F:$F,$AB$2) ) /100000000,"") -> 34.806384 | AD16: =IFERROR( ( SUMIFS(자금총괄!$M:$M, 자금총괄!$B:$B,펀드현황!$C16,자금총괄!$F:$F,$AB$2) ) /100000000,"") -> 34.423089 | AE16: =IFERROR( ( SUMIFS(자금총괄!$O:$O, 자금총괄!$B:$B,펀드현황!$C16,자금총괄!$F:$F,$AB$2) ) /100000000,"") -> 30.726909 | AF16: =IFERROR( ( SUMIFS(자금총괄!$Q:$Q, 자금총괄!$B:$B,펀드현황!$C16,자금총괄!$F:$F,$AB$2) ) /100000000,"") -> 329.71286 | AH16: =IFERROR( ( SUMIFS(자금총괄!$G:$G, 자금총괄!$B:$B,펀드현황!$C16,자금총괄!$F:$F,$AI$2)/10000 ),"") -> 0.056421 | AI16: =IFERROR( ( SUMIFS(자금총괄!$I:$I, 자금총괄!$B:$B,펀드현황!$C16,자금총괄!$F:$F,$AI$2)/10000 ),"") -> 0.056421 | AJ16: =IFERROR((SUMIFS(자금총괄!$K:$K,자금총괄!$B:$B,펀드현황!$C16,자금총괄!$F:$F,$AI$2)/10000),"") -> 0.056421 | AK16: =IFERROR((SUMIFS(자금총괄!$M:$M,자금총괄!$B:$B,펀드현황!$C16,자금총괄!$F:$F,$AI$2)/10000),"") -> 0.056421 | AL16: =IFERROR( ( SUMIFS(자금총괄!$O:$O, 자금총괄!$B:$B,펀드현황!$C16,자금총괄!$F:$F,$AI$2) /10000 ),"") -> 0.056421 | AM16: =IFERROR( ( SUMIFS(자금총괄!$Q:$Q, 자금총괄!$B:$B,펀드현황!$C16,자금총괄!$F:$F,$AI$2) /10000 ),"") -> -2308.9436
C17: 05C44 | D17: =VLOOKUP(C17,'MOS4110'!$A:$B,2,0) -> 한국투자TDF알아서2030증권투자신탁(주식혼합-재간접형)(모) | E17: =AVERAGEIFS(#REF!,#REF!,펀드현황!$C17)/100000000 -> #REF! | F17: =IFERROR(VLOOKUP($T17,자금총괄!$B:$E,4,0)/100000000,"") -> 2790.7718 | G17: =VLOOKUP($C17,'MOS4110'!$A:$BP,펀드현황!G$2,0) -> 42796 | H17: =VLOOKUP($C17,'MOS4110'!$A:$BP,펀드현황!H$2,0) -> 1447.07 | I17: =VLOOKUP($C17,'MOS4110'!$A:$BP,펀드현황!I$2,0) -> 2.0897 | J17: =VLOOKUP($C17,'MOS4110'!$A:$BP,펀드현황!J$2,0) -> 6.9401 | K17: =VLOOKUP($C17,'MOS4110'!$A:$BP,펀드현황!K$2,0) -> 7.9863 | L17: =VLOOKUP($C17,'MOS4110'!$A:$BP,펀드현황!L$2,0) -> 11.6024 | M17: =VLOOKUP($C17,'MOS4110'!$A:$BP,펀드현황!M$2,0) -> 6.2952 | N17: =VLOOKUP($C17,'MOS4110'!$A:$BP,펀드현황!N$2,0) -> 1.9481 | ... P17: =VLOOKUP($C17,'MOS4110'!$A:$BP,펀드현황!P$2,0) -> 46.773 | T17: =C17 -> 05C44 | V17: =IFERROR( ( SUMIFS(설정해지!$G:$G, 설정해지!$B:$B,펀드현황!$C17,설정해지!$F:$F,"KRW")-SUMIFS(설정해지!$H:$H, 설정해지!$B:$B,펀드현황!$C17,설정해지!$F:$F,"KRW") ) /100000000,"") -> -1.2525133 | W17: =IFERROR( ( SUMIFS(설정해지!$I:$I, 설정해지!$B:$B,펀드현황!$C17,설정해지!$F:$F,"KRW")-SUMIFS(설정해지!$J:$J, 설정해지!$B:$B,펀드현황!$C17,설정해지!$F:$F,"KRW") ) /100000000,"") -> 0.44025064 | X17: =IFERROR( ( SUMIFS(설정해지!$K:$K, 설정해지!$B:$B,펀드현황!$C17,설정해지!$F:$F,"KRW")-SUMIFS(설정해지!$L:$L, 설정해지!$B:$B,펀드현황!$C17,설정해지!$F:$F,"KRW") ) /100000000,"") -> -7.8152405 | Z17: =IFERROR( ( SUMIFS(자금총괄!$G:$G, 자금총괄!$B:$B,펀드현황!$C17,자금총괄!$F:$F,$AB$2) ) /100000000,"") -> 74.387464 | AA17: =Z17/F17 -> 0.0266548 | AB17: =IFERROR( ( SUMIFS(자금총괄!$I:$I, 자금총괄!$B:$B,펀드현황!$C17,자금총괄!$F:$F,$AB$2) ) /100000000,"") -> 74.827715 | AC17: =IFERROR( ( SUMIFS(자금총괄!$K:$K, 자금총괄!$B:$B,펀드현황!$C17,자금총괄!$F:$F,$AB$2) ) /100000000,"") -> 67.012475 | AD17: =IFERROR( ( SUMIFS(자금총괄!$M:$M, 자금총괄!$B:$B,펀드현황!$C17,자금총괄!$F:$F,$AB$2) ) /100000000,"") -> 63.133015 | AE17: =IFERROR( ( SUMIFS(자금총괄!$O:$O, 자금총괄!$B:$B,펀드현황!$C17,자금총괄!$F:$F,$AB$2) ) /100000000,"") -> 62.035324 | AF17: =IFERROR( ( SUMIFS(자금총괄!$Q:$Q, 자금총괄!$B:$B,펀드현황!$C17,자금총괄!$F:$F,$AB$2) ) /100000000,"") -> 548.99742 | AH17: =IFERROR( ( SUMIFS(자금총괄!$G:$G, 자금총괄!$B:$B,펀드현황!$C17,자금총괄!$F:$F,$AI$2)/10000 ),"") -> 0.016561 | AI17: =IFERROR( ( SUMIFS(자금총괄!$I:$I, 자금총괄!$B:$B,펀드현황!$C17,자금총괄!$F:$F,$AI$2)/10000 ),"") -> 0.016561 | AJ17: =IFERROR((SUMIFS(자금총괄!$K:$K,자금총괄!$B:$B,펀드현황!$C17,자금총괄!$F:$F,$AI$2)/10000),"") -> 0.016561 | AK17: =IFERROR((SUMIFS(자금총괄!$M:$M,자금총괄!$B:$B,펀드현황!$C17,자금총괄!$F:$F,$AI$2)/10000),"") -> 0.016561 | AL17: =IFERROR( ( SUMIFS(자금총괄!$O:$O, 자금총괄!$B:$B,펀드현황!$C17,자금총괄!$F:$F,$AI$2) /10000 ),"") -> 0.016561 | AM17: =IFERROR( ( SUMIFS(자금총괄!$Q:$Q, 자금총괄!$B:$B,펀드현황!$C17,자금총괄!$F:$F,$AI$2) /10000 ),"") -> -3762.9834
C18: 05C58 | D18: =VLOOKUP(C18,'MOS4110'!$A:$B,2,0) -> 한국투자TDF알아서2035증권투자신탁(주식혼합-재간접형)(모) | E18: =AVERAGEIFS(#REF!,#REF!,펀드현황!$C18)/100000000 -> #REF! | F18: =IFERROR(VLOOKUP($T18,자금총괄!$B:$E,4,0)/100000000,"") -> 1486.1227 | G18: =VLOOKUP($C18,'MOS4110'!$A:$BP,펀드현황!G$2,0) -> 42796 | H18: =VLOOKUP($C18,'MOS4110'!$A:$BP,펀드현황!H$2,0) -> 1509.55 | I18: =VLOOKUP($C18,'MOS4110'!$A:$BP,펀드현황!I$2,0) -> 2.5558 | J18: =VLOOKUP($C18,'MOS4110'!$A:$BP,펀드현황!J$2,0) -> 7.7519 | K18: =VLOOKUP($C18,'MOS4110'!$A:$BP,펀드현황!K$2,0) -> 8.889 | L18: =VLOOKUP($C18,'MOS4110'!$A:$BP,펀드현황!L$2,0) -> 13.1327 | M18: =VLOOKUP($C18,'MOS4110'!$A:$BP,펀드현황!M$2,0) -> 7.9405 | N18: =VLOOKUP($C18,'MOS4110'!$A:$BP,펀드현황!N$2,0) -> 3.3419 | ... P18: =VLOOKUP($C18,'MOS4110'!$A:$BP,펀드현황!P$2,0) -> 53.1097 | T18: =C18 -> 05C58 | V18: =IFERROR( ( SUMIFS(설정해지!$G:$G, 설정해지!$B:$B,펀드현황!$C18,설정해지!$F:$F,"KRW")-SUMIFS(설정해지!$H:$H, 설정해지!$B:$B,펀드현황!$C18,설정해지!$F:$F,"KRW") ) /100000000,"") -> -0.17814913 | W18: =IFERROR( ( SUMIFS(설정해지!$I:$I, 설정해지!$B:$B,펀드현황!$C18,설정해지!$F:$F,"KRW")-SUMIFS(설정해지!$J:$J, 설정해지!$B:$B,펀드현황!$C18,설정해지!$F:$F,"KRW") ) /100000000,"") -> 0.7920524 | X18: =IFERROR( ( SUMIFS(설정해지!$K:$K, 설정해지!$B:$B,펀드현황!$C18,설정해지!$F:$F,"KRW")-SUMIFS(설정해지!$L:$L, 설정해지!$B:$B,펀드현황!$C18,설정해지!$F:$F,"KRW") ) /100000000,"") -> -3.4830989 | Z18: =IFERROR( ( SUMIFS(자금총괄!$G:$G, 자금총괄!$B:$B,펀드현황!$C18,자금총괄!$F:$F,$AB$2) ) /100000000,"") -> 46.81667 | AA18: =Z18/F18 -> 0.031502559 | AB18: =IFERROR( ( SUMIFS(자금총괄!$I:$I, 자금총괄!$B:$B,펀드현황!$C18,자금총괄!$F:$F,$AB$2) ) /100000000,"") -> 47.608722 | AC18: =IFERROR( ( SUMIFS(자금총괄!$K:$K, 자금총괄!$B:$B,펀드현황!$C18,자금총괄!$F:$F,$AB$2) ) /100000000,"") -> 44.125623 | AD18: =IFERROR( ( SUMIFS(자금총괄!$M:$M, 자금총괄!$B:$B,펀드현황!$C18,자금총괄!$F:$F,$AB$2) ) /100000000,"") -> 43.923812 | AE18: =IFERROR( ( SUMIFS(자금총괄!$O:$O, 자금총괄!$B:$B,펀드현황!$C18,자금총괄!$F:$F,$AB$2) ) /100000000,"") -> 43.162089 | AF18: =IFERROR( ( SUMIFS(자금총괄!$Q:$Q, 자금총괄!$B:$B,펀드현황!$C18,자금총괄!$F:$F,$AB$2) ) /100000000,"") -> 294.79273 | AH18: =IFERROR( ( SUMIFS(자금총괄!$G:$G, 자금총괄!$B:$B,펀드현황!$C18,자금총괄!$F:$F,$AI$2)/10000 ),"") -> 4.658794 | AI18: =IFERROR( ( SUMIFS(자금총괄!$I:$I, 자금총괄!$B:$B,펀드현황!$C18,자금총괄!$F:$F,$AI$2)/10000 ),"") -> 4.658794 | AJ18: =IFERROR((SUMIFS(자금총괄!$K:$K,자금총괄!$B:$B,펀드현황!$C18,자금총괄!$F:$F,$AI$2)/10000),"") -> 4.658794 | AK18: =IFERROR((SUMIFS(자금총괄!$M:$M,자금총괄!$B:$B,펀드현황!$C18,자금총괄!$F:$F,$AI$2)/10000),"") -> 4.658794 | AL18: =IFERROR( ( SUMIFS(자금총괄!$O:$O, 자금총괄!$B:$B,펀드현황!$C18,자금총괄!$F:$F,$AI$2) /10000 ),"") -> 4.658794 | AM18: =IFERROR( ( SUMIFS(자금총괄!$Q:$Q, 자금총괄!$B:$B,펀드현황!$C18,자금총괄!$F:$F,$AI$2) /10000 ),"") -> -1943.3412
C19: 05C72 | D19: =VLOOKUP(C19,'MOS4110'!$A:$B,2,0) -> 한국투자TDF알아서2040증권투자신탁(주식혼합-재간접형)(모) | E19: =AVERAGEIFS(#REF!,#REF!,펀드현황!$C19)/100000000 -> #REF! | F19: =IFERROR(VLOOKUP($T19,자금총괄!$B:$E,4,0)/100000000,"") -> 2049.1878 | G19: =VLOOKUP($C19,'MOS4110'!$A:$BP,펀드현황!G$2,0) -> 42796 | H19: =VLOOKUP($C19,'MOS4110'!$A:$BP,펀드현황!H$2,0) -> 1567 | I19: =VLOOKUP($C19,'MOS4110'!$A:$BP,펀드현황!I$2,0) -> 2.8965 | J19: =VLOOKUP($C19,'MOS4110'!$A:$BP,펀드현황!J$2,0) -> 8.3222 | K19: =VLOOKUP($C19,'MOS4110'!$A:$BP,펀드현황!K$2,0) -> 9.484 | L19: =VLOOKUP($C19,'MOS4110'!$A:$BP,펀드현황!L$2,0) -> 14.0718 | M19: =VLOOKUP($C19,'MOS4110'!$A:$BP,펀드현황!M$2,0) -> 9.1878 | N19: =VLOOKUP($C19,'MOS4110'!$A:$BP,펀드현황!N$2,0) -> 4.66 | ... P19: =VLOOKUP($C19,'MOS4110'!$A:$BP,펀드현황!P$2,0) -> 59.0336 | T19: =C19 -> 05C72 | V19: =IFERROR( ( SUMIFS(설정해지!$G:$G, 설정해지!$B:$B,펀드현황!$C19,설정해지!$F:$F,"KRW")-SUMIFS(설정해지!$H:$H, 설정해지!$B:$B,펀드현황!$C19,설정해지!$F:$F,"KRW") ) /100000000,"") -> -0.13030738 | W19: =IFERROR( ( SUMIFS(설정해지!$I:$I, 설정해지!$B:$B,펀드현황!$C19,설정해지!$F:$F,"KRW")-SUMIFS(설정해지!$J:$J, 설정해지!$B:$B,펀드현황!$C19,설정해지!$F:$F,"KRW") ) /100000000,"") -> 1.8456872 | X19: =IFERROR( ( SUMIFS(설정해지!$K:$K, 설정해지!$B:$B,펀드현황!$C19,설정해지!$F:$F,"KRW")-SUMIFS(설정해지!$L:$L, 설정해지!$B:$B,펀드현황!$C19,설정해지!$F:$F,"KRW") ) /100000000,"") -> -7.1000374 | Z19: =IFERROR( ( SUMIFS(자금총괄!$G:$G, 자금총괄!$B:$B,펀드현황!$C19,자금총괄!$F:$F,$AB$2) ) /100000000,"") -> 62.801468 | AA19: =Z19/F19 -> 0.030647005 | AB19: =IFERROR( ( SUMIFS(자금총괄!$I:$I, 자금총괄!$B:$B,펀드현황!$C19,자금총괄!$F:$F,$AB$2) ) /100000000,"") -> 64.647155 | AC19: =IFERROR( ( SUMIFS(자금총괄!$K:$K, 자금총괄!$B:$B,펀드현황!$C19,자금총괄!$F:$F,$AB$2) ) /100000000,"") -> 57.547118 | AD19: =IFERROR( ( SUMIFS(자금총괄!$M:$M, 자금총괄!$B:$B,펀드현황!$C19,자금총괄!$F:$F,$AB$2) ) /100000000,"") -> 55.979451 | AE19: =IFERROR( ( SUMIFS(자금총괄!$O:$O, 자금총괄!$B:$B,펀드현황!$C19,자금총괄!$F:$F,$AB$2) ) /100000000,"") -> 54.357342 | AF19: =IFERROR( ( SUMIFS(자금총괄!$Q:$Q, 자금총괄!$B:$B,펀드현황!$C19,자금총괄!$F:$F,$AB$2) ) /100000000,"") -> 400.71756 | AH19: =IFERROR( ( SUMIFS(자금총괄!$G:$G, 자금총괄!$B:$B,펀드현황!$C19,자금총괄!$F:$F,$AI$2)/10000 ),"") -> 6.647696 | AI19: =IFERROR( ( SUMIFS(자금총괄!$I:$I, 자금총괄!$B:$B,펀드현황!$C19,자금총괄!$F:$F,$AI$2)/10000 ),"") -> 6.647696 | AJ19: =IFERROR((SUMIFS(자금총괄!$K:$K,자금총괄!$B:$B,펀드현황!$C19,자금총괄!$F:$F,$AI$2)/10000),"") -> 6.647696 | AK19: =IFERROR((SUMIFS(자금총괄!$M:$M,자금총괄!$B:$B,펀드현황!$C19,자금총괄!$F:$F,$AI$2)/10000),"") -> 6.647696 | AL19: =IFERROR( ( SUMIFS(자금총괄!$O:$O, 자금총괄!$B:$B,펀드현황!$C19,자금총괄!$F:$F,$AI$2) /10000 ),"") -> 6.647696 | AM19: =IFERROR( ( SUMIFS(자금총괄!$Q:$Q, 자금총괄!$B:$B,펀드현황!$C19,자금총괄!$F:$F,$AI$2) /10000 ),"") -> -2673.3523
C20: 05C86 | D20: =VLOOKUP(C20,'MOS4110'!$A:$B,2,0) -> 한국투자TDF알아서2045증권투자신탁(주식혼합-재간접형)(모) | E20: =AVERAGEIFS(#REF!,#REF!,펀드현황!$C20)/100000000 -> #REF! | F20: =IFERROR(VLOOKUP($T20,자금총괄!$B:$E,4,0)/100000000,"") -> 2901.8146 | G20: =VLOOKUP($C20,'MOS4110'!$A:$BP,펀드현황!G$2,0) -> 42796 | H20: =VLOOKUP($C20,'MOS4110'!$A:$BP,펀드현황!H$2,0) -> 1582.38 | I20: =VLOOKUP($C20,'MOS4110'!$A:$BP,펀드현황!I$2,0) -> 3.1317 | J20: =VLOOKUP($C20,'MOS4110'!$A:$BP,펀드현황!J$2,0) -> 8.7913 | K20: =VLOOKUP($C20,'MOS4110'!$A:$BP,펀드현황!K$2,0) -> 9.9394 | L20: =VLOOKUP($C20,'MOS4110'!$A:$BP,펀드현황!L$2,0) -> 14.7796 | M20: =VLOOKUP($C20,'MOS4110'!$A:$BP,펀드현황!M$2,0) -> 9.8603 | N20: =VLOOKUP($C20,'MOS4110'!$A:$BP,펀드현황!N$2,0) -> 4.8544 | ... P20: =VLOOKUP($C20,'MOS4110'!$A:$BP,펀드현황!P$2,0) -> 60.5712 | T20: =C20 -> 05C86 | V20: =IFERROR( ( SUMIFS(설정해지!$G:$G, 설정해지!$B:$B,펀드현황!$C20,설정해지!$F:$F,"KRW")-SUMIFS(설정해지!$H:$H, 설정해지!$B:$B,펀드현황!$C20,설정해지!$F:$F,"KRW") ) /100000000,"") -> 5.6872295 | W20: =IFERROR( ( SUMIFS(설정해지!$I:$I, 설정해지!$B:$B,펀드현황!$C20,설정해지!$F:$F,"KRW")-SUMIFS(설정해지!$J:$J, 설정해지!$B:$B,펀드현황!$C20,설정해지!$F:$F,"KRW") ) /100000000,"") -> 3.8775186 | X20: =IFERROR( ( SUMIFS(설정해지!$K:$K, 설정해지!$B:$B,펀드현황!$C20,설정해지!$F:$F,"KRW")-SUMIFS(설정해지!$L:$L, 설정해지!$B:$B,펀드현황!$C20,설정해지!$F:$F,"KRW") ) /100000000,"") -> -9.7334857 | Z20: =IFERROR( ( SUMIFS(자금총괄!$G:$G, 자금총괄!$B:$B,펀드현황!$C20,자금총괄!$F:$F,$AB$2) ) /100000000,"") -> 139.73402 | AA20: =Z20/F20 -> 0.048154012 | AB20: =IFERROR( ( SUMIFS(자금총괄!$I:$I, 자금총괄!$B:$B,펀드현황!$C20,자금총괄!$F:$F,$AB$2) ) /100000000,"") -> 143.61153 | AC20: =IFERROR( ( SUMIFS(자금총괄!$K:$K, 자금총괄!$B:$B,펀드현황!$C20,자금총괄!$F:$F,$AB$2) ) /100000000,"") -> 133.87805 | AD20: =IFERROR( ( SUMIFS(자금총괄!$M:$M, 자금총괄!$B:$B,펀드현황!$C20,자금총괄!$F:$F,$AB$2) ) /100000000,"") -> 130.65804 | AE20: =IFERROR( ( SUMIFS(자금총괄!$O:$O, 자금총괄!$B:$B,펀드현황!$C20,자금총괄!$F:$F,$AB$2) ) /100000000,"") -> 125.85006 | AF20: =IFERROR( ( SUMIFS(자금총괄!$Q:$Q, 자금총괄!$B:$B,펀드현황!$C20,자금총괄!$F:$F,$AB$2) ) /100000000,"") -> 587.70404 | AH20: =IFERROR( ( SUMIFS(자금총괄!$G:$G, 자금총괄!$B:$B,펀드현황!$C20,자금총괄!$F:$F,$AI$2)/10000 ),"") -> 81.07425 | AI20: =IFERROR( ( SUMIFS(자금총괄!$I:$I, 자금총괄!$B:$B,펀드현황!$C20,자금총괄!$F:$F,$AI$2)/10000 ),"") -> 81.07425 | AJ20: =IFERROR((SUMIFS(자금총괄!$K:$K,자금총괄!$B:$B,펀드현황!$C20,자금총괄!$F:$F,$AI$2)/10000),"") -> 81.07425 | AK20: =IFERROR((SUMIFS(자금총괄!$M:$M,자금총괄!$B:$B,펀드현황!$C20,자금총괄!$F:$F,$AI$2)/10000),"") -> 81.07425 | AL20: =IFERROR( ( SUMIFS(자금총괄!$O:$O, 자금총괄!$B:$B,펀드현황!$C20,자금총괄!$F:$F,$AI$2) /10000 ),"") -> 81.07425 | AM20: =IFERROR( ( SUMIFS(자금총괄!$Q:$Q, 자금총괄!$B:$B,펀드현황!$C20,자금총괄!$F:$F,$AI$2) /10000 ),"") -> -3500.9257
C21: 05W24 | D21: =VLOOKUP(C21,'MOS4110'!$A:$B,2,0) -> 한국투자TDF알아서2050증권자투자신탁H(주식혼합-재간접형)(모) | E21: =AVERAGEIFS(#REF!,#REF!,펀드현황!$C21)/100000000 -> #REF! | F21: =IFERROR(VLOOKUP($T21,자금총괄!$B:$E,4,0)/100000000,"") -> 385.32759 | G21: =VLOOKUP($C21,'MOS4110'!$A:$BP,펀드현황!G$2,0) -> 43713 | H21: =VLOOKUP($C21,'MOS4110'!$A:$BP,펀드현황!H$2,0) -> 1342.46 | I21: =VLOOKUP($C21,'MOS4110'!$A:$BP,펀드현황!I$2,0) -> 2.9976 | J21: =VLOOKUP($C21,'MOS4110'!$A:$BP,펀드현황!J$2,0) -> 8.4072 | K21: =VLOOKUP($C21,'MOS4110'!$A:$BP,펀드현황!K$2,0) -> 9.6167 | L21: =VLOOKUP($C21,'MOS4110'!$A:$BP,펀드현황!L$2,0) -> 14.3705 | M21: =VLOOKUP($C21,'MOS4110'!$A:$BP,펀드현황!M$2,0) -> 9.7215 | N21: =VLOOKUP($C21,'MOS4110'!$A:$BP,펀드현황!N$2,0) -> 5.0345 | ... P21: =VLOOKUP($C21,'MOS4110'!$A:$BP,펀드현황!P$2,0) -> 35.8552 | T21: =C21 -> 05W24 | V21: =IFERROR( ( SUMIFS(설정해지!$G:$G, 설정해지!$B:$B,펀드현황!$C21,설정해지!$F:$F,"KRW")-SUMIFS(설정해지!$H:$H, 설정해지!$B:$B,펀드현황!$C21,설정해지!$F:$F,"KRW") ) /100000000,"") -> 0.63807226 | W21: =IFERROR( ( SUMIFS(설정해지!$I:$I, 설정해지!$B:$B,펀드현황!$C21,설정해지!$F:$F,"KRW")-SUMIFS(설정해지!$J:$J, 설정해지!$B:$B,펀드현황!$C21,설정해지!$F:$F,"KRW") ) /100000000,"") -> 0.49612093 | X21: =IFERROR( ( SUMIFS(설정해지!$K:$K, 설정해지!$B:$B,펀드현황!$C21,설정해지!$F:$F,"KRW")-SUMIFS(설정해지!$L:$L, 설정해지!$B:$B,펀드현황!$C21,설정해지!$F:$F,"KRW") ) /100000000,"") -> -0.2382968 | Z21: =IFERROR( ( SUMIFS(자금총괄!$G:$G, 자금총괄!$B:$B,펀드현황!$C21,자금총괄!$F:$F,$AB$2) ) /100000000,"") -> 16.616802 | AA21: =Z21/F21 -> 0.04312383 | AB21: =IFERROR( ( SUMIFS(자금총괄!$I:$I, 자금총괄!$B:$B,펀드현황!$C21,자금총괄!$F:$F,$AB$2) ) /100000000,"") -> 16.575367 | AC21: =IFERROR( ( SUMIFS(자금총괄!$K:$K, 자금총괄!$B:$B,펀드현황!$C21,자금총괄!$F:$F,$AB$2) ) /100000000,"") -> 16.582516 | AD21: =IFERROR( ( SUMIFS(자금총괄!$M:$M, 자금총괄!$B:$B,펀드현황!$C21,자금총괄!$F:$F,$AB$2) ) /100000000,"") -> 15.979201 | AE21: =IFERROR( ( SUMIFS(자금총괄!$O:$O, 자금총괄!$B:$B,펀드현황!$C21,자금총괄!$F:$F,$AB$2) ) /100000000,"") -> 15.996222 | AF21: =IFERROR( ( SUMIFS(자금총괄!$Q:$Q, 자금총괄!$B:$B,펀드현황!$C21,자금총괄!$F:$F,$AB$2) ) /100000000,"") -> 76.947861 | AH21: =IFERROR( ( SUMIFS(자금총괄!$G:$G, 자금총괄!$B:$B,펀드현황!$C21,자금총괄!$F:$F,$AI$2)/10000 ),"") -> 0 | AI21: =IFERROR( ( SUMIFS(자금총괄!$I:$I, 자금총괄!$B:$B,펀드현황!$C21,자금총괄!$F:$F,$AI$2)/10000 ),"") -> 0 | AJ21: =IFERROR((SUMIFS(자금총괄!$K:$K,자금총괄!$B:$B,펀드현황!$C21,자금총괄!$F:$F,$AI$2)/10000),"") -> 0 | AK21: =IFERROR((SUMIFS(자금총괄!$M:$M,자금총괄!$B:$B,펀드현황!$C21,자금총괄!$F:$F,$AI$2)/10000),"") -> 0 | AL21: =IFERROR( ( SUMIFS(자금총괄!$O:$O, 자금총괄!$B:$B,펀드현황!$C21,자금총괄!$F:$F,$AI$2) /10000 ),"") -> 0 | AM21: =IFERROR( ( SUMIFS(자금총괄!$Q:$Q, 자금총괄!$B:$B,펀드현황!$C21,자금총괄!$F:$F,$AI$2) /10000 ),"") -> -470
C22: 07A77 | D22: =VLOOKUP(C22,'MOS4110'!$A:$B,2,0) -> 한국투자신종개인연금TDF알아서2050전환형자H(주혼-재간접)(모) | E22: =AVERAGEIFS(#REF!,#REF!,펀드현황!$C22)/100000000 -> #REF! | F22: =IFERROR(VLOOKUP($T22,자금총괄!$B:$E,4,0)/100000000,"") -> 78.343186 | G22: =VLOOKUP($C22,'MOS4110'!$A:$BP,펀드현황!G$2,0) -> 44236 | H22: =VLOOKUP($C22,'MOS4110'!$A:$BP,펀드현황!H$2,0) -> 1020.6 | I22: =VLOOKUP($C22,'MOS4110'!$A:$BP,펀드현황!I$2,0) -> 2.9904 | J22: =VLOOKUP($C22,'MOS4110'!$A:$BP,펀드현황!J$2,0) -> 8.4156 | K22: =VLOOKUP($C22,'MOS4110'!$A:$BP,펀드현황!K$2,0) -> 9.5871 | L22: =VLOOKUP($C22,'MOS4110'!$A:$BP,펀드현황!L$2,0) -> 14.3299 | M22: =VLOOKUP($C22,'MOS4110'!$A:$BP,펀드현황!M$2,0) -> 10.0967 | N22: =VLOOKUP($C22,'MOS4110'!$A:$BP,펀드현황!N$2,0) -> 3.8323 | ... P22: =VLOOKUP($C22,'MOS4110'!$A:$BP,펀드현황!P$2,0) -> 4.1614 | T22: =C22 -> 07A77 | V22: =IFERROR( ( SUMIFS(설정해지!$G:$G, 설정해지!$B:$B,펀드현황!$C22,설정해지!$F:$F,"KRW")-SUMIFS(설정해지!$H:$H, 설정해지!$B:$B,펀드현황!$C22,설정해지!$F:$F,"KRW") ) /100000000,"") -> 0.01055084 | W22: =IFERROR( ( SUMIFS(설정해지!$I:$I, 설정해지!$B:$B,펀드현황!$C22,설정해지!$F:$F,"KRW")-SUMIFS(설정해지!$J:$J, 설정해지!$B:$B,펀드현황!$C22,설정해지!$F:$F,"KRW") ) /100000000,"") -> -0.00436014 | X22: =IFERROR( ( SUMIFS(설정해지!$K:$K, 설정해지!$B:$B,펀드현황!$C22,설정해지!$F:$F,"KRW")-SUMIFS(설정해지!$L:$L, 설정해지!$B:$B,펀드현황!$C22,설정해지!$F:$F,"KRW") ) /100000000,"") -> -0.02015269 | Z22: =IFERROR( ( SUMIFS(자금총괄!$G:$G, 자금총괄!$B:$B,펀드현황!$C22,자금총괄!$F:$F,$AB$2) ) /100000000,"") -> 3.4303266 | AA22: =Z22/F22 -> 0.043785895 | AB22: =IFERROR( ( SUMIFS(자금총괄!$I:$I, 자금총괄!$B:$B,펀드현황!$C22,자금총괄!$F:$F,$AB$2) ) /100000000,"") -> 3.4089574 | AC22: =IFERROR( ( SUMIFS(자금총괄!$K:$K, 자금총괄!$B:$B,펀드현황!$C22,자금총괄!$F:$F,$AB$2) ) /100000000,"") -> 3.4095619 | AD22: =IFERROR( ( SUMIFS(자금총괄!$M:$M, 자금총괄!$B:$B,펀드현황!$C22,자금총괄!$F:$F,$AB$2) ) /100000000,"") -> 3.4098376 | AE22: =IFERROR( ( SUMIFS(자금총괄!$O:$O, 자금총괄!$B:$B,펀드현황!$C22,자금총괄!$F:$F,$AB$2) ) /100000000,"") -> 3.4098376 | AF22: =IFERROR( ( SUMIFS(자금총괄!$Q:$Q, 자금총괄!$B:$B,펀드현황!$C22,자금총괄!$F:$F,$AB$2) ) /100000000,"") -> 10.541028 | AH22: =IFERROR( ( SUMIFS(자금총괄!$G:$G, 자금총괄!$B:$B,펀드현황!$C22,자금총괄!$F:$F,$AI$2)/10000 ),"") -> 0 | AI22: =IFERROR( ( SUMIFS(자금총괄!$I:$I, 자금총괄!$B:$B,펀드현황!$C22,자금총괄!$F:$F,$AI$2)/10000 ),"") -> 0 | AJ22: =IFERROR((SUMIFS(자금총괄!$K:$K,자금총괄!$B:$B,펀드현황!$C22,자금총괄!$F:$F,$AI$2)/10000),"") -> 0 | AK22: =IFERROR((SUMIFS(자금총괄!$M:$M,자금총괄!$B:$B,펀드현황!$C22,자금총괄!$F:$F,$AI$2)/10000),"") -> 0 | AL22: =IFERROR( ( SUMIFS(자금총괄!$O:$O, 자금총괄!$B:$B,펀드현황!$C22,자금총괄!$F:$F,$AI$2) /10000 ),"") -> 0 | AM22: =IFERROR( ( SUMIFS(자금총괄!$Q:$Q, 자금총괄!$B:$B,펀드현황!$C22,자금총괄!$F:$F,$AI$2) /10000 ),"") -> -55
C23: 05W41 | D23: =VLOOKUP(C23,'MOS4110'!$A:$B,2,0) -> 한국투자TDF알아서2050증권자투자신탁UH(주식혼합-재간접형)(모) | E23: =AVERAGEIFS(#REF!,#REF!,펀드현황!$C23)/100000000 -> #REF! | F23: =IFERROR(VLOOKUP($T23,자금총괄!$B:$E,4,0)/100000000,"") -> 366.9394 | G23: =VLOOKUP($C23,'MOS4110'!$A:$BP,펀드현황!G$2,0) -> 43713 | H23: =VLOOKUP($C23,'MOS4110'!$A:$BP,펀드현황!H$2,0) -> 1529.59 | I23: =VLOOKUP($C23,'MOS4110'!$A:$BP,펀드현황!I$2,0) -> 2.905 | J23: =VLOOKUP($C23,'MOS4110'!$A:$BP,펀드현황!J$2,0) -> 10.4453 | K23: =VLOOKUP($C23,'MOS4110'!$A:$BP,펀드현황!K$2,0) -> 11.0195 | L23: =VLOOKUP($C23,'MOS4110'!$A:$BP,펀드현황!L$2,0) -> 18.0858 | M23: =VLOOKUP($C23,'MOS4110'!$A:$BP,펀드현황!M$2,0) -> 21.5798 | N23: =VLOOKUP($C23,'MOS4110'!$A:$BP,펀드현황!N$2,0) -> 22.5831 | ... P23: =VLOOKUP($C23,'MOS4110'!$A:$BP,펀드현황!P$2,0) -> 54.7006 | T23: =C23 -> 05W41 | V23: =IFERROR( ( SUMIFS(설정해지!$G:$G, 설정해지!$B:$B,펀드현황!$C23,설정해지!$F:$F,"KRW")-SUMIFS(설정해지!$H:$H, 설정해지!$B:$B,펀드현황!$C23,설정해지!$F:$F,"KRW") ) /100000000,"") -> 3.0996163 | W23: =IFERROR( ( SUMIFS(설정해지!$I:$I, 설정해지!$B:$B,펀드현황!$C23,설정해지!$F:$F,"KRW")-SUMIFS(설정해지!$J:$J, 설정해지!$B:$B,펀드현황!$C23,설정해지!$F:$F,"KRW") ) /100000000,"") -> 2.2460213 | X23: =IFERROR( ( SUMIFS(설정해지!$K:$K, 설정해지!$B:$B,펀드현황!$C23,설정해지!$F:$F,"KRW")-SUMIFS(설정해지!$L:$L, 설정해지!$B:$B,펀드현황!$C23,설정해지!$F:$F,"KRW") ) /100000000,"") -> -0.71219894 | Z23: =IFERROR( ( SUMIFS(자금총괄!$G:$G, 자금총괄!$B:$B,펀드현황!$C23,자금총괄!$F:$F,$AB$2) ) /100000000,"") -> 6.9533007 | AA23: =Z23/F23 -> 0.018949452 | AB23: =IFERROR( ( SUMIFS(자금총괄!$I:$I, 자금총괄!$B:$B,펀드현황!$C23,자금총괄!$F:$F,$AB$2) ) /100000000,"") -> 6.9808477 | AC23: =IFERROR( ( SUMIFS(자금총괄!$K:$K, 자금총괄!$B:$B,펀드현황!$C23,자금총괄!$F:$F,$AB$2) ) /100000000,"") -> 6.9879697 | AD23: =IFERROR( ( SUMIFS(자금총괄!$M:$M, 자금총괄!$B:$B,펀드현황!$C23,자금총괄!$F:$F,$AB$2) ) /100000000,"") -> 6.4625045 | AE23: =IFERROR( ( SUMIFS(자금총괄!$O:$O, 자금총괄!$B:$B,펀드현황!$C23,자금총괄!$F:$F,$AB$2) ) /100000000,"") -> 6.4641557 | AF23: =IFERROR( ( SUMIFS(자금총괄!$Q:$Q, 자금총괄!$B:$B,펀드현황!$C23,자금총괄!$F:$F,$AB$2) ) /100000000,"") -> 6.4650842 | AH23: =IFERROR( ( SUMIFS(자금총괄!$G:$G, 자금총괄!$B:$B,펀드현황!$C23,자금총괄!$F:$F,$AI$2)/10000 ),"") -> 0 | AI23: =IFERROR( ( SUMIFS(자금총괄!$I:$I, 자금총괄!$B:$B,펀드현황!$C23,자금총괄!$F:$F,$AI$2)/10000 ),"") -> 0 | AJ23: =IFERROR((SUMIFS(자금총괄!$K:$K,자금총괄!$B:$B,펀드현황!$C23,자금총괄!$F:$F,$AI$2)/10000),"") -> 0 | AK23: =IFERROR((SUMIFS(자금총괄!$M:$M,자금총괄!$B:$B,펀드현황!$C23,자금총괄!$F:$F,$AI$2)/10000),"") -> 0 | AL23: =IFERROR( ( SUMIFS(자금총괄!$O:$O, 자금총괄!$B:$B,펀드현황!$C23,자금총괄!$F:$F,$AI$2) /10000 ),"") -> 0 | AM23: =IFERROR( ( SUMIFS(자금총괄!$Q:$Q, 자금총괄!$B:$B,펀드현황!$C23,자금총괄!$F:$F,$AI$2) /10000 ),"") -> 0
C24: 07H33 | D24: =VLOOKUP(C24,'MOS4110'!$A:$B,2,0) -> 한국투자TDF알아서2055증권자투자신탁H(주식혼합-재간접형)(모) | E24: =AVERAGEIFS(#REF!,#REF!,펀드현황!$C24)/100000000 -> #REF! | F24: =IFERROR(VLOOKUP($T24,자금총괄!$B:$E,4,0)/100000000,"") -> 36.771682 | G24: =VLOOKUP($C24,'MOS4110'!$A:$BP,펀드현황!G$2,0) -> 44651 | H24: =VLOOKUP($C24,'MOS4110'!$A:$BP,펀드현황!H$2,0) -> 1046.82 | I24: =VLOOKUP($C24,'MOS4110'!$A:$BP,펀드현황!I$2,0) -> 2.9028 | J24: =VLOOKUP($C24,'MOS4110'!$A:$BP,펀드현황!J$2,0) -> 8.1124 | K24: =VLOOKUP($C24,'MOS4110'!$A:$BP,펀드현황!K$2,0) -> 9.1802 | L24: =VLOOKUP($C24,'MOS4110'!$A:$BP,펀드현황!L$2,0) -> 13.6921 | M24: =VLOOKUP($C24,'MOS4110'!$A:$BP,펀드현황!M$2,0) -> 0 | N24: =VLOOKUP($C24,'MOS4110'!$A:$BP,펀드현황!N$2,0) -> 0 | ... P24: =VLOOKUP($C24,'MOS4110'!$A:$BP,펀드현황!P$2,0) -> 4.682 | T24: =C24 -> 07H33 | V24: =IFERROR( ( SUMIFS(설정해지!$G:$G, 설정해지!$B:$B,펀드현황!$C24,설정해지!$F:$F,"KRW")-SUMIFS(설정해지!$H:$H, 설정해지!$B:$B,펀드현황!$C24,설정해지!$F:$F,"KRW") ) /100000000,"") -> 0.00555711 | W24: =IFERROR( ( SUMIFS(설정해지!$I:$I, 설정해지!$B:$B,펀드현황!$C24,설정해지!$F:$F,"KRW")-SUMIFS(설정해지!$J:$J, 설정해지!$B:$B,펀드현황!$C24,설정해지!$F:$F,"KRW") ) /100000000,"") -> 0.05163152 | X24: =IFERROR( ( SUMIFS(설정해지!$K:$K, 설정해지!$B:$B,펀드현황!$C24,설정해지!$F:$F,"KRW")-SUMIFS(설정해지!$L:$L, 설정해지!$B:$B,펀드현황!$C24,설정해지!$F:$F,"KRW") ) /100000000,"") -> 0 | Z24: =IFERROR( ( SUMIFS(자금총괄!$G:$G, 자금총괄!$B:$B,펀드현황!$C24,자금총괄!$F:$F,$AB$2) ) /100000000,"") -> 1.7816124 | AA24: =Z24/F24 -> 0.048450664 | AB24: =IFERROR( ( SUMIFS(자금총괄!$I:$I, 자금총괄!$B:$B,펀드현황!$C24,자금총괄!$F:$F,$AB$2) ) /100000000,"") -> 1.7750214 | AC24: =IFERROR( ( SUMIFS(자금총괄!$K:$K, 자금총괄!$B:$B,펀드현황!$C24,자금총괄!$F:$F,$AB$2) ) /100000000,"") -> 1.7750214 | AD24: =IFERROR( ( SUMIFS(자금총괄!$M:$M, 자금총괄!$B:$B,펀드현황!$C24,자금총괄!$F:$F,$AB$2) ) /100000000,"") -> 1.7750214 | AE24: =IFERROR( ( SUMIFS(자금총괄!$O:$O, 자금총괄!$B:$B,펀드현황!$C24,자금총괄!$F:$F,$AB$2) ) /100000000,"") -> 1.7750214 | AF24: =IFERROR( ( SUMIFS(자금총괄!$Q:$Q, 자금총괄!$B:$B,펀드현황!$C24,자금총괄!$F:$F,$AB$2) ) /100000000,"") -> 2.1639954 | AH24: =IFERROR( ( SUMIFS(자금총괄!$G:$G, 자금총괄!$B:$B,펀드현황!$C24,자금총괄!$F:$F,$AI$2)/10000 ),"") -> 0 | AI24: =IFERROR( ( SUMIFS(자금총괄!$I:$I, 자금총괄!$B:$B,펀드현황!$C24,자금총괄!$F:$F,$AI$2)/10000 ),"") -> 0 | AJ24: =IFERROR((SUMIFS(자금총괄!$K:$K,자금총괄!$B:$B,펀드현황!$C24,자금총괄!$F:$F,$AI$2)/10000),"") -> 0 | AK24: =IFERROR((SUMIFS(자금총괄!$M:$M,자금총괄!$B:$B,펀드현황!$C24,자금총괄!$F:$F,$AI$2)/10000),"") -> 0 | AL24: =IFERROR( ( SUMIFS(자금총괄!$O:$O, 자금총괄!$B:$B,펀드현황!$C24,자금총괄!$F:$F,$AI$2) /10000 ),"") -> 0 | AM24: =IFERROR( ( SUMIFS(자금총괄!$Q:$Q, 자금총괄!$B:$B,펀드현황!$C24,자금총괄!$F:$F,$AI$2) /10000 ),"") -> -3
C25: 07H50 | D25: =VLOOKUP(C25,'MOS4110'!$A:$B,2,0) -> 한국투자TDF알아서2055증권자투자신탁UH(주식혼합-재간접형)(모) | E25: =AVERAGEIFS(#REF!,#REF!,펀드현황!$C25)/100000000 -> #REF! | F25: =IFERROR(VLOOKUP($T25,자금총괄!$B:$E,4,0)/100000000,"") -> 155.66911 | G25: =VLOOKUP($C25,'MOS4110'!$A:$BP,펀드현황!G$2,0) -> 44651 | H25: =VLOOKUP($C25,'MOS4110'!$A:$BP,펀드현황!H$2,0) -> 1152.61 | I25: =VLOOKUP($C25,'MOS4110'!$A:$BP,펀드현황!I$2,0) -> 2.8382 | J25: =VLOOKUP($C25,'MOS4110'!$A:$BP,펀드현황!J$2,0) -> 10.2512 | K25: =VLOOKUP($C25,'MOS4110'!$A:$BP,펀드현황!K$2,0) -> 10.6895 | L25: =VLOOKUP($C25,'MOS4110'!$A:$BP,펀드현황!L$2,0) -> 17.4144 | M25: =VLOOKUP($C25,'MOS4110'!$A:$BP,펀드현황!M$2,0) -> 0 | N25: =VLOOKUP($C25,'MOS4110'!$A:$BP,펀드현황!N$2,0) -> 0 | ... P25: =VLOOKUP($C25,'MOS4110'!$A:$BP,펀드현황!P$2,0) -> 15.261 | T25: =C25 -> 07H50 | V25: =IFERROR( ( SUMIFS(설정해지!$G:$G, 설정해지!$B:$B,펀드현황!$C25,설정해지!$F:$F,"KRW")-SUMIFS(설정해지!$H:$H, 설정해지!$B:$B,펀드현황!$C25,설정해지!$F:$F,"KRW") ) /100000000,"") -> 0.51632402 | W25: =IFERROR( ( SUMIFS(설정해지!$I:$I, 설정해지!$B:$B,펀드현황!$C25,설정해지!$F:$F,"KRW")-SUMIFS(설정해지!$J:$J, 설정해지!$B:$B,펀드현황!$C25,설정해지!$F:$F,"KRW") ) /100000000,"") -> -0.28207158 | X25: =IFERROR( ( SUMIFS(설정해지!$K:$K, 설정해지!$B:$B,펀드현황!$C25,설정해지!$F:$F,"KRW")-SUMIFS(설정해지!$L:$L, 설정해지!$B:$B,펀드현황!$C25,설정해지!$F:$F,"KRW") ) /100000000,"") -> -0.1869702 | Z25: =IFERROR( ( SUMIFS(자금총괄!$G:$G, 자금총괄!$B:$B,펀드현황!$C25,자금총괄!$F:$F,$AB$2) ) /100000000,"") -> 3.0539837 | AA25: =Z25/F25 -> 0.01961843 | AB25: =IFERROR( ( SUMIFS(자금총괄!$I:$I, 자금총괄!$B:$B,펀드현황!$C25,자금총괄!$F:$F,$AB$2) ) /100000000,"") -> 3.072531 | AC25: =IFERROR( ( SUMIFS(자금총괄!$K:$K, 자금총괄!$B:$B,펀드현황!$C25,자금총괄!$F:$F,$AB$2) ) /100000000,"") -> 3.0762704 | AD25: =IFERROR( ( SUMIFS(자금총괄!$M:$M, 자금총괄!$B:$B,펀드현황!$C25,자금총괄!$F:$F,$AB$2) ) /100000000,"") -> 3.0767164 | AE25: =IFERROR( ( SUMIFS(자금총괄!$O:$O, 자금총괄!$B:$B,펀드현황!$C25,자금총괄!$F:$F,$AB$2) ) /100000000,"") -> 3.0866604 | AF25: =IFERROR( ( SUMIFS(자금총괄!$Q:$Q, 자금총괄!$B:$B,펀드현황!$C25,자금총괄!$F:$F,$AB$2) ) /100000000,"") -> 3.0928717 | AH25: =IFERROR( ( SUMIFS(자금총괄!$G:$G, 자금총괄!$B:$B,펀드현황!$C25,자금총괄!$F:$F,$AI$2)/10000 ),"") -> 0 | AI25: =IFERROR( ( SUMIFS(자금총괄!$I:$I, 자금총괄!$B:$B,펀드현황!$C25,자금총괄!$F:$F,$AI$2)/10000 ),"") -> 0 | AJ25: =IFERROR((SUMIFS(자금총괄!$K:$K,자금총괄!$B:$B,펀드현황!$C25,자금총괄!$F:$F,$AI$2)/10000),"") -> 0 | AK25: =IFERROR((SUMIFS(자금총괄!$M:$M,자금총괄!$B:$B,펀드현황!$C25,자금총괄!$F:$F,$AI$2)/10000),"") -> 0 | AL25: =IFERROR( ( SUMIFS(자금총괄!$O:$O, 자금총괄!$B:$B,펀드현황!$C25,자금총괄!$F:$F,$AI$2) /10000 ),"") -> 0 | AM25: =IFERROR( ( SUMIFS(자금총괄!$Q:$Q, 자금총괄!$B:$B,펀드현황!$C25,자금총괄!$F:$F,$AI$2) /10000 ),"") -> 0
C26: 07H68 | D26: =VLOOKUP(C26,'MOS4110'!$A:$B,2,0) -> 한국투자TDF알아서2060증권자투자신탁H(주식혼합-재간접형)(모) | E26: =AVERAGEIFS(#REF!,#REF!,펀드현황!$C26)/100000000 -> #REF! | F26: =IFERROR(VLOOKUP($T26,자금총괄!$B:$E,4,0)/100000000,"") -> 52.234419 | G26: =VLOOKUP($C26,'MOS4110'!$A:$BP,펀드현황!G$2,0) -> 44651 | H26: =VLOOKUP($C26,'MOS4110'!$A:$BP,펀드현황!H$2,0) -> 1051.56 | I26: =VLOOKUP($C26,'MOS4110'!$A:$BP,펀드현황!I$2,0) -> 2.971 | J26: =VLOOKUP($C26,'MOS4110'!$A:$BP,펀드현황!J$2,0) -> 8.3613 | K26: =VLOOKUP($C26,'MOS4110'!$A:$BP,펀드현황!K$2,0) -> 9.5877 | L26: =VLOOKUP($C26,'MOS4110'!$A:$BP,펀드현황!L$2,0) -> 14.2863 | M26: =VLOOKUP($C26,'MOS4110'!$A:$BP,펀드현황!M$2,0) -> 0 | N26: =VLOOKUP($C26,'MOS4110'!$A:$BP,펀드현황!N$2,0) -> 0 | ... P26: =VLOOKUP($C26,'MOS4110'!$A:$BP,펀드현황!P$2,0) -> 5.156 | T26: =C26 -> 07H68 | V26: =IFERROR( ( SUMIFS(설정해지!$G:$G, 설정해지!$B:$B,펀드현황!$C26,설정해지!$F:$F,"KRW")-SUMIFS(설정해지!$H:$H, 설정해지!$B:$B,펀드현황!$C26,설정해지!$F:$F,"KRW") ) /100000000,"") -> 0.02869888 | W26: =IFERROR( ( SUMIFS(설정해지!$I:$I, 설정해지!$B:$B,펀드현황!$C26,설정해지!$F:$F,"KRW")-SUMIFS(설정해지!$J:$J, 설정해지!$B:$B,펀드현황!$C26,설정해지!$F:$F,"KRW") ) /100000000,"") -> 0.03014173 | X26: =IFERROR( ( SUMIFS(설정해지!$K:$K, 설정해지!$B:$B,펀드현황!$C26,설정해지!$F:$F,"KRW")-SUMIFS(설정해지!$L:$L, 설정해지!$B:$B,펀드현황!$C26,설정해지!$F:$F,"KRW") ) /100000000,"") -> -1.293e-05 | Z26: =IFERROR( ( SUMIFS(자금총괄!$G:$G, 자금총괄!$B:$B,펀드현황!$C26,자금총괄!$F:$F,$AB$2) ) /100000000,"") -> 2.5580584 | AA26: =Z26/F26 -> 0.048972659 | AB26: =IFERROR( ( SUMIFS(자금총괄!$I:$I, 자금총괄!$B:$B,펀드현황!$C26,자금총괄!$F:$F,$AB$2) ) /100000000,"") -> 2.5452727 | AC26: =IFERROR( ( SUMIFS(자금총괄!$K:$K, 자금총괄!$B:$B,펀드현황!$C26,자금총괄!$F:$F,$AB$2) ) /100000000,"") -> 2.5452731 | AD26: =IFERROR( ( SUMIFS(자금총괄!$M:$M, 자금총괄!$B:$B,펀드현황!$C26,자금총괄!$F:$F,$AB$2) ) /100000000,"") -> 2.5452755 | AE26: =IFERROR( ( SUMIFS(자금총괄!$O:$O, 자금총괄!$B:$B,펀드현황!$C26,자금총괄!$F:$F,$AB$2) ) /100000000,"") -> 2.5452755 | AF26: =IFERROR( ( SUMIFS(자금총괄!$Q:$Q, 자금총괄!$B:$B,펀드현황!$C26,자금총괄!$F:$F,$AB$2) ) /100000000,"") -> 2.5452755 | AH26: =IFERROR( ( SUMIFS(자금총괄!$G:$G, 자금총괄!$B:$B,펀드현황!$C26,자금총괄!$F:$F,$AI$2)/10000 ),"") -> 0 | AI26: =IFERROR( ( SUMIFS(자금총괄!$I:$I, 자금총괄!$B:$B,펀드현황!$C26,자금총괄!$F:$F,$AI$2)/10000 ),"") -> 0 | AJ26: =IFERROR((SUMIFS(자금총괄!$K:$K,자금총괄!$B:$B,펀드현황!$C26,자금총괄!$F:$F,$AI$2)/10000),"") -> 0 | AK26: =IFERROR((SUMIFS(자금총괄!$M:$M,자금총괄!$B:$B,펀드현황!$C26,자금총괄!$F:$F,$AI$2)/10000),"") -> 0 | AL26: =IFERROR( ( SUMIFS(자금총괄!$O:$O, 자금총괄!$B:$B,펀드현황!$C26,자금총괄!$F:$F,$AI$2) /10000 ),"") -> 0 | AM26: =IFERROR( ( SUMIFS(자금총괄!$Q:$Q, 자금총괄!$B:$B,펀드현황!$C26,자금총괄!$F:$F,$AI$2) /10000 ),"") -> 0
... C28: 05C02 | D28: =VLOOKUP(C28,'MOS4110'!$A:$B,2,0) -> 한국투자TDF알아서증권투자신탁(채권혼합-재간접형)(모) | E28: =AVERAGEIFS(#REF!,#REF!,펀드현황!$C28)/100000000 -> #REF! | F28: =IFERROR(VLOOKUP($T28,자금총괄!$B:$E,4,0)/100000000,"") -> 1775.686 | G28: =VLOOKUP($C28,'MOS4110'!$A:$BP,펀드현황!G$2,0) -> 42788 | H28: =VLOOKUP($C28,'MOS4110'!$A:$BP,펀드현황!H$2,0) -> 1267.23 | I28: =VLOOKUP($C28,'MOS4110'!$A:$BP,펀드현황!I$2,0) -> 1.1972 | J28: =VLOOKUP($C28,'MOS4110'!$A:$BP,펀드현황!J$2,0) -> 5.3943 | K28: =VLOOKUP($C28,'MOS4110'!$A:$BP,펀드현황!K$2,0) -> 6.2936 | L28: =VLOOKUP($C28,'MOS4110'!$A:$BP,펀드현황!L$2,0) -> 8.6124 | M28: =VLOOKUP($C28,'MOS4110'!$A:$BP,펀드현황!M$2,0) -> 2.7728 | N28: =VLOOKUP($C28,'MOS4110'!$A:$BP,펀드현황!N$2,0) -> -1.7278 | ... P28: =VLOOKUP($C28,'MOS4110'!$A:$BP,펀드현황!P$2,0) -> 28.8886 | T28: =C28 -> 05C02 | V28: =IFERROR( ( SUMIFS(설정해지!$G:$G, 설정해지!$B:$B,펀드현황!$C28,설정해지!$F:$F,"KRW")-SUMIFS(설정해지!$H:$H, 설정해지!$B:$B,펀드현황!$C28,설정해지!$F:$F,"KRW") ) /100000000,"") -> -3.052232 | W28: =IFERROR( ( SUMIFS(설정해지!$I:$I, 설정해지!$B:$B,펀드현황!$C28,설정해지!$F:$F,"KRW")-SUMIFS(설정해지!$J:$J, 설정해지!$B:$B,펀드현황!$C28,설정해지!$F:$F,"KRW") ) /100000000,"") -> -0.77894544 | X28: =IFERROR( ( SUMIFS(설정해지!$K:$K, 설정해지!$B:$B,펀드현황!$C28,설정해지!$F:$F,"KRW")-SUMIFS(설정해지!$L:$L, 설정해지!$B:$B,펀드현황!$C28,설정해지!$F:$F,"KRW") ) /100000000,"") -> -1.1947915 | Z28: =IFERROR( ( SUMIFS(자금총괄!$G:$G, 자금총괄!$B:$B,펀드현황!$C28,자금총괄!$F:$F,$AB$2) ) /100000000,"") -> 47.296073 | AA28: =Z28/F28 -> 0.026635381 | AB28: =IFERROR( ( SUMIFS(자금총괄!$I:$I, 자금총괄!$B:$B,펀드현황!$C28,자금총괄!$F:$F,$AB$2) ) /100000000,"") -> 46.517128 | AC28: =IFERROR( ( SUMIFS(자금총괄!$K:$K, 자금총괄!$B:$B,펀드현황!$C28,자금총괄!$F:$F,$AB$2) ) /100000000,"") -> 45.322336 | AD28: =IFERROR( ( SUMIFS(자금총괄!$M:$M, 자금총괄!$B:$B,펀드현황!$C28,자금총괄!$F:$F,$AB$2) ) /100000000,"") -> 44.24951 | AE28: =IFERROR( ( SUMIFS(자금총괄!$O:$O, 자금총괄!$B:$B,펀드현황!$C28,자금총괄!$F:$F,$AB$2) ) /100000000,"") -> 43.126797 | AF28: =IFERROR( ( SUMIFS(자금총괄!$Q:$Q, 자금총괄!$B:$B,펀드현황!$C28,자금총괄!$F:$F,$AB$2) ) /100000000,"") -> 456.25417 | AH28: =IFERROR( ( SUMIFS(자금총괄!$G:$G, 자금총괄!$B:$B,펀드현황!$C28,자금총괄!$F:$F,$AI$2)/10000 ),"") -> 0.076967 | AI28: =IFERROR( ( SUMIFS(자금총괄!$I:$I, 자금총괄!$B:$B,펀드현황!$C28,자금총괄!$F:$F,$AI$2)/10000 ),"") -> 0.076967 | AJ28: =IFERROR((SUMIFS(자금총괄!$K:$K,자금총괄!$B:$B,펀드현황!$C28,자금총괄!$F:$F,$AI$2)/10000),"") -> 0.076967 | AK28: =IFERROR((SUMIFS(자금총괄!$M:$M,자금총괄!$B:$B,펀드현황!$C28,자금총괄!$F:$F,$AI$2)/10000),"") -> 0.076967 | AL28: =IFERROR( ( SUMIFS(자금총괄!$O:$O, 자금총괄!$B:$B,펀드현황!$C28,자금총괄!$F:$F,$AI$2) /10000 ),"") -> 0.076967 | AM28: =IFERROR( ( SUMIFS(자금총괄!$Q:$Q, 자금총괄!$B:$B,펀드현황!$C28,자금총괄!$F:$F,$AI$2) /10000 ),"") -> -3200.923
B29: TRP TIF | C29: 05N79 | D29: =VLOOKUP(C29,'MOS4110'!$A:$B,2,0) -> 한국투자TIF알아서평생소득월지급식증권자(채권-재)(모) | E29: =AVERAGEIFS(#REF!,#REF!,펀드현황!$C29)/100000000 -> #REF! | F29: =IFERROR(VLOOKUP($T29,자금총괄!$B:$E,4,0)/100000000,"") -> 2.298198 | G29: =VLOOKUP($C29,'MOS4110'!$A:$BP,펀드현황!G$2,0) -> 43887 | H29: =VLOOKUP($C29,'MOS4110'!$A:$BP,펀드현황!H$2,0) -> 828.68 | I29: =VLOOKUP($C29,'MOS4110'!$A:$BP,펀드현황!I$2,0) -> -0.0643 | J29: =VLOOKUP($C29,'MOS4110'!$A:$BP,펀드현황!J$2,0) -> 3.7375 | K29: =VLOOKUP($C29,'MOS4110'!$A:$BP,펀드현황!K$2,0) -> 4.6116 | L29: =VLOOKUP($C29,'MOS4110'!$A:$BP,펀드현황!L$2,0) -> 5.1973 | M29: =VLOOKUP($C29,'MOS4110'!$A:$BP,펀드현황!M$2,0) -> -1.6575 | N29: =VLOOKUP($C29,'MOS4110'!$A:$BP,펀드현황!N$2,0) -> -3.9116 | ... P29: =VLOOKUP($C29,'MOS4110'!$A:$BP,펀드현황!P$2,0) -> -2.8987 | T29: =C29 -> 05N79 | V29: =IFERROR( ( SUMIFS(설정해지!$G:$G, 설정해지!$B:$B,펀드현황!$C29,설정해지!$F:$F,"KRW")-SUMIFS(설정해지!$H:$H, 설정해지!$B:$B,펀드현황!$C29,설정해지!$F:$F,"KRW") ) /100000000,"") -> -0.07408774 | W29: =IFERROR( ( SUMIFS(설정해지!$I:$I, 설정해지!$B:$B,펀드현황!$C29,설정해지!$F:$F,"KRW")-SUMIFS(설정해지!$J:$J, 설정해지!$B:$B,펀드현황!$C29,설정해지!$F:$F,"KRW") ) /100000000,"") -> 0.00033215 | X29: =IFERROR( ( SUMIFS(설정해지!$K:$K, 설정해지!$B:$B,펀드현황!$C29,설정해지!$F:$F,"KRW")-SUMIFS(설정해지!$L:$L, 설정해지!$B:$B,펀드현황!$C29,설정해지!$F:$F,"KRW") ) /100000000,"") -> 0 | Z29: =IFERROR( ( SUMIFS(자금총괄!$G:$G, 자금총괄!$B:$B,펀드현황!$C29,자금총괄!$F:$F,$AB$2) ) /100000000,"") -> 0.03754319 | AB29: =IFERROR( ( SUMIFS(자금총괄!$I:$I, 자금총괄!$B:$B,펀드현황!$C29,자금총괄!$F:$F,$AB$2) ) /100000000,"") -> 0.03754652 | AC29: =IFERROR( ( SUMIFS(자금총괄!$K:$K, 자금총괄!$B:$B,펀드현황!$C29,자금총괄!$F:$F,$AB$2) ) /100000000,"") -> 0.03754652 | AD29: =IFERROR( ( SUMIFS(자금총괄!$M:$M, 자금총괄!$B:$B,펀드현황!$C29,자금총괄!$F:$F,$AB$2) ) /100000000,"") -> 0.03754652 | AE29: =IFERROR( ( SUMIFS(자금총괄!$O:$O, 자금총괄!$B:$B,펀드현황!$C29,자금총괄!$F:$F,$AB$2) ) /100000000,"") -> 0.03754652 | AF29: =IFERROR( ( SUMIFS(자금총괄!$Q:$Q, 자금총괄!$B:$B,펀드현황!$C29,자금총괄!$F:$F,$AB$2) ) /100000000,"") -> 0.03754652 | AH29: =IFERROR( ( SUMIFS(자금총괄!$G:$G, 자금총괄!$B:$B,펀드현황!$C29,자금총괄!$F:$F,$AI$2)/10000 ),"") -> 0 | AI29: =IFERROR( ( SUMIFS(자금총괄!$I:$I, 자금총괄!$B:$B,펀드현황!$C29,자금총괄!$F:$F,$AI$2)/10000 ),"") -> 0 | AJ29: =IFERROR((SUMIFS(자금총괄!$K:$K,자금총괄!$B:$B,펀드현황!$C29,자금총괄!$F:$F,$AI$2)/10000),"") -> 0 | AK29: =IFERROR((SUMIFS(자금총괄!$M:$M,자금총괄!$B:$B,펀드현황!$C29,자금총괄!$F:$F,$AI$2)/10000),"") -> 0 | AL29: =IFERROR( ( SUMIFS(자금총괄!$O:$O, 자금총괄!$B:$B,펀드현황!$C29,자금총괄!$F:$F,$AI$2) /10000 ),"") -> 0 | AM29: =IFERROR( ( SUMIFS(자금총괄!$Q:$Q, 자금총괄!$B:$B,펀드현황!$C29,자금총괄!$F:$F,$AI$2) /10000 ),"") -> 0
C30: 05N43 | D30: =VLOOKUP(C30,'MOS4110'!$A:$B,2,0) -> 한국투자TIF알아서평생소득월지급식증권자(채혼-재)(모) | E30: =AVERAGEIFS(#REF!,#REF!,펀드현황!$C30)/100000000 -> #REF! | F30: =IFERROR(VLOOKUP($T30,자금총괄!$B:$E,4,0)/100000000,"") -> 26.975954 | G30: =VLOOKUP($C30,'MOS4110'!$A:$BP,펀드현황!G$2,0) -> 43056 | H30: =VLOOKUP($C30,'MOS4110'!$A:$BP,펀드현황!H$2,0) -> 867.93 | I30: =VLOOKUP($C30,'MOS4110'!$A:$BP,펀드현황!I$2,0) -> 1.2971 | J30: =VLOOKUP($C30,'MOS4110'!$A:$BP,펀드현황!J$2,0) -> 5.9944 | K30: =VLOOKUP($C30,'MOS4110'!$A:$BP,펀드현황!K$2,0) -> 7.2232 | L30: =VLOOKUP($C30,'MOS4110'!$A:$BP,펀드현황!L$2,0) -> 9.3681 | M30: =VLOOKUP($C30,'MOS4110'!$A:$BP,펀드현황!M$2,0) -> 3.2786 | N30: =VLOOKUP($C30,'MOS4110'!$A:$BP,펀드현황!N$2,0) -> 0.6715 | ... P30: =VLOOKUP($C30,'MOS4110'!$A:$BP,펀드현황!P$2,0) -> 25.7147 | T30: =C30 -> 05N43 | V30: =IFERROR( ( SUMIFS(설정해지!$G:$G, 설정해지!$B:$B,펀드현황!$C30,설정해지!$F:$F,"KRW")-SUMIFS(설정해지!$H:$H, 설정해지!$B:$B,펀드현황!$C30,설정해지!$F:$F,"KRW") ) /100000000,"") -> 0.0009993 | W30: =IFERROR( ( SUMIFS(설정해지!$I:$I, 설정해지!$B:$B,펀드현황!$C30,설정해지!$F:$F,"KRW")-SUMIFS(설정해지!$J:$J, 설정해지!$B:$B,펀드현황!$C30,설정해지!$F:$F,"KRW") ) /100000000,"") -> -0.00080372 | X30: =IFERROR( ( SUMIFS(설정해지!$K:$K, 설정해지!$B:$B,펀드현황!$C30,설정해지!$F:$F,"KRW")-SUMIFS(설정해지!$L:$L, 설정해지!$B:$B,펀드현황!$C30,설정해지!$F:$F,"KRW") ) /100000000,"") -> -0.00364142 | Z30: =IFERROR( ( SUMIFS(자금총괄!$G:$G, 자금총괄!$B:$B,펀드현황!$C30,자금총괄!$F:$F,$AB$2) ) /100000000,"") -> 0.41630657 | AB30: =IFERROR( ( SUMIFS(자금총괄!$I:$I, 자금총괄!$B:$B,펀드현황!$C30,자금총괄!$F:$F,$AB$2) ) /100000000,"") -> 0.41631856 | AC30: =IFERROR( ( SUMIFS(자금총괄!$K:$K, 자금총괄!$B:$B,펀드현황!$C30,자금총괄!$F:$F,$AB$2) ) /100000000,"") -> 0.41635497 | AD30: =IFERROR( ( SUMIFS(자금총괄!$M:$M, 자금총괄!$B:$B,펀드현황!$C30,자금총괄!$F:$F,$AB$2) ) /100000000,"") -> 0.41636527 | AE30: =IFERROR( ( SUMIFS(자금총괄!$O:$O, 자금총괄!$B:$B,펀드현황!$C30,자금총괄!$F:$F,$AB$2) ) /100000000,"") -> 0.41636527 | AF30: =IFERROR( ( SUMIFS(자금총괄!$Q:$Q, 자금총괄!$B:$B,펀드현황!$C30,자금총괄!$F:$F,$AB$2) ) /100000000,"") -> 0.41636727 | AH30: =IFERROR( ( SUMIFS(자금총괄!$G:$G, 자금총괄!$B:$B,펀드현황!$C30,자금총괄!$F:$F,$AI$2)/10000 ),"") -> 0 | AI30: =IFERROR( ( SUMIFS(자금총괄!$I:$I, 자금총괄!$B:$B,펀드현황!$C30,자금총괄!$F:$F,$AI$2)/10000 ),"") -> 0 | AJ30: =IFERROR((SUMIFS(자금총괄!$K:$K,자금총괄!$B:$B,펀드현황!$C30,자금총괄!$F:$F,$AI$2)/10000),"") -> 0 | AK30: =IFERROR((SUMIFS(자금총괄!$M:$M,자금총괄!$B:$B,펀드현황!$C30,자금총괄!$F:$F,$AI$2)/10000),"") -> 0 | AL30: =IFERROR( ( SUMIFS(자금총괄!$O:$O, 자금총괄!$B:$B,펀드현황!$C30,자금총괄!$F:$F,$AI$2) /10000 ),"") -> 0 | AM30: =IFERROR( ( SUMIFS(자금총괄!$Q:$Q, 자금총괄!$B:$B,펀드현황!$C30,자금총괄!$F:$F,$AI$2) /10000 ),"") -> 0
C31: 05N61 | D31: =VLOOKUP(C31,'MOS4110'!$A:$B,2,0) -> 한국투자TIF알아서평생소득증권자투자신탁(채권-재간접형)(모) | E31: =AVERAGEIFS(#REF!,#REF!,펀드현황!$C31)/100000000 -> #REF! | F31: =IFERROR(VLOOKUP($T31,자금총괄!$B:$E,4,0)/100000000,"") -> 93.765447 | G31: =VLOOKUP($C31,'MOS4110'!$A:$BP,펀드현황!G$2,0) -> 43056 | H31: =VLOOKUP($C31,'MOS4110'!$A:$BP,펀드현황!H$2,0) -> 1080.54 | I31: =VLOOKUP($C31,'MOS4110'!$A:$BP,펀드현황!I$2,0) -> -0.0647 | J31: =VLOOKUP($C31,'MOS4110'!$A:$BP,펀드현황!J$2,0) -> 3.7464 | K31: =VLOOKUP($C31,'MOS4110'!$A:$BP,펀드현황!K$2,0) -> 4.6242 | L31: =VLOOKUP($C31,'MOS4110'!$A:$BP,펀드현황!L$2,0) -> 5.2113 | M31: =VLOOKUP($C31,'MOS4110'!$A:$BP,펀드현황!M$2,0) -> -1.5863 | N31: =VLOOKUP($C31,'MOS4110'!$A:$BP,펀드현황!N$2,0) -> -3.844 | ... P31: =VLOOKUP($C31,'MOS4110'!$A:$BP,펀드현황!P$2,0) -> 8.7055 | T31: =C31 -> 05N61 | V31: =IFERROR( ( SUMIFS(설정해지!$G:$G, 설정해지!$B:$B,펀드현황!$C31,설정해지!$F:$F,"KRW")-SUMIFS(설정해지!$H:$H, 설정해지!$B:$B,펀드현황!$C31,설정해지!$F:$F,"KRW") ) /100000000,"") -> 0.28496425 | W31: =IFERROR( ( SUMIFS(설정해지!$I:$I, 설정해지!$B:$B,펀드현황!$C31,설정해지!$F:$F,"KRW")-SUMIFS(설정해지!$J:$J, 설정해지!$B:$B,펀드현황!$C31,설정해지!$F:$F,"KRW") ) /100000000,"") -> 0.41659024 | X31: =IFERROR( ( SUMIFS(설정해지!$K:$K, 설정해지!$B:$B,펀드현황!$C31,설정해지!$F:$F,"KRW")-SUMIFS(설정해지!$L:$L, 설정해지!$B:$B,펀드현황!$C31,설정해지!$F:$F,"KRW") ) /100000000,"") -> -0.01650754 | Z31: =IFERROR( ( SUMIFS(자금총괄!$G:$G, 자금총괄!$B:$B,펀드현황!$C31,자금총괄!$F:$F,$AB$2) ) /100000000,"") -> 1.9727912 | AB31: =IFERROR( ( SUMIFS(자금총괄!$I:$I, 자금총괄!$B:$B,펀드현황!$C31,자금총괄!$F:$F,$AB$2) ) /100000000,"") -> 1.9778541 | AC31: =IFERROR( ( SUMIFS(자금총괄!$K:$K, 자금총괄!$B:$B,펀드현황!$C31,자금총괄!$F:$F,$AB$2) ) /100000000,"") -> 1.9780192 | AD31: =IFERROR( ( SUMIFS(자금총괄!$M:$M, 자금총괄!$B:$B,펀드현황!$C31,자금총괄!$F:$F,$AB$2) ) /100000000,"") -> 1.9835821 | AE31: =IFERROR( ( SUMIFS(자금총괄!$O:$O, 자금총괄!$B:$B,펀드현황!$C31,자금총괄!$F:$F,$AB$2) ) /100000000,"") -> 1.9836214 | AF31: =IFERROR( ( SUMIFS(자금총괄!$Q:$Q, 자금총괄!$B:$B,펀드현황!$C31,자금총괄!$F:$F,$AB$2) ) /100000000,"") -> 1.9847676 | AH31: =IFERROR( ( SUMIFS(자금총괄!$G:$G, 자금총괄!$B:$B,펀드현황!$C31,자금총괄!$F:$F,$AI$2)/10000 ),"") -> 0 | AI31: =IFERROR( ( SUMIFS(자금총괄!$I:$I, 자금총괄!$B:$B,펀드현황!$C31,자금총괄!$F:$F,$AI$2)/10000 ),"") -> 0 | AJ31: =IFERROR((SUMIFS(자금총괄!$K:$K,자금총괄!$B:$B,펀드현황!$C31,자금총괄!$F:$F,$AI$2)/10000),"") -> 0 | AK31: =IFERROR((SUMIFS(자금총괄!$M:$M,자금총괄!$B:$B,펀드현황!$C31,자금총괄!$F:$F,$AI$2)/10000),"") -> 0 | AL31: =IFERROR( ( SUMIFS(자금총괄!$O:$O, 자금총괄!$B:$B,펀드현황!$C31,자금총괄!$F:$F,$AI$2) /10000 ),"") -> 0 | AM31: =IFERROR( ( SUMIFS(자금총괄!$Q:$Q, 자금총괄!$B:$B,펀드현황!$C31,자금총괄!$F:$F,$AI$2) /10000 ),"") -> 0
C32: 05N25 | D32: =VLOOKUP(C32,'MOS4110'!$A:$B,2,0) -> 한국투자TIF알아서평생소득증권자투자신탁(채혼-재)(모) | E32: =AVERAGEIFS(#REF!,#REF!,펀드현황!$C32)/100000000 -> #REF! | F32: =IFERROR(VLOOKUP($T32,자금총괄!$B:$E,4,0)/100000000,"") -> 74.041712 | G32: =VLOOKUP($C32,'MOS4110'!$A:$BP,펀드현황!G$2,0) -> 43056 | H32: =VLOOKUP($C32,'MOS4110'!$A:$BP,펀드현황!H$2,0) -> 1244.72 | I32: =VLOOKUP($C32,'MOS4110'!$A:$BP,펀드현황!I$2,0) -> 1.2939 | J32: =VLOOKUP($C32,'MOS4110'!$A:$BP,펀드현황!J$2,0) -> 5.9796 | K32: =VLOOKUP($C32,'MOS4110'!$A:$BP,펀드현황!K$2,0) -> 7.2037 | L32: =VLOOKUP($C32,'MOS4110'!$A:$BP,펀드현황!L$2,0) -> 9.3577 | M32: =VLOOKUP($C32,'MOS4110'!$A:$BP,펀드현황!M$2,0) -> 3.2762 | N32: =VLOOKUP($C32,'MOS4110'!$A:$BP,펀드현황!N$2,0) -> 0.5331 | ... P32: =VLOOKUP($C32,'MOS4110'!$A:$BP,펀드현황!P$2,0) -> 25.4406 | T32: =C32 -> 05N25 | V32: =IFERROR( ( SUMIFS(설정해지!$G:$G, 설정해지!$B:$B,펀드현황!$C32,설정해지!$F:$F,"KRW")-SUMIFS(설정해지!$H:$H, 설정해지!$B:$B,펀드현황!$C32,설정해지!$F:$F,"KRW") ) /100000000,"") -> 0.0849163 | W32: =IFERROR( ( SUMIFS(설정해지!$I:$I, 설정해지!$B:$B,펀드현황!$C32,설정해지!$F:$F,"KRW")-SUMIFS(설정해지!$J:$J, 설정해지!$B:$B,펀드현황!$C32,설정해지!$F:$F,"KRW") ) /100000000,"") -> 0.05007824 | X32: =IFERROR( ( SUMIFS(설정해지!$K:$K, 설정해지!$B:$B,펀드현황!$C32,설정해지!$F:$F,"KRW")-SUMIFS(설정해지!$L:$L, 설정해지!$B:$B,펀드현황!$C32,설정해지!$F:$F,"KRW") ) /100000000,"") -> -0.32826277 | Z32: =IFERROR( ( SUMIFS(자금총괄!$G:$G, 자금총괄!$B:$B,펀드현황!$C32,자금총괄!$F:$F,$AB$2) ) /100000000,"") -> 1.5641388 | AB32: =IFERROR( ( SUMIFS(자금총괄!$I:$I, 자금총괄!$B:$B,펀드현황!$C32,자금총괄!$F:$F,$AB$2) ) /100000000,"") -> 1.5648052 | AC32: =IFERROR( ( SUMIFS(자금총괄!$K:$K, 자금총괄!$B:$B,펀드현황!$C32,자금총괄!$F:$F,$AB$2) ) /100000000,"") -> 1.5680878 | AD32: =IFERROR( ( SUMIFS(자금총괄!$M:$M, 자금총괄!$B:$B,펀드현황!$C32,자금총괄!$F:$F,$AB$2) ) /100000000,"") -> 1.5681974 | AE32: =IFERROR( ( SUMIFS(자금총괄!$O:$O, 자금총괄!$B:$B,펀드현황!$C32,자금총괄!$F:$F,$AB$2) ) /100000000,"") -> 1.5681974 | AF32: =IFERROR( ( SUMIFS(자금총괄!$Q:$Q, 자금총괄!$B:$B,펀드현황!$C32,자금총괄!$F:$F,$AB$2) ) /100000000,"") -> 1.5682042 | AH32: =IFERROR( ( SUMIFS(자금총괄!$G:$G, 자금총괄!$B:$B,펀드현황!$C32,자금총괄!$F:$F,$AI$2)/10000 ),"") -> 0 | AI32: =IFERROR( ( SUMIFS(자금총괄!$I:$I, 자금총괄!$B:$B,펀드현황!$C32,자금총괄!$F:$F,$AI$2)/10000 ),"") -> 0 | AJ32: =IFERROR((SUMIFS(자금총괄!$K:$K,자금총괄!$B:$B,펀드현황!$C32,자금총괄!$F:$F,$AI$2)/10000),"") -> 0 | AK32: =IFERROR((SUMIFS(자금총괄!$M:$M,자금총괄!$B:$B,펀드현황!$C32,자금총괄!$F:$F,$AI$2)/10000),"") -> 0 | AL32: =IFERROR( ( SUMIFS(자금총괄!$O:$O, 자금총괄!$B:$B,펀드현황!$C32,자금총괄!$F:$F,$AI$2) /10000 ),"") -> 0 | AM32: =IFERROR( ( SUMIFS(자금총괄!$Q:$Q, 자금총괄!$B:$B,펀드현황!$C32,자금총괄!$F:$F,$AI$2) /10000 ),"") -> 0
D33: TDF/TIF 합계 | E33: =SUM(E14:E32) -> #REF! | F33: =SUM(F14:F32) -> 14502.068
B36: 자산배분 | C36: 03V94 | D36: 한국투자글로벌채권솔루션(모 - 채권) | E36: =AVERAGEIFS(#REF!,#REF!,펀드현황!$C36)/100000000 -> #REF! | F36: =IFERROR(VLOOKUP($T36,자금총괄!$B:$E,4,0)/100000000,"") -> 142.05941 | G36: =VLOOKUP($C36,'MOS4110'!$A:$BP,펀드현황!G$2,0) -> 43475 | H36: =VLOOKUP($C36,'MOS4110'!$A:$BP,펀드현황!H$2,0) -> 906.66 | I36: =VLOOKUP($C36,'MOS4110'!$A:$BP,펀드현황!I$2,0) -> -0.495 | J36: =VLOOKUP($C36,'MOS4110'!$A:$BP,펀드현황!J$2,0) -> 2.3064 | K36: =VLOOKUP($C36,'MOS4110'!$A:$BP,펀드현황!K$2,0) -> 1.0814 | L36: =VLOOKUP($C36,'MOS4110'!$A:$BP,펀드현황!L$2,0) -> -1.9212 | M36: =VLOOKUP($C36,'MOS4110'!$A:$BP,펀드현황!M$2,0) -> -8.7096 | N36: =VLOOKUP($C36,'MOS4110'!$A:$BP,펀드현황!N$2,0) -> -8.6608 | ... Q36: =VLOOKUP($C36,'MOS4110'!$A:$BP,펀드현황!Q$2,0) -> 0.9774 | S36: 자산배분 | T36: =C36 -> 03V94 | V36: =IFERROR( ( SUMIFS(설정해지!$G:$G, 설정해지!$B:$B,펀드현황!$C36,설정해지!$F:$F,"KRW")-SUMIFS(설정해지!$H:$H, 설정해지!$B:$B,펀드현황!$C36,설정해지!$F:$F,"KRW") ) /100000000,"") -> -0.00986804 | W36: =IFERROR( ( SUMIFS(설정해지!$I:$I, 설정해지!$B:$B,펀드현황!$C36,설정해지!$F:$F,"KRW")-SUMIFS(설정해지!$J:$J, 설정해지!$B:$B,펀드현황!$C36,설정해지!$F:$F,"KRW") ) /100000000,"") -> -0.35088132 | X36: =IFERROR( ( SUMIFS(설정해지!$K:$K, 설정해지!$B:$B,펀드현황!$C36,설정해지!$F:$F,"KRW")-SUMIFS(설정해지!$L:$L, 설정해지!$B:$B,펀드현황!$C36,설정해지!$F:$F,"KRW") ) /100000000,"") -> -0.11800391 | Z36: =IFERROR( ( SUMIFS(자금총괄!$G:$G, 자금총괄!$B:$B,펀드현황!$C36,자금총괄!$F:$F,$AB$2) ) /100000000,"") -> 1.1464338 | AA36: =Z36/F36 -> 0.0080701013 | AB36: =IFERROR( ( SUMIFS(자금총괄!$I:$I, 자금총괄!$B:$B,펀드현황!$C36,자금총괄!$F:$F,$AB$2) ) /100000000,"") -> 3.6077325 | AC36: =IFERROR( ( SUMIFS(자금총괄!$K:$K, 자금총괄!$B:$B,펀드현황!$C36,자금총괄!$F:$F,$AB$2) ) /100000000,"") -> 3.4897286 | AD36: =IFERROR( ( SUMIFS(자금총괄!$M:$M, 자금총괄!$B:$B,펀드현황!$C36,자금총괄!$F:$F,$AB$2) ) /100000000,"") -> 3.3393575 | AE36: =IFERROR( ( SUMIFS(자금총괄!$O:$O, 자금총괄!$B:$B,펀드현황!$C36,자금총괄!$F:$F,$AB$2) ) /100000000,"") -> 3.240023 | AF36: =IFERROR( ( SUMIFS(자금총괄!$Q:$Q, 자금총괄!$B:$B,펀드현황!$C36,자금총괄!$F:$F,$AB$2) ) /100000000,"") -> 2.9687127 | AH36: =IFERROR( ( SUMIFS(자금총괄!$G:$G, 자금총괄!$B:$B,펀드현황!$C36,자금총괄!$F:$F,$AI$2)/10000 ),"") -> 28.413239 | AI36: =IFERROR( ( SUMIFS(자금총괄!$I:$I, 자금총괄!$B:$B,펀드현황!$C36,자금총괄!$F:$F,$AI$2)/10000 ),"") -> 11.527004 | AJ36: =IFERROR((SUMIFS(자금총괄!$K:$K,자금총괄!$B:$B,펀드현황!$C36,자금총괄!$F:$F,$AI$2)/10000),"") -> 11.527004 | AK36: =IFERROR((SUMIFS(자금총괄!$M:$M,자금총괄!$B:$B,펀드현황!$C36,자금총괄!$F:$F,$AI$2)/10000),"") -> 11.527004 | AL36: =IFERROR( ( SUMIFS(자금총괄!$O:$O, 자금총괄!$B:$B,펀드현황!$C36,자금총괄!$F:$F,$AI$2) /10000 ),"") -> 11.527004 | AM36: =IFERROR( ( SUMIFS(자금총괄!$Q:$Q, 자금총괄!$B:$B,펀드현황!$C36,자금총괄!$F:$F,$AI$2) /10000 ),"") -> 11.527004
C37: 03V95 | D37: 한국투자글로벌주식솔루션(모 - 주식) | E37: =AVERAGEIFS(#REF!,#REF!,펀드현황!$C37)/100000000 -> #REF! | F37: =IFERROR(VLOOKUP($T37,자금총괄!$B:$E,4,0)/100000000,"") -> 53.662705 | G37: =VLOOKUP($C37,'MOS4110'!$A:$BP,펀드현황!G$2,0) -> 43475 | H37: =VLOOKUP($C37,'MOS4110'!$A:$BP,펀드현황!H$2,0) -> 1293.33 | I37: =VLOOKUP($C37,'MOS4110'!$A:$BP,펀드현황!I$2,0) -> 3.4548 | J37: =VLOOKUP($C37,'MOS4110'!$A:$BP,펀드현황!J$2,0) -> 8.5529 | K37: =VLOOKUP($C37,'MOS4110'!$A:$BP,펀드현황!K$2,0) -> 11.1608 | L37: =VLOOKUP($C37,'MOS4110'!$A:$BP,펀드현황!L$2,0) -> 14.9334 | M37: =VLOOKUP($C37,'MOS4110'!$A:$BP,펀드현황!M$2,0) -> -0.1181 | N37: =VLOOKUP($C37,'MOS4110'!$A:$BP,펀드현황!N$2,0) -> 1.4102 | ... Q37: =VLOOKUP($C37,'MOS4110'!$A:$BP,펀드현황!Q$2,0) -> 0.3252 | T37: =C37 -> 03V95 | V37: =IFERROR( ( SUMIFS(설정해지!$G:$G, 설정해지!$B:$B,펀드현황!$C37,설정해지!$F:$F,"KRW")-SUMIFS(설정해지!$H:$H, 설정해지!$B:$B,펀드현황!$C37,설정해지!$F:$F,"KRW") ) /100000000,"") -> -0.02706403 | W37: =IFERROR( ( SUMIFS(설정해지!$I:$I, 설정해지!$B:$B,펀드현황!$C37,설정해지!$F:$F,"KRW")-SUMIFS(설정해지!$J:$J, 설정해지!$B:$B,펀드현황!$C37,설정해지!$F:$F,"KRW") ) /100000000,"") -> -0.10530365 | X37: =IFERROR( ( SUMIFS(설정해지!$K:$K, 설정해지!$B:$B,펀드현황!$C37,설정해지!$F:$F,"KRW")-SUMIFS(설정해지!$L:$L, 설정해지!$B:$B,펀드현황!$C37,설정해지!$F:$F,"KRW") ) /100000000,"") -> -0.12312827 | Z37: =IFERROR( ( SUMIFS(자금총괄!$G:$G, 자금총괄!$B:$B,펀드현황!$C37,자금총괄!$F:$F,$AB$2) ) /100000000,"") -> 0.45504635 | AA37: =Z37/F37 -> 0.0084797505 | AB37: =IFERROR( ( SUMIFS(자금총괄!$I:$I, 자금총괄!$B:$B,펀드현황!$C37,자금총괄!$F:$F,$AB$2) ) /100000000,"") -> 2.2356927 | AC37: =IFERROR( ( SUMIFS(자금총괄!$K:$K, 자금총괄!$B:$B,펀드현황!$C37,자금총괄!$F:$F,$AB$2) ) /100000000,"") -> 2.1125644 | AD37: =IFERROR( ( SUMIFS(자금총괄!$M:$M, 자금총괄!$B:$B,펀드현황!$C37,자금총괄!$F:$F,$AB$2) ) /100000000,"") -> 1.9106337 | AE37: =IFERROR( ( SUMIFS(자금총괄!$O:$O, 자금총괄!$B:$B,펀드현황!$C37,자금총괄!$F:$F,$AB$2) ) /100000000,"") -> 1.8214086 | AF37: =IFERROR( ( SUMIFS(자금총괄!$Q:$Q, 자금총괄!$B:$B,펀드현황!$C37,자금총괄!$F:$F,$AB$2) ) /100000000,"") -> 1.4637189 | AH37: =IFERROR( ( SUMIFS(자금총괄!$G:$G, 자금총괄!$B:$B,펀드현황!$C37,자금총괄!$F:$F,$AI$2)/10000 ),"") -> 26.235509 | AI37: =IFERROR( ( SUMIFS(자금총괄!$I:$I, 자금총괄!$B:$B,펀드현황!$C37,자금총괄!$F:$F,$AI$2)/10000 ),"") -> 13.517649 | AJ37: =IFERROR((SUMIFS(자금총괄!$K:$K,자금총괄!$B:$B,펀드현황!$C37,자금총괄!$F:$F,$AI$2)/10000),"") -> 13.517649 | AK37: =IFERROR((SUMIFS(자금총괄!$M:$M,자금총괄!$B:$B,펀드현황!$C37,자금총괄!$F:$F,$AI$2)/10000),"") -> 13.517649 | AL37: =IFERROR( ( SUMIFS(자금총괄!$O:$O, 자금총괄!$B:$B,펀드현황!$C37,자금총괄!$F:$F,$AI$2) /10000 ),"") -> 13.517649 | AM37: =IFERROR( ( SUMIFS(자금총괄!$Q:$Q, 자금총괄!$B:$B,펀드현황!$C37,자금총괄!$F:$F,$AI$2) /10000 ),"") -> 13.517649
C38: 05H80 | D38: EMP 글로벌자산배분 펀드 (채권혼합) | E38: =AVERAGEIFS(#REF!,#REF!,펀드현황!$C38)/100000000 -> #REF! | F38: =IFERROR(VLOOKUP($T38,자금총괄!$B:$E,4,0)/100000000,"") -> 35.700717 | G38: =VLOOKUP($C38,'MOS4110'!$A:$BP,펀드현황!G$2,0) -> 42215 | H38: =VLOOKUP($C38,'MOS4110'!$A:$BP,펀드현황!H$2,0) -> 1123.98 | I38: =VLOOKUP($C38,'MOS4110'!$A:$BP,펀드현황!I$2,0) -> 1.041 | J38: =VLOOKUP($C38,'MOS4110'!$A:$BP,펀드현황!J$2,0) -> 4.5086 | K38: =VLOOKUP($C38,'MOS4110'!$A:$BP,펀드현황!K$2,0) -> 4.7414 | L38: =VLOOKUP($C38,'MOS4110'!$A:$BP,펀드현황!L$2,0) -> 4.2654 | M38: =VLOOKUP($C38,'MOS4110'!$A:$BP,펀드현황!M$2,0) -> -4.5772 | N38: =VLOOKUP($C38,'MOS4110'!$A:$BP,펀드현황!N$2,0) -> -4.0377 | ... Q38: =VLOOKUP($C38,'MOS4110'!$A:$BP,펀드현황!Q$2,0) -> 0.754 | T38: =C38 -> 05H80 | V38: =IFERROR( ( SUMIFS(설정해지!$G:$G, 설정해지!$B:$B,펀드현황!$C38,설정해지!$F:$F,"KRW")-SUMIFS(설정해지!$H:$H, 설정해지!$B:$B,펀드현황!$C38,설정해지!$F:$F,"KRW") ) /100000000,"") -> 0.00959031 | W38: =IFERROR( ( SUMIFS(설정해지!$I:$I, 설정해지!$B:$B,펀드현황!$C38,설정해지!$F:$F,"KRW")-SUMIFS(설정해지!$J:$J, 설정해지!$B:$B,펀드현황!$C38,설정해지!$F:$F,"KRW") ) /100000000,"") -> -0.12228974 | X38: =IFERROR( ( SUMIFS(설정해지!$K:$K, 설정해지!$B:$B,펀드현황!$C38,설정해지!$F:$F,"KRW")-SUMIFS(설정해지!$L:$L, 설정해지!$B:$B,펀드현황!$C38,설정해지!$F:$F,"KRW") ) /100000000,"") -> -0.05134424 | Z38: =IFERROR( ( SUMIFS(자금총괄!$G:$G, 자금총괄!$B:$B,펀드현황!$C38,자금총괄!$F:$F,$AB$2) ) /100000000,"") -> 0.79721226 | AA38: =Z38/F38 -> 0.022330427 | AB38: =IFERROR( ( SUMIFS(자금총괄!$I:$I, 자금총괄!$B:$B,펀드현황!$C38,자금총괄!$F:$F,$AB$2) ) /100000000,"") -> 0.7999575 | AC38: =IFERROR( ( SUMIFS(자금총괄!$K:$K, 자금총괄!$B:$B,펀드현황!$C38,자금총괄!$F:$F,$AB$2) ) /100000000,"") -> 0.80098438 | AD38: =IFERROR( ( SUMIFS(자금총괄!$M:$M, 자금총괄!$B:$B,펀드현황!$C38,자금총괄!$F:$F,$AB$2) ) /100000000,"") -> 0.80108596 | AE38: =IFERROR( ( SUMIFS(자금총괄!$O:$O, 자금총괄!$B:$B,펀드현황!$C38,자금총괄!$F:$F,$AB$2) ) /100000000,"") -> 0.80317886 | AF38: =IFERROR( ( SUMIFS(자금총괄!$Q:$Q, 자금총괄!$B:$B,펀드현황!$C38,자금총괄!$F:$F,$AB$2) ) /100000000,"") -> 0.80391971 | AH38: =IFERROR( ( SUMIFS(자금총괄!$G:$G, 자금총괄!$B:$B,펀드현황!$C38,자금총괄!$F:$F,$AI$2)/10000 ),"") -> 0 | AI38: =IFERROR( ( SUMIFS(자금총괄!$I:$I, 자금총괄!$B:$B,펀드현황!$C38,자금총괄!$F:$F,$AI$2)/10000 ),"") -> 0 | AJ38: =IFERROR((SUMIFS(자금총괄!$K:$K,자금총괄!$B:$B,펀드현황!$C38,자금총괄!$F:$F,$AI$2)/10000),"") -> 0 | AK38: =IFERROR((SUMIFS(자금총괄!$M:$M,자금총괄!$B:$B,펀드현황!$C38,자금총괄!$F:$F,$AI$2)/10000),"") -> 0 | AL38: =IFERROR( ( SUMIFS(자금총괄!$O:$O, 자금총괄!$B:$B,펀드현황!$C38,자금총괄!$F:$F,$AI$2) /10000 ),"") -> 0 | AM38: =IFERROR( ( SUMIFS(자금총괄!$Q:$Q, 자금총괄!$B:$B,펀드현황!$C38,자금총괄!$F:$F,$AI$2) /10000 ),"") -> 0
C39: 05H73 | D39: EMP 글로벌자산배분 펀드 (주식혼합) | E39: =AVERAGEIFS(#REF!,#REF!,펀드현황!$C39)/100000000 -> #REF! | F39: =IFERROR(VLOOKUP($T39,자금총괄!$B:$E,4,0)/100000000,"") -> 66.648198 | G39: =VLOOKUP($C39,'MOS4110'!$A:$BP,펀드현황!G$2,0) -> 42215 | H39: =VLOOKUP($C39,'MOS4110'!$A:$BP,펀드현황!H$2,0) -> 1230.95 | I39: =VLOOKUP($C39,'MOS4110'!$A:$BP,펀드현황!I$2,0) -> 1.8189 | J39: =VLOOKUP($C39,'MOS4110'!$A:$BP,펀드현황!J$2,0) -> 5.769 | K39: =VLOOKUP($C39,'MOS4110'!$A:$BP,펀드현황!K$2,0) -> 6.7717 | L39: =VLOOKUP($C39,'MOS4110'!$A:$BP,펀드현황!L$2,0) -> 7.6431 | M39: =VLOOKUP($C39,'MOS4110'!$A:$BP,펀드현황!M$2,0) -> -3.1789 | N39: =VLOOKUP($C39,'MOS4110'!$A:$BP,펀드현황!N$2,0) -> -2.2973 | ... Q39: =VLOOKUP($C39,'MOS4110'!$A:$BP,펀드현황!Q$2,0) -> 1.2049 | T39: =C39 -> 05H73 | V39: =IFERROR( ( SUMIFS(설정해지!$G:$G, 설정해지!$B:$B,펀드현황!$C39,설정해지!$F:$F,"KRW")-SUMIFS(설정해지!$H:$H, 설정해지!$B:$B,펀드현황!$C39,설정해지!$F:$F,"KRW") ) /100000000,"") -> -0.04422389 | W39: =IFERROR( ( SUMIFS(설정해지!$I:$I, 설정해지!$B:$B,펀드현황!$C39,설정해지!$F:$F,"KRW")-SUMIFS(설정해지!$J:$J, 설정해지!$B:$B,펀드현황!$C39,설정해지!$F:$F,"KRW") ) /100000000,"") -> -0.08745532 | X39: =IFERROR( ( SUMIFS(설정해지!$K:$K, 설정해지!$B:$B,펀드현황!$C39,설정해지!$F:$F,"KRW")-SUMIFS(설정해지!$L:$L, 설정해지!$B:$B,펀드현황!$C39,설정해지!$F:$F,"KRW") ) /100000000,"") -> -0.16696049 | Z39: =IFERROR( ( SUMIFS(자금총괄!$G:$G, 자금총괄!$B:$B,펀드현황!$C39,자금총괄!$F:$F,$AB$2) ) /100000000,"") -> 1.7180016 | AA39: =Z39/F39 -> 0.025777165 | AB39: =IFERROR( ( SUMIFS(자금총괄!$I:$I, 자금총괄!$B:$B,펀드현황!$C39,자금총괄!$F:$F,$AB$2) ) /100000000,"") -> 1.7226957 | AC39: =IFERROR( ( SUMIFS(자금총괄!$K:$K, 자금총괄!$B:$B,펀드현황!$C39,자금총괄!$F:$F,$AB$2) ) /100000000,"") -> 1.7260349 | AD39: =IFERROR( ( SUMIFS(자금총괄!$M:$M, 자금총괄!$B:$B,펀드현황!$C39,자금총괄!$F:$F,$AB$2) ) /100000000,"") -> 1.7325662 | AE39: =IFERROR( ( SUMIFS(자금총괄!$O:$O, 자금총괄!$B:$B,펀드현황!$C39,자금총괄!$F:$F,$AB$2) ) /100000000,"") -> 1.7340868 | AF39: =IFERROR( ( SUMIFS(자금총괄!$Q:$Q, 자금총괄!$B:$B,펀드현황!$C39,자금총괄!$F:$F,$AB$2) ) /100000000,"") -> 1.7452821 | AH39: =IFERROR( ( SUMIFS(자금총괄!$G:$G, 자금총괄!$B:$B,펀드현황!$C39,자금총괄!$F:$F,$AI$2)/10000 ),"") -> 0 | AI39: =IFERROR( ( SUMIFS(자금총괄!$I:$I, 자금총괄!$B:$B,펀드현황!$C39,자금총괄!$F:$F,$AI$2)/10000 ),"") -> 0 | AJ39: =IFERROR((SUMIFS(자금총괄!$K:$K,자금총괄!$B:$B,펀드현황!$C39,자금총괄!$F:$F,$AI$2)/10000),"") -> 0 | AK39: =IFERROR((SUMIFS(자금총괄!$M:$M,자금총괄!$B:$B,펀드현황!$C39,자금총괄!$F:$F,$AI$2)/10000),"") -> 0 | AL39: =IFERROR( ( SUMIFS(자금총괄!$O:$O, 자금총괄!$B:$B,펀드현황!$C39,자금총괄!$F:$F,$AI$2) /10000 ),"") -> 0 | AM39: =IFERROR( ( SUMIFS(자금총괄!$Q:$Q, 자금총괄!$B:$B,펀드현황!$C39,자금총괄!$F:$F,$AI$2) /10000 ),"") -> 0
C40: 05W58 | D40: 한국투자다이나믹헤지인컴증권자투자신탁(채권-재간접형)(모) | E40: =AVERAGEIFS(#REF!,#REF!,펀드현황!$C40)/100000000 -> #REF! | F40: =IFERROR(VLOOKUP($T40,자금총괄!$B:$E,4,0)/100000000,"") -> 97.425114 | G40: =VLOOKUP($C40,'MOS4110'!$A:$BP,펀드현황!G$2,0) -> 43703 | H40: =VLOOKUP($C40,'MOS4110'!$A:$BP,펀드현황!H$2,0) -> 927.51 | I40: =VLOOKUP($C40,'MOS4110'!$A:$BP,펀드현황!I$2,0) -> -0.4796 | J40: =VLOOKUP($C40,'MOS4110'!$A:$BP,펀드현황!J$2,0) -> 2.2027 | K40: =VLOOKUP($C40,'MOS4110'!$A:$BP,펀드현황!K$2,0) -> 1.0657 | L40: =VLOOKUP($C40,'MOS4110'!$A:$BP,펀드현황!L$2,0) -> -1.7583 | M40: =VLOOKUP($C40,'MOS4110'!$A:$BP,펀드현황!M$2,0) -> -8.2046 | N40: =VLOOKUP($C40,'MOS4110'!$A:$BP,펀드현황!N$2,0) -> -7.9285 | ... Q40: =VLOOKUP($C40,'MOS4110'!$A:$BP,펀드현황!Q$2,0) -> 1.0178 | T40: =C40 -> 05W58 | V40: =IFERROR( ( SUMIFS(설정해지!$G:$G, 설정해지!$B:$B,펀드현황!$C40,설정해지!$F:$F,"KRW")-SUMIFS(설정해지!$H:$H, 설정해지!$B:$B,펀드현황!$C40,설정해지!$F:$F,"KRW") ) /100000000,"") -> 0.00580805 | W40: =IFERROR( ( SUMIFS(설정해지!$I:$I, 설정해지!$B:$B,펀드현황!$C40,설정해지!$F:$F,"KRW")-SUMIFS(설정해지!$J:$J, 설정해지!$B:$B,펀드현황!$C40,설정해지!$F:$F,"KRW") ) /100000000,"") -> -0.23423584 | X40: =IFERROR( ( SUMIFS(설정해지!$K:$K, 설정해지!$B:$B,펀드현황!$C40,설정해지!$F:$F,"KRW")-SUMIFS(설정해지!$L:$L, 설정해지!$B:$B,펀드현황!$C40,설정해지!$F:$F,"KRW") ) /100000000,"") -> -0.01809937 | Z40: =IFERROR( ( SUMIFS(자금총괄!$G:$G, 자금총괄!$B:$B,펀드현황!$C40,자금총괄!$F:$F,$AB$2) ) /100000000,"") -> 1.9773121 | AA40: =Z40/F40 -> 0.020295712 | AB40: =IFERROR( ( SUMIFS(자금총괄!$I:$I, 자금총괄!$B:$B,펀드현황!$C40,자금총괄!$F:$F,$AB$2) ) /100000000,"") -> 1.9820768 | AC40: =IFERROR( ( SUMIFS(자금총괄!$K:$K, 자금총괄!$B:$B,펀드현황!$C40,자금총괄!$F:$F,$AB$2) ) /100000000,"") -> 1.9824388 | AD40: =IFERROR( ( SUMIFS(자금총괄!$M:$M, 자금총괄!$B:$B,펀드현황!$C40,자금총괄!$F:$F,$AB$2) ) /100000000,"") -> 1.9827138 | AE40: =IFERROR( ( SUMIFS(자금총괄!$O:$O, 자금총괄!$B:$B,펀드현황!$C40,자금총괄!$F:$F,$AB$2) ) /100000000,"") -> 1.9827975 | AF40: =IFERROR( ( SUMIFS(자금총괄!$Q:$Q, 자금총괄!$B:$B,펀드현황!$C40,자금총괄!$F:$F,$AB$2) ) /100000000,"") -> 1.9831947 | AH40: =IFERROR( ( SUMIFS(자금총괄!$G:$G, 자금총괄!$B:$B,펀드현황!$C40,자금총괄!$F:$F,$AI$2)/10000 ),"") -> 0 | AI40: =IFERROR( ( SUMIFS(자금총괄!$I:$I, 자금총괄!$B:$B,펀드현황!$C40,자금총괄!$F:$F,$AI$2)/10000 ),"") -> 0 | AJ40: =IFERROR((SUMIFS(자금총괄!$K:$K,자금총괄!$B:$B,펀드현황!$C40,자금총괄!$F:$F,$AI$2)/10000),"") -> 0 | AK40: =IFERROR((SUMIFS(자금총괄!$M:$M,자금총괄!$B:$B,펀드현황!$C40,자금총괄!$F:$F,$AI$2)/10000),"") -> 0 | AL40: =IFERROR( ( SUMIFS(자금총괄!$O:$O, 자금총괄!$B:$B,펀드현황!$C40,자금총괄!$F:$F,$AI$2) /10000 ),"") -> 0 | AM40: =IFERROR( ( SUMIFS(자금총괄!$Q:$Q, 자금총괄!$B:$B,펀드현황!$C40,자금총괄!$F:$F,$AI$2) /10000 ),"") -> 0
C41: 2JM57 | D41: Dream Big 글로벌 자산배분형70 (일임) | E41: =AVERAGEIFS(#REF!,#REF!,펀드현황!$C41)/100000000 -> #REF! | F41: =IFERROR(VLOOKUP($T41,자금총괄!$B:$E,4,0)/100000000,"") -> 234.87513 | G41: =VLOOKUP($C41,'MOS4110'!$A:$BP,펀드현황!G$2,0) -> 42825 | H41: =VLOOKUP($C41,'MOS4110'!$A:$BP,펀드현황!H$2,0) -> 1358.6 | I41: =VLOOKUP($C41,'MOS4110'!$A:$BP,펀드현황!I$2,0) -> 2.5088 | J41: =VLOOKUP($C41,'MOS4110'!$A:$BP,펀드현황!J$2,0) -> 6.7159 | K41: =VLOOKUP($C41,'MOS4110'!$A:$BP,펀드현황!K$2,0) -> 8.5144 | L41: =VLOOKUP($C41,'MOS4110'!$A:$BP,펀드현황!L$2,0) -> 11.0766 | M41: =VLOOKUP($C41,'MOS4110'!$A:$BP,펀드현황!M$2,0) -> 2.5088 | N41: =VLOOKUP($C41,'MOS4110'!$A:$BP,펀드현황!N$2,0) -> 5.7663 | ... Q41: =VLOOKUP($C41,'MOS4110'!$A:$BP,펀드현황!Q$2,0) -> 0.8173 | T41: =C41 -> 2JM57 | V41: =IFERROR( ( SUMIFS(설정해지!$G:$G, 설정해지!$B:$B,펀드현황!$C41,설정해지!$F:$F,"KRW")-SUMIFS(설정해지!$H:$H, 설정해지!$B:$B,펀드현황!$C41,설정해지!$F:$F,"KRW") ) /100000000,"") -> 0 | W41: =IFERROR( ( SUMIFS(설정해지!$I:$I, 설정해지!$B:$B,펀드현황!$C41,설정해지!$F:$F,"KRW")-SUMIFS(설정해지!$J:$J, 설정해지!$B:$B,펀드현황!$C41,설정해지!$F:$F,"KRW") ) /100000000,"") -> 0 | X41: =IFERROR( ( SUMIFS(설정해지!$K:$K, 설정해지!$B:$B,펀드현황!$C41,설정해지!$F:$F,"KRW")-SUMIFS(설정해지!$L:$L, 설정해지!$B:$B,펀드현황!$C41,설정해지!$F:$F,"KRW") ) /100000000,"") -> 0 | Z41: =IFERROR( ( SUMIFS(자금총괄!$G:$G, 자금총괄!$B:$B,펀드현황!$C41,자금총괄!$F:$F,$AB$2) ) /100000000,"") -> 4.3148607 | AA41: =Z41/F41 -> 0.018370871 | AB41: =IFERROR( ( SUMIFS(자금총괄!$I:$I, 자금총괄!$B:$B,펀드현황!$C41,자금총괄!$F:$F,$AB$2) ) /100000000,"") -> 4.3148607 | AC41: =IFERROR( ( SUMIFS(자금총괄!$K:$K, 자금총괄!$B:$B,펀드현황!$C41,자금총괄!$F:$F,$AB$2) ) /100000000,"") -> 4.2889562 | AD41: =IFERROR( ( SUMIFS(자금총괄!$M:$M, 자금총괄!$B:$B,펀드현황!$C41,자금총괄!$F:$F,$AB$2) ) /100000000,"") -> 4.2889562 | AE41: =IFERROR( ( SUMIFS(자금총괄!$O:$O, 자금총괄!$B:$B,펀드현황!$C41,자금총괄!$F:$F,$AB$2) ) /100000000,"") -> 4.2889562 | AF41: =IFERROR( ( SUMIFS(자금총괄!$Q:$Q, 자금총괄!$B:$B,펀드현황!$C41,자금총괄!$F:$F,$AB$2) ) /100000000,"") -> 4.2889562 | AH41: =IFERROR( ( SUMIFS(자금총괄!$G:$G, 자금총괄!$B:$B,펀드현황!$C41,자금총괄!$F:$F,$AI$2)/10000 ),"") -> 50.266405 | AI41: =IFERROR( ( SUMIFS(자금총괄!$I:$I, 자금총괄!$B:$B,펀드현황!$C41,자금총괄!$F:$F,$AI$2)/10000 ),"") -> 45.595723 | AJ41: =IFERROR((SUMIFS(자금총괄!$K:$K,자금총괄!$B:$B,펀드현황!$C41,자금총괄!$F:$F,$AI$2)/10000),"") -> 45.595723 | AK41: =IFERROR((SUMIFS(자금총괄!$M:$M,자금총괄!$B:$B,펀드현황!$C41,자금총괄!$F:$F,$AI$2)/10000),"") -> 45.595723 | AL41: =IFERROR( ( SUMIFS(자금총괄!$O:$O, 자금총괄!$B:$B,펀드현황!$C41,자금총괄!$F:$F,$AI$2) /10000 ),"") -> 45.595723 | AM41: =IFERROR( ( SUMIFS(자금총괄!$Q:$Q, 자금총괄!$B:$B,펀드현황!$C41,자금총괄!$F:$F,$AI$2) /10000 ),"") -> 45.595723
C42: 3JM97 | D42: Dream Big 글로벌 자산배분형30 (일임) | E42: =AVERAGEIFS(#REF!,#REF!,펀드현황!$C42)/100000000 -> #REF! | F42: =IFERROR(VLOOKUP($T42,자금총괄!$B:$E,4,0)/100000000,"") -> 46.244318 | G42: =VLOOKUP($C42,'MOS4110'!$A:$BP,펀드현황!G$2,0) -> 44378 | H42: =VLOOKUP($C42,'MOS4110'!$A:$BP,펀드현황!H$2,0) -> 911.7 | I42: =VLOOKUP($C42,'MOS4110'!$A:$BP,펀드현황!I$2,0) -> 0.6058 | J42: =VLOOKUP($C42,'MOS4110'!$A:$BP,펀드현황!J$2,0) -> 3.6694 | K42: =VLOOKUP($C42,'MOS4110'!$A:$BP,펀드현황!K$2,0) -> 3.7744 | L42: =VLOOKUP($C42,'MOS4110'!$A:$BP,펀드현황!L$2,0) -> 3.123 | M42: =VLOOKUP($C42,'MOS4110'!$A:$BP,펀드현황!M$2,0) -> -5.0421 | N42: =VLOOKUP($C42,'MOS4110'!$A:$BP,펀드현황!N$2,0) -> 0 | ... Q42: =VLOOKUP($C42,'MOS4110'!$A:$BP,펀드현황!Q$2,0) -> 0.8365 | T42: =C42 -> 3JM97 | V42: =IFERROR( ( SUMIFS(설정해지!$G:$G, 설정해지!$B:$B,펀드현황!$C42,설정해지!$F:$F,"KRW")-SUMIFS(설정해지!$H:$H, 설정해지!$B:$B,펀드현황!$C42,설정해지!$F:$F,"KRW") ) /100000000,"") -> 0 | W42: =IFERROR( ( SUMIFS(설정해지!$I:$I, 설정해지!$B:$B,펀드현황!$C42,설정해지!$F:$F,"KRW")-SUMIFS(설정해지!$J:$J, 설정해지!$B:$B,펀드현황!$C42,설정해지!$F:$F,"KRW") ) /100000000,"") -> 0 | X42: =IFERROR( ( SUMIFS(설정해지!$K:$K, 설정해지!$B:$B,펀드현황!$C42,설정해지!$F:$F,"KRW")-SUMIFS(설정해지!$L:$L, 설정해지!$B:$B,펀드현황!$C42,설정해지!$F:$F,"KRW") ) /100000000,"") -> 0 | Z42: =IFERROR( ( SUMIFS(자금총괄!$G:$G, 자금총괄!$B:$B,펀드현황!$C42,자금총괄!$F:$F,$AB$2) ) /100000000,"") -> 0.92013232 | AA42: =Z42/F42 -> 0.019897197 | AB42: =IFERROR( ( SUMIFS(자금총괄!$I:$I, 자금총괄!$B:$B,펀드현황!$C42,자금총괄!$F:$F,$AB$2) ) /100000000,"") -> 0.92013232 | AC42: =IFERROR( ( SUMIFS(자금총괄!$K:$K, 자금총괄!$B:$B,펀드현황!$C42,자금총괄!$F:$F,$AB$2) ) /100000000,"") -> 0.90476395 | AD42: =IFERROR( ( SUMIFS(자금총괄!$M:$M, 자금총괄!$B:$B,펀드현황!$C42,자금총괄!$F:$F,$AB$2) ) /100000000,"") -> 0.90476395 | AE42: =IFERROR( ( SUMIFS(자금총괄!$O:$O, 자금총괄!$B:$B,펀드현황!$C42,자금총괄!$F:$F,$AB$2) ) /100000000,"") -> 0.90476395 | AF42: =IFERROR( ( SUMIFS(자금총괄!$Q:$Q, 자금총괄!$B:$B,펀드현황!$C42,자금총괄!$F:$F,$AB$2) ) /100000000,"") -> 0.90476395 | AH42: =IFERROR( ( SUMIFS(자금총괄!$G:$G, 자금총괄!$B:$B,펀드현황!$C42,자금총괄!$F:$F,$AI$2)/10000 ),"") -> 7.773534 | AI42: =IFERROR( ( SUMIFS(자금총괄!$I:$I, 자금총괄!$B:$B,펀드현황!$C42,자금총괄!$F:$F,$AI$2)/10000 ),"") -> 7.874556 | AJ42: =IFERROR((SUMIFS(자금총괄!$K:$K,자금총괄!$B:$B,펀드현황!$C42,자금총괄!$F:$F,$AI$2)/10000),"") -> 7.874556 | AK42: =IFERROR((SUMIFS(자금총괄!$M:$M,자금총괄!$B:$B,펀드현황!$C42,자금총괄!$F:$F,$AI$2)/10000),"") -> 7.874556 | AL42: =IFERROR( ( SUMIFS(자금총괄!$O:$O, 자금총괄!$B:$B,펀드현황!$C42,자금총괄!$F:$F,$AI$2) /10000 ),"") -> 7.874556 | AM42: =IFERROR( ( SUMIFS(자금총괄!$Q:$Q, 자금총괄!$B:$B,펀드현황!$C42,자금총괄!$F:$F,$AI$2) /10000 ),"") -> 7.874556
C43: 06K04 | D43: 한국투자퇴직연금자산배분전문투자형(사모) | E43: =AVERAGEIFS(#REF!,#REF!,펀드현황!$C43)/100000000 -> #REF! | F43: =IFERROR(VLOOKUP($T43,자금총괄!$B:$E,4,0)/100000000,"") -> 92.512591 | G43: =VLOOKUP($C43,'MOS4110'!$A:$BP,펀드현황!G$2,0) -> 43448 | H43: =VLOOKUP($C43,'MOS4110'!$A:$BP,펀드현황!H$2,0) -> 975.22 | I43: =VLOOKUP($C43,'MOS4110'!$A:$BP,펀드현황!I$2,0) -> 4.6576 | J43: =VLOOKUP($C43,'MOS4110'!$A:$BP,펀드현황!J$2,0) -> 8.9534 | K43: =VLOOKUP($C43,'MOS4110'!$A:$BP,펀드현황!K$2,0) -> 11.0754 | L43: =VLOOKUP($C43,'MOS4110'!$A:$BP,펀드현황!L$2,0) -> 17.5134 | M43: =VLOOKUP($C43,'MOS4110'!$A:$BP,펀드현황!M$2,0) -> 2.7467 | N43: =VLOOKUP($C43,'MOS4110'!$A:$BP,펀드현황!N$2,0) -> 3.3057 | ... Q43: =VLOOKUP($C43,'MOS4110'!$A:$BP,펀드현황!Q$2,0) -> -0.4156 | T43: =C43 -> 06K04 | V43: =IFERROR( ( SUMIFS(설정해지!$G:$G, 설정해지!$B:$B,펀드현황!$C43,설정해지!$F:$F,"KRW")-SUMIFS(설정해지!$H:$H, 설정해지!$B:$B,펀드현황!$C43,설정해지!$F:$F,"KRW") ) /100000000,"") -> 0 | W43: =IFERROR( ( SUMIFS(설정해지!$I:$I, 설정해지!$B:$B,펀드현황!$C43,설정해지!$F:$F,"KRW")-SUMIFS(설정해지!$J:$J, 설정해지!$B:$B,펀드현황!$C43,설정해지!$F:$F,"KRW") ) /100000000,"") -> 0 | X43: =IFERROR( ( SUMIFS(설정해지!$K:$K, 설정해지!$B:$B,펀드현황!$C43,설정해지!$F:$F,"KRW")-SUMIFS(설정해지!$L:$L, 설정해지!$B:$B,펀드현황!$C43,설정해지!$F:$F,"KRW") ) /100000000,"") -> 0 | Z43: =IFERROR( ( SUMIFS(자금총괄!$G:$G, 자금총괄!$B:$B,펀드현황!$C43,자금총괄!$F:$F,$AB$2) ) /100000000,"") -> 5.3640425 | AA43: =Z43/F43 -> 0.057981757 | AB43: =IFERROR( ( SUMIFS(자금총괄!$I:$I, 자금총괄!$B:$B,펀드현황!$C43,자금총괄!$F:$F,$AB$2) ) /100000000,"") -> 5.3640425 | AC43: =IFERROR( ( SUMIFS(자금총괄!$K:$K, 자금총괄!$B:$B,펀드현황!$C43,자금총괄!$F:$F,$AB$2) ) /100000000,"") -> 5.3640425 | AD43: =IFERROR( ( SUMIFS(자금총괄!$M:$M, 자금총괄!$B:$B,펀드현황!$C43,자금총괄!$F:$F,$AB$2) ) /100000000,"") -> 5.3640425 | AE43: =IFERROR( ( SUMIFS(자금총괄!$O:$O, 자금총괄!$B:$B,펀드현황!$C43,자금총괄!$F:$F,$AB$2) ) /100000000,"") -> 5.3640425 | AF43: =IFERROR( ( SUMIFS(자금총괄!$Q:$Q, 자금총괄!$B:$B,펀드현황!$C43,자금총괄!$F:$F,$AB$2) ) /100000000,"") -> 5.3640425 | AH43: =IFERROR( ( SUMIFS(자금총괄!$G:$G, 자금총괄!$B:$B,펀드현황!$C43,자금총괄!$F:$F,$AI$2)/10000 ),"") -> 12.720234 | AI43: =IFERROR( ( SUMIFS(자금총괄!$I:$I, 자금총괄!$B:$B,펀드현황!$C43,자금총괄!$F:$F,$AI$2)/10000 ),"") -> 13.299059 | AJ43: =IFERROR((SUMIFS(자금총괄!$K:$K,자금총괄!$B:$B,펀드현황!$C43,자금총괄!$F:$F,$AI$2)/10000),"") -> 13.299059 | AK43: =IFERROR((SUMIFS(자금총괄!$M:$M,자금총괄!$B:$B,펀드현황!$C43,자금총괄!$F:$F,$AI$2)/10000),"") -> 13.299059 | AL43: =IFERROR( ( SUMIFS(자금총괄!$O:$O, 자금총괄!$B:$B,펀드현황!$C43,자금총괄!$F:$F,$AI$2) /10000 ),"") -> 13.299059 | AM43: =IFERROR( ( SUMIFS(자금총괄!$Q:$Q, 자금총괄!$B:$B,펀드현황!$C43,자금총괄!$F:$F,$AI$2) /10000 ),"") -> 13.299059
C44: 3JM08 | D44: 한투 VUL S자산배분형30(채권) | E44: =AVERAGEIFS(#REF!,#REF!,펀드현황!$C44)/100000000 -> #REF! | F44: =IFERROR(VLOOKUP($T44,자금총괄!$B:$E,4,0)/100000000,"") -> 32.291043 | G44: =VLOOKUP($C44,'MOS4110'!$A:$BP,펀드현황!G$2,0) -> 43389 | H44: =VLOOKUP($C44,'MOS4110'!$A:$BP,펀드현황!H$2,0) -> 1120.95 | I44: =VLOOKUP($C44,'MOS4110'!$A:$BP,펀드현황!I$2,0) -> 1.2849 | J44: =VLOOKUP($C44,'MOS4110'!$A:$BP,펀드현황!J$2,0) -> 4.657 | K44: =VLOOKUP($C44,'MOS4110'!$A:$BP,펀드현황!K$2,0) -> 6.6383 | L44: =VLOOKUP($C44,'MOS4110'!$A:$BP,펀드현황!L$2,0) -> 7.6977 | M44: =VLOOKUP($C44,'MOS4110'!$A:$BP,펀드현황!M$2,0) -> 3.1157 | N44: =VLOOKUP($C44,'MOS4110'!$A:$BP,펀드현황!N$2,0) -> 1.4306 | ... Q44: =VLOOKUP($C44,'MOS4110'!$A:$BP,펀드현황!Q$2,0) -> -0.2293 | T44: =C44 -> 3JM08 | V44: =IFERROR( ( SUMIFS(설정해지!$G:$G, 설정해지!$B:$B,펀드현황!$C44,설정해지!$F:$F,"KRW")-SUMIFS(설정해지!$H:$H, 설정해지!$B:$B,펀드현황!$C44,설정해지!$F:$F,"KRW") ) /100000000,"") -> 0 | W44: =IFERROR( ( SUMIFS(설정해지!$I:$I, 설정해지!$B:$B,펀드현황!$C44,설정해지!$F:$F,"KRW")-SUMIFS(설정해지!$J:$J, 설정해지!$B:$B,펀드현황!$C44,설정해지!$F:$F,"KRW") ) /100000000,"") -> 0 | X44: =IFERROR( ( SUMIFS(설정해지!$K:$K, 설정해지!$B:$B,펀드현황!$C44,설정해지!$F:$F,"KRW")-SUMIFS(설정해지!$L:$L, 설정해지!$B:$B,펀드현황!$C44,설정해지!$F:$F,"KRW") ) /100000000,"") -> 0 | Z44: =IFERROR( ( SUMIFS(자금총괄!$G:$G, 자금총괄!$B:$B,펀드현황!$C44,자금총괄!$F:$F,$AB$2) ) /100000000,"") -> 0.06733565 | AA44: =Z44/F44 -> 0.0020852733 | AB44: =IFERROR( ( SUMIFS(자금총괄!$I:$I, 자금총괄!$B:$B,펀드현황!$C44,자금총괄!$F:$F,$AB$2) ) /100000000,"") -> 0.23956907 | AC44: =IFERROR( ( SUMIFS(자금총괄!$K:$K, 자금총괄!$B:$B,펀드현황!$C44,자금총괄!$F:$F,$AB$2) ) /100000000,"") -> 0.23956907 | AD44: =IFERROR( ( SUMIFS(자금총괄!$M:$M, 자금총괄!$B:$B,펀드현황!$C44,자금총괄!$F:$F,$AB$2) ) /100000000,"") -> 0.23956907 | AE44: =IFERROR( ( SUMIFS(자금총괄!$O:$O, 자금총괄!$B:$B,펀드현황!$C44,자금총괄!$F:$F,$AB$2) ) /100000000,"") -> 0.23956907 | AF44: =IFERROR( ( SUMIFS(자금총괄!$Q:$Q, 자금총괄!$B:$B,펀드현황!$C44,자금총괄!$F:$F,$AB$2) ) /100000000,"") -> 0.23956907 | AH44: =IFERROR( ( SUMIFS(자금총괄!$G:$G, 자금총괄!$B:$B,펀드현황!$C44,자금총괄!$F:$F,$AI$2)/10000 ),"") -> 2.299601 | AI44: =IFERROR( ( SUMIFS(자금총괄!$I:$I, 자금총괄!$B:$B,펀드현황!$C44,자금총괄!$F:$F,$AI$2)/10000 ),"") -> 1.199601 | AJ44: =IFERROR((SUMIFS(자금총괄!$K:$K,자금총괄!$B:$B,펀드현황!$C44,자금총괄!$F:$F,$AI$2)/10000),"") -> 1.199601 | AK44: =IFERROR((SUMIFS(자금총괄!$M:$M,자금총괄!$B:$B,펀드현황!$C44,자금총괄!$F:$F,$AI$2)/10000),"") -> 1.199601 | AL44: =IFERROR( ( SUMIFS(자금총괄!$O:$O, 자금총괄!$B:$B,펀드현황!$C44,자금총괄!$F:$F,$AI$2) /10000 ),"") -> 1.199601 | AM44: =IFERROR( ( SUMIFS(자금총괄!$Q:$Q, 자금총괄!$B:$B,펀드현황!$C44,자금총괄!$F:$F,$AI$2) /10000 ),"") -> 1.199601
C45: 3JM09 | D45: 한투 변액연금 S자산배분형30(채권) | E45: =AVERAGEIFS(#REF!,#REF!,펀드현황!$C45)/100000000 -> #REF! | F45: =IFERROR(VLOOKUP($T45,자금총괄!$B:$E,4,0)/100000000,"") -> 282.35272 | G45: =VLOOKUP($C45,'MOS4110'!$A:$BP,펀드현황!G$2,0) -> 43389 | H45: =VLOOKUP($C45,'MOS4110'!$A:$BP,펀드현황!H$2,0) -> 1096.48 | I45: =VLOOKUP($C45,'MOS4110'!$A:$BP,펀드현황!I$2,0) -> 1.2681 | J45: =VLOOKUP($C45,'MOS4110'!$A:$BP,펀드현황!J$2,0) -> 4.5471 | K45: =VLOOKUP($C45,'MOS4110'!$A:$BP,펀드현황!K$2,0) -> 6.4626 | L45: =VLOOKUP($C45,'MOS4110'!$A:$BP,펀드현황!L$2,0) -> 7.3454 | M45: =VLOOKUP($C45,'MOS4110'!$A:$BP,펀드현황!M$2,0) -> 2.1864 | N45: =VLOOKUP($C45,'MOS4110'!$A:$BP,펀드현황!N$2,0) -> 0.2239 | ... Q45: =VLOOKUP($C45,'MOS4110'!$A:$BP,펀드현황!Q$2,0) -> -0.3157 | T45: =C45 -> 3JM09 | V45: =IFERROR( ( SUMIFS(설정해지!$G:$G, 설정해지!$B:$B,펀드현황!$C45,설정해지!$F:$F,"KRW")-SUMIFS(설정해지!$H:$H, 설정해지!$B:$B,펀드현황!$C45,설정해지!$F:$F,"KRW") ) /100000000,"") -> 0 | W45: =IFERROR( ( SUMIFS(설정해지!$I:$I, 설정해지!$B:$B,펀드현황!$C45,설정해지!$F:$F,"KRW")-SUMIFS(설정해지!$J:$J, 설정해지!$B:$B,펀드현황!$C45,설정해지!$F:$F,"KRW") ) /100000000,"") -> 0 | X45: =IFERROR( ( SUMIFS(설정해지!$K:$K, 설정해지!$B:$B,펀드현황!$C45,설정해지!$F:$F,"KRW")-SUMIFS(설정해지!$L:$L, 설정해지!$B:$B,펀드현황!$C45,설정해지!$F:$F,"KRW") ) /100000000,"") -> 0 | Z45: =IFERROR( ( SUMIFS(자금총괄!$G:$G, 자금총괄!$B:$B,펀드현황!$C45,자금총괄!$F:$F,$AB$2) ) /100000000,"") -> 3.3823212 | AA45: =Z45/F45 -> 0.011979064 | AB45: =IFERROR( ( SUMIFS(자금총괄!$I:$I, 자금총괄!$B:$B,펀드현황!$C45,자금총괄!$F:$F,$AB$2) ) /100000000,"") -> 3.579795 | AC45: =IFERROR( ( SUMIFS(자금총괄!$K:$K, 자금총괄!$B:$B,펀드현황!$C45,자금총괄!$F:$F,$AB$2) ) /100000000,"") -> 3.579795 | AD45: =IFERROR( ( SUMIFS(자금총괄!$M:$M, 자금총괄!$B:$B,펀드현황!$C45,자금총괄!$F:$F,$AB$2) ) /100000000,"") -> 3.579795 | AE45: =IFERROR( ( SUMIFS(자금총괄!$O:$O, 자금총괄!$B:$B,펀드현황!$C45,자금총괄!$F:$F,$AB$2) ) /100000000,"") -> 3.579795 | AF45: =IFERROR( ( SUMIFS(자금총괄!$Q:$Q, 자금총괄!$B:$B,펀드현황!$C45,자금총괄!$F:$F,$AB$2) ) /100000000,"") -> 3.579795 | AH45: =IFERROR( ( SUMIFS(자금총괄!$G:$G, 자금총괄!$B:$B,펀드현황!$C45,자금총괄!$F:$F,$AI$2)/10000 ),"") -> 11.850287 | AI45: =IFERROR( ( SUMIFS(자금총괄!$I:$I, 자금총괄!$B:$B,펀드현황!$C45,자금총괄!$F:$F,$AI$2)/10000 ),"") -> 11.850287 | AJ45: =IFERROR((SUMIFS(자금총괄!$K:$K,자금총괄!$B:$B,펀드현황!$C45,자금총괄!$F:$F,$AI$2)/10000),"") -> 11.850287 | AK45: =IFERROR((SUMIFS(자금총괄!$M:$M,자금총괄!$B:$B,펀드현황!$C45,자금총괄!$F:$F,$AI$2)/10000),"") -> 11.850287 | AL45: =IFERROR( ( SUMIFS(자금총괄!$O:$O, 자금총괄!$B:$B,펀드현황!$C45,자금총괄!$F:$F,$AI$2) /10000 ),"") -> 11.850287 | AM45: =IFERROR( ( SUMIFS(자금총괄!$Q:$Q, 자금총괄!$B:$B,펀드현황!$C45,자금총괄!$F:$F,$AI$2) /10000 ),"") -> 11.850287
C46: 3JM10 | D46: 한투 VUL종신 new S자산배분형30(채권) | E46: =AVERAGEIFS(#REF!,#REF!,펀드현황!$C46)/100000000 -> #REF! | F46: =IFERROR(VLOOKUP($T46,자금총괄!$B:$E,4,0)/100000000,"") -> 208.42577 | G46: =VLOOKUP($C46,'MOS4110'!$A:$BP,펀드현황!G$2,0) -> 43389 | H46: =VLOOKUP($C46,'MOS4110'!$A:$BP,펀드현황!H$2,0) -> 1121.67 | I46: =VLOOKUP($C46,'MOS4110'!$A:$BP,펀드현황!I$2,0) -> 1.2996 | J46: =VLOOKUP($C46,'MOS4110'!$A:$BP,펀드현황!J$2,0) -> 4.649 | K46: =VLOOKUP($C46,'MOS4110'!$A:$BP,펀드현황!K$2,0) -> 6.6794 | L46: =VLOOKUP($C46,'MOS4110'!$A:$BP,펀드현황!L$2,0) -> 7.8042 | M46: =VLOOKUP($C46,'MOS4110'!$A:$BP,펀드현황!M$2,0) -> 3.0369 | N46: =VLOOKUP($C46,'MOS4110'!$A:$BP,펀드현황!N$2,0) -> 1.5123 | ... Q46: =VLOOKUP($C46,'MOS4110'!$A:$BP,펀드현황!Q$2,0) -> -0.2508 | T46: =C46 -> 3JM10 | V46: =IFERROR( ( SUMIFS(설정해지!$G:$G, 설정해지!$B:$B,펀드현황!$C46,설정해지!$F:$F,"KRW")-SUMIFS(설정해지!$H:$H, 설정해지!$B:$B,펀드현황!$C46,설정해지!$F:$F,"KRW") ) /100000000,"") -> 0 | W46: =IFERROR( ( SUMIFS(설정해지!$I:$I, 설정해지!$B:$B,펀드현황!$C46,설정해지!$F:$F,"KRW")-SUMIFS(설정해지!$J:$J, 설정해지!$B:$B,펀드현황!$C46,설정해지!$F:$F,"KRW") ) /100000000,"") -> 0 | X46: =IFERROR( ( SUMIFS(설정해지!$K:$K, 설정해지!$B:$B,펀드현황!$C46,설정해지!$F:$F,"KRW")-SUMIFS(설정해지!$L:$L, 설정해지!$B:$B,펀드현황!$C46,설정해지!$F:$F,"KRW") ) /100000000,"") -> 0 | Z46: =IFERROR( ( SUMIFS(자금총괄!$G:$G, 자금총괄!$B:$B,펀드현황!$C46,자금총괄!$F:$F,$AB$2) ) /100000000,"") -> 0.88297099 | AA46: =Z46/F46 -> 0.0042363811 | AB46: =IFERROR( ( SUMIFS(자금총괄!$I:$I, 자금총괄!$B:$B,펀드현황!$C46,자금총괄!$F:$F,$AB$2) ) /100000000,"") -> 1.7389479 | AC46: =IFERROR( ( SUMIFS(자금총괄!$K:$K, 자금총괄!$B:$B,펀드현황!$C46,자금총괄!$F:$F,$AB$2) ) /100000000,"") -> 1.7389479 | AD46: =IFERROR( ( SUMIFS(자금총괄!$M:$M, 자금총괄!$B:$B,펀드현황!$C46,자금총괄!$F:$F,$AB$2) ) /100000000,"") -> 1.7389479 | AE46: =IFERROR( ( SUMIFS(자금총괄!$O:$O, 자금총괄!$B:$B,펀드현황!$C46,자금총괄!$F:$F,$AB$2) ) /100000000,"") -> 1.7389479 | AF46: =IFERROR( ( SUMIFS(자금총괄!$Q:$Q, 자금총괄!$B:$B,펀드현황!$C46,자금총괄!$F:$F,$AB$2) ) /100000000,"") -> 1.7389479 | AH46: =IFERROR( ( SUMIFS(자금총괄!$G:$G, 자금총괄!$B:$B,펀드현황!$C46,자금총괄!$F:$F,$AI$2)/10000 ),"") -> 28.60513 | AI46: =IFERROR( ( SUMIFS(자금총괄!$I:$I, 자금총괄!$B:$B,펀드현황!$C46,자금총괄!$F:$F,$AI$2)/10000 ),"") -> 7.86106 | AJ46: =IFERROR((SUMIFS(자금총괄!$K:$K,자금총괄!$B:$B,펀드현황!$C46,자금총괄!$F:$F,$AI$2)/10000),"") -> 7.86106 | AK46: =IFERROR((SUMIFS(자금총괄!$M:$M,자금총괄!$B:$B,펀드현황!$C46,자금총괄!$F:$F,$AI$2)/10000),"") -> 7.86106 | AL46: =IFERROR( ( SUMIFS(자금총괄!$O:$O, 자금총괄!$B:$B,펀드현황!$C46,자금총괄!$F:$F,$AI$2) /10000 ),"") -> 7.86106 | AM46: =IFERROR( ( SUMIFS(자금총괄!$Q:$Q, 자금총괄!$B:$B,펀드현황!$C46,자금총괄!$F:$F,$AI$2) /10000 ),"") -> 7.86106
C47: 3JM11 | D47: 한투 빅보너스VA S자산배분형50(채권) | E47: =AVERAGEIFS(#REF!,#REF!,펀드현황!$C47)/100000000 -> #REF! | F47: =IFERROR(VLOOKUP($T47,자금총괄!$B:$E,4,0)/100000000,"") -> 841.66627 | G47: =VLOOKUP($C47,'MOS4110'!$A:$BP,펀드현황!G$2,0) -> 43460 | H47: =VLOOKUP($C47,'MOS4110'!$A:$BP,펀드현황!H$2,0) -> 1233.31 | I47: =VLOOKUP($C47,'MOS4110'!$A:$BP,펀드현황!I$2,0) -> 2.0445 | J47: =VLOOKUP($C47,'MOS4110'!$A:$BP,펀드현황!J$2,0) -> 5.8808 | K47: =VLOOKUP($C47,'MOS4110'!$A:$BP,펀드현황!K$2,0) -> 8.0514 | L47: =VLOOKUP($C47,'MOS4110'!$A:$BP,펀드현황!L$2,0) -> 10.1711 | M47: =VLOOKUP($C47,'MOS4110'!$A:$BP,펀드현황!M$2,0) -> 3.636 | N47: =VLOOKUP($C47,'MOS4110'!$A:$BP,펀드현황!N$2,0) -> 2.6655 | ... Q47: =VLOOKUP($C47,'MOS4110'!$A:$BP,펀드현황!Q$2,0) -> -0.487 | T47: =C47 -> 3JM11 | V47: =IFERROR( ( SUMIFS(설정해지!$G:$G, 설정해지!$B:$B,펀드현황!$C47,설정해지!$F:$F,"KRW")-SUMIFS(설정해지!$H:$H, 설정해지!$B:$B,펀드현황!$C47,설정해지!$F:$F,"KRW") ) /100000000,"") -> 0 | W47: =IFERROR( ( SUMIFS(설정해지!$I:$I, 설정해지!$B:$B,펀드현황!$C47,설정해지!$F:$F,"KRW")-SUMIFS(설정해지!$J:$J, 설정해지!$B:$B,펀드현황!$C47,설정해지!$F:$F,"KRW") ) /100000000,"") -> 0 | X47: =IFERROR( ( SUMIFS(설정해지!$K:$K, 설정해지!$B:$B,펀드현황!$C47,설정해지!$F:$F,"KRW")-SUMIFS(설정해지!$L:$L, 설정해지!$B:$B,펀드현황!$C47,설정해지!$F:$F,"KRW") ) /100000000,"") -> 0 | Z47: =IFERROR( ( SUMIFS(자금총괄!$G:$G, 자금총괄!$B:$B,펀드현황!$C47,자금총괄!$F:$F,$AB$2) ) /100000000,"") -> 0.29282294 | AA47: =Z47/F47 -> 0.00034790861 | AB47: =IFERROR( ( SUMIFS(자금총괄!$I:$I, 자금총괄!$B:$B,펀드현황!$C47,자금총괄!$F:$F,$AB$2) ) /100000000,"") -> 5.4598957 | AC47: =IFERROR( ( SUMIFS(자금총괄!$K:$K, 자금총괄!$B:$B,펀드현황!$C47,자금총괄!$F:$F,$AB$2) ) /100000000,"") -> 5.4598957 | AD47: =IFERROR( ( SUMIFS(자금총괄!$M:$M, 자금총괄!$B:$B,펀드현황!$C47,자금총괄!$F:$F,$AB$2) ) /100000000,"") -> 5.4598957 | AE47: =IFERROR( ( SUMIFS(자금총괄!$O:$O, 자금총괄!$B:$B,펀드현황!$C47,자금총괄!$F:$F,$AB$2) ) /100000000,"") -> 5.4598957 | AF47: =IFERROR( ( SUMIFS(자금총괄!$Q:$Q, 자금총괄!$B:$B,펀드현황!$C47,자금총괄!$F:$F,$AB$2) ) /100000000,"") -> 5.4598957 | AH47: =IFERROR( ( SUMIFS(자금총괄!$G:$G, 자금총괄!$B:$B,펀드현황!$C47,자금총괄!$F:$F,$AI$2)/10000 ),"") -> 64.934509 | AI47: =IFERROR( ( SUMIFS(자금총괄!$I:$I, 자금총괄!$B:$B,펀드현황!$C47,자금총괄!$F:$F,$AI$2)/10000 ),"") -> 34.934509 | AJ47: =IFERROR((SUMIFS(자금총괄!$K:$K,자금총괄!$B:$B,펀드현황!$C47,자금총괄!$F:$F,$AI$2)/10000),"") -> 34.934509 | AK47: =IFERROR((SUMIFS(자금총괄!$M:$M,자금총괄!$B:$B,펀드현황!$C47,자금총괄!$F:$F,$AI$2)/10000),"") -> 34.934509 | AL47: =IFERROR( ( SUMIFS(자금총괄!$O:$O, 자금총괄!$B:$B,펀드현황!$C47,자금총괄!$F:$F,$AI$2) /10000 ),"") -> 34.934509 | AM47: =IFERROR( ( SUMIFS(자금총괄!$Q:$Q, 자금총괄!$B:$B,펀드현황!$C47,자금총괄!$F:$F,$AI$2) /10000 ),"") -> 34.934509
C48: 3JM12 | D48: 한투 빅보너스VA S자산배분형30(채권) | E48: =AVERAGEIFS(#REF!,#REF!,펀드현황!$C48)/100000000 -> #REF! | F48: =IFERROR(VLOOKUP($T48,자금총괄!$B:$E,4,0)/100000000,"") -> 866.86005 | G48: =VLOOKUP($C48,'MOS4110'!$A:$BP,펀드현황!G$2,0) -> 43460 | H48: =VLOOKUP($C48,'MOS4110'!$A:$BP,펀드현황!H$2,0) -> 1142.65 | I48: =VLOOKUP($C48,'MOS4110'!$A:$BP,펀드현황!I$2,0) -> 1.3086 | J48: =VLOOKUP($C48,'MOS4110'!$A:$BP,펀드현황!J$2,0) -> 4.6795 | K48: =VLOOKUP($C48,'MOS4110'!$A:$BP,펀드현황!K$2,0) -> 6.7827 | L48: =VLOOKUP($C48,'MOS4110'!$A:$BP,펀드현황!L$2,0) -> 7.956 | M48: =VLOOKUP($C48,'MOS4110'!$A:$BP,펀드현황!M$2,0) -> 3.3231 | N48: =VLOOKUP($C48,'MOS4110'!$A:$BP,펀드현황!N$2,0) -> 1.9522 | ... Q48: =VLOOKUP($C48,'MOS4110'!$A:$BP,펀드현황!Q$2,0) -> -0.234 | T48: =C48 -> 3JM12 | V48: =IFERROR( ( SUMIFS(설정해지!$G:$G, 설정해지!$B:$B,펀드현황!$C48,설정해지!$F:$F,"KRW")-SUMIFS(설정해지!$H:$H, 설정해지!$B:$B,펀드현황!$C48,설정해지!$F:$F,"KRW") ) /100000000,"") -> 0 | W48: =IFERROR( ( SUMIFS(설정해지!$I:$I, 설정해지!$B:$B,펀드현황!$C48,설정해지!$F:$F,"KRW")-SUMIFS(설정해지!$J:$J, 설정해지!$B:$B,펀드현황!$C48,설정해지!$F:$F,"KRW") ) /100000000,"") -> 0 | X48: =IFERROR( ( SUMIFS(설정해지!$K:$K, 설정해지!$B:$B,펀드현황!$C48,설정해지!$F:$F,"KRW")-SUMIFS(설정해지!$L:$L, 설정해지!$B:$B,펀드현황!$C48,설정해지!$F:$F,"KRW") ) /100000000,"") -> 0 | Z48: =IFERROR( ( SUMIFS(자금총괄!$G:$G, 자금총괄!$B:$B,펀드현황!$C48,자금총괄!$F:$F,$AB$2) ) /100000000,"") -> 1.2625164 | AA48: =Z48/F48 -> 0.0014564248 | AB48: =IFERROR( ( SUMIFS(자금총괄!$I:$I, 자금총괄!$B:$B,펀드현황!$C48,자금총괄!$F:$F,$AB$2) ) /100000000,"") -> 6.6967344 | AC48: =IFERROR( ( SUMIFS(자금총괄!$K:$K, 자금총괄!$B:$B,펀드현황!$C48,자금총괄!$F:$F,$AB$2) ) /100000000,"") -> 6.6967344 | AD48: =IFERROR( ( SUMIFS(자금총괄!$M:$M, 자금총괄!$B:$B,펀드현황!$C48,자금총괄!$F:$F,$AB$2) ) /100000000,"") -> 6.6967344 | AE48: =IFERROR( ( SUMIFS(자금총괄!$O:$O, 자금총괄!$B:$B,펀드현황!$C48,자금총괄!$F:$F,$AB$2) ) /100000000,"") -> 6.6967344 | AF48: =IFERROR( ( SUMIFS(자금총괄!$Q:$Q, 자금총괄!$B:$B,펀드현황!$C48,자금총괄!$F:$F,$AB$2) ) /100000000,"") -> 6.6967344 | AH48: =IFERROR( ( SUMIFS(자금총괄!$G:$G, 자금총괄!$B:$B,펀드현황!$C48,자금총괄!$F:$F,$AI$2)/10000 ),"") -> 67.930309 | AI48: =IFERROR( ( SUMIFS(자금총괄!$I:$I, 자금총괄!$B:$B,펀드현황!$C48,자금총괄!$F:$F,$AI$2)/10000 ),"") -> 32.630309 | AJ48: =IFERROR((SUMIFS(자금총괄!$K:$K,자금총괄!$B:$B,펀드현황!$C48,자금총괄!$F:$F,$AI$2)/10000),"") -> 32.630309 | AK48: =IFERROR((SUMIFS(자금총괄!$M:$M,자금총괄!$B:$B,펀드현황!$C48,자금총괄!$F:$F,$AI$2)/10000),"") -> 32.630309 | AL48: =IFERROR( ( SUMIFS(자금총괄!$O:$O, 자금총괄!$B:$B,펀드현황!$C48,자금총괄!$F:$F,$AI$2) /10000 ),"") -> 32.630309 | AM48: =IFERROR( ( SUMIFS(자금총괄!$Q:$Q, 자금총괄!$B:$B,펀드현황!$C48,자금총괄!$F:$F,$AI$2) /10000 ),"") -> 32.630309
... C51: 4JM04 | D51: 한투 퇴직연금 S자산배분형70(멀티에셋) | E51: =AVERAGEIFS(#REF!,#REF!,펀드현황!$C51)/100000000 -> #REF! | F51: =IFERROR(VLOOKUP($T51,자금총괄!$B:$E,4,0)/100000000,"") -> 15.882787 | G51: =VLOOKUP($C51,'MOS4110'!$A:$BP,펀드현황!G$2,0) -> 44585 | H51: =VLOOKUP($C51,'MOS4110'!$A:$BP,펀드현황!H$2,0) -> 980.94 | I51: =VLOOKUP($C51,'MOS4110'!$A:$BP,펀드현황!I$2,0) -> 2.6152 | J51: =VLOOKUP($C51,'MOS4110'!$A:$BP,펀드현황!J$2,0) -> 6.8981 | K51: =VLOOKUP($C51,'MOS4110'!$A:$BP,펀드현황!K$2,0) -> 8.5855 | L51: =VLOOKUP($C51,'MOS4110'!$A:$BP,펀드현황!L$2,0) -> 10.9046 | M51: =VLOOKUP($C51,'MOS4110'!$A:$BP,펀드현황!M$2,0) -> 1.5855 | N51: =VLOOKUP($C51,'MOS4110'!$A:$BP,펀드현황!N$2,0) -> 0 | ... Q51: =VLOOKUP($C51,'MOS4110'!$A:$BP,펀드현황!Q$2,0) -> -0.9672 | T51: =C51 -> 4JM04 | V51: =IFERROR( ( SUMIFS(설정해지!$G:$G, 설정해지!$B:$B,펀드현황!$C51,설정해지!$F:$F,"KRW")-SUMIFS(설정해지!$H:$H, 설정해지!$B:$B,펀드현황!$C51,설정해지!$F:$F,"KRW") ) /100000000,"") -> 0 | W51: =IFERROR( ( SUMIFS(설정해지!$I:$I, 설정해지!$B:$B,펀드현황!$C51,설정해지!$F:$F,"KRW")-SUMIFS(설정해지!$J:$J, 설정해지!$B:$B,펀드현황!$C51,설정해지!$F:$F,"KRW") ) /100000000,"") -> 0 | X51: =IFERROR( ( SUMIFS(설정해지!$K:$K, 설정해지!$B:$B,펀드현황!$C51,설정해지!$F:$F,"KRW")-SUMIFS(설정해지!$L:$L, 설정해지!$B:$B,펀드현황!$C51,설정해지!$F:$F,"KRW") ) /100000000,"") -> 0 | Z51: =IFERROR( ( SUMIFS(자금총괄!$G:$G, 자금총괄!$B:$B,펀드현황!$C51,자금총괄!$F:$F,$AB$2) ) /100000000,"") -> 0.01525351 | AA51: =Z51/F51 -> 0.00096037994 | AB51: =IFERROR( ( SUMIFS(자금총괄!$I:$I, 자금총괄!$B:$B,펀드현황!$C51,자금총괄!$F:$F,$AB$2) ) /100000000,"") -> 0.04878556 | AC51: =IFERROR( ( SUMIFS(자금총괄!$K:$K, 자금총괄!$B:$B,펀드현황!$C51,자금총괄!$F:$F,$AB$2) ) /100000000,"") -> 0.04878556 | AD51: =IFERROR( ( SUMIFS(자금총괄!$M:$M, 자금총괄!$B:$B,펀드현황!$C51,자금총괄!$F:$F,$AB$2) ) /100000000,"") -> 0.04878556 | AE51: =IFERROR( ( SUMIFS(자금총괄!$O:$O, 자금총괄!$B:$B,펀드현황!$C51,자금총괄!$F:$F,$AB$2) ) /100000000,"") -> 0.04878556 | AF51: =IFERROR( ( SUMIFS(자금총괄!$Q:$Q, 자금총괄!$B:$B,펀드현황!$C51,자금총괄!$F:$F,$AB$2) ) /100000000,"") -> 0.04878556 | AH51: =IFERROR( ( SUMIFS(자금총괄!$G:$G, 자금총괄!$B:$B,펀드현황!$C51,자금총괄!$F:$F,$AI$2)/10000 ),"") -> 1.125583 | AI51: =IFERROR( ( SUMIFS(자금총괄!$I:$I, 자금총괄!$B:$B,펀드현황!$C51,자금총괄!$F:$F,$AI$2)/10000 ),"") -> 1.189037 | AJ51: =IFERROR((SUMIFS(자금총괄!$K:$K,자금총괄!$B:$B,펀드현황!$C51,자금총괄!$F:$F,$AI$2)/10000),"") -> 1.929661 | AK51: =IFERROR((SUMIFS(자금총괄!$M:$M,자금총괄!$B:$B,펀드현황!$C51,자금총괄!$F:$F,$AI$2)/10000),"") -> 1.929661 | AL51: =IFERROR( ( SUMIFS(자금총괄!$O:$O, 자금총괄!$B:$B,펀드현황!$C51,자금총괄!$F:$F,$AI$2) /10000 ),"") -> 1.929661 | AM51: =IFERROR( ( SUMIFS(자금총괄!$Q:$Q, 자금총괄!$B:$B,펀드현황!$C51,자금총괄!$F:$F,$AI$2) /10000 ),"") -> 1.929661
D52: 자산배분 합계 | E52: =SUM(E38:E51) -> #REF! | F52: =SUM(F38:F51) -> 4961.9
B54: 솔루션 | C54: 2JM14 | D54: 삼성생명 퇴직연금 변액 (일임) | E54: =AVERAGEIFS(#REF!,#REF!,펀드현황!$C54)/100000000 -> #REF! | F54: =IFERROR(VLOOKUP($T54,자금총괄!$B:$E,4,0)/100000000,"") -> 131.33401 | G54: =VLOOKUP($C54,'MOS4110'!$A:$BP,펀드현황!G$2,0) -> 42331 | H54: =VLOOKUP($C54,'MOS4110'!$A:$BP,펀드현황!H$2,0) -> 1408.38 | I54: =VLOOKUP($C54,'MOS4110'!$A:$BP,펀드현황!I$2,0) -> 5.8304 | J54: =VLOOKUP($C54,'MOS4110'!$A:$BP,펀드현황!J$2,0) -> 5.7207 | K54: =VLOOKUP($C54,'MOS4110'!$A:$BP,펀드현황!K$2,0) -> 5.6359 | L54: =VLOOKUP($C54,'MOS4110'!$A:$BP,펀드현황!L$2,0) -> 17.9459 | M54: =VLOOKUP($C54,'MOS4110'!$A:$BP,펀드현황!M$2,0) -> 6.4004 | N54: =VLOOKUP($C54,'MOS4110'!$A:$BP,펀드현황!N$2,0) -> -3.0622 | ... Q54: =VLOOKUP($C54,'MOS4110'!$A:$BP,펀드현황!Q$2,0) -> -0.27 | S54: 솔루션 | T54: =C54 -> 2JM14 | V54: =IFERROR( ( SUMIFS(설정해지!$G:$G, 설정해지!$B:$B,펀드현황!$C54,설정해지!$F:$F,"KRW")-SUMIFS(설정해지!$H:$H, 설정해지!$B:$B,펀드현황!$C54,설정해지!$F:$F,"KRW") ) /100000000,"") -> 0 | W54: =IFERROR( ( SUMIFS(설정해지!$I:$I, 설정해지!$B:$B,펀드현황!$C54,설정해지!$F:$F,"KRW")-SUMIFS(설정해지!$J:$J, 설정해지!$B:$B,펀드현황!$C54,설정해지!$F:$F,"KRW") ) /100000000,"") -> 0 | X54: =IFERROR( ( SUMIFS(설정해지!$K:$K, 설정해지!$B:$B,펀드현황!$C54,설정해지!$F:$F,"KRW")-SUMIFS(설정해지!$L:$L, 설정해지!$B:$B,펀드현황!$C54,설정해지!$F:$F,"KRW") ) /100000000,"") -> 0 | Z54: =IFERROR( ( SUMIFS(자금총괄!$G:$G, 자금총괄!$B:$B,펀드현황!$C54,자금총괄!$F:$F,$AB$2) ) /100000000,"") -> 6.4204084 | AA54: =Z54/F54 -> 0.048886105 | AB54: =IFERROR( ( SUMIFS(자금총괄!$I:$I, 자금총괄!$B:$B,펀드현황!$C54,자금총괄!$F:$F,$AB$2) ) /100000000,"") -> 12.114305 | AC54: =IFERROR( ( SUMIFS(자금총괄!$K:$K, 자금총괄!$B:$B,펀드현황!$C54,자금총괄!$F:$F,$AB$2) ) /100000000,"") -> 12.114305 | AD54: =IFERROR( ( SUMIFS(자금총괄!$M:$M, 자금총괄!$B:$B,펀드현황!$C54,자금총괄!$F:$F,$AB$2) ) /100000000,"") -> 12.114305 | AE54: =IFERROR( ( SUMIFS(자금총괄!$O:$O, 자금총괄!$B:$B,펀드현황!$C54,자금총괄!$F:$F,$AB$2) ) /100000000,"") -> 12.114305 | AF54: =IFERROR( ( SUMIFS(자금총괄!$Q:$Q, 자금총괄!$B:$B,펀드현황!$C54,자금총괄!$F:$F,$AB$2) ) /100000000,"") -> 12.114305 | AH54: =IFERROR( ( SUMIFS(자금총괄!$G:$G, 자금총괄!$B:$B,펀드현황!$C54,자금총괄!$F:$F,$AI$2)/10000 ),"") -> 0 | AI54: =IFERROR( ( SUMIFS(자금총괄!$I:$I, 자금총괄!$B:$B,펀드현황!$C54,자금총괄!$F:$F,$AI$2)/10000 ),"") -> 0 | AJ54: =IFERROR((SUMIFS(자금총괄!$K:$K,자금총괄!$B:$B,펀드현황!$C54,자금총괄!$F:$F,$AI$2)/10000),"") -> 0 | AK54: =IFERROR((SUMIFS(자금총괄!$M:$M,자금총괄!$B:$B,펀드현황!$C54,자금총괄!$F:$F,$AI$2)/10000),"") -> 0 | AL54: =IFERROR( ( SUMIFS(자금총괄!$O:$O, 자금총괄!$B:$B,펀드현황!$C54,자금총괄!$F:$F,$AI$2) /10000 ),"") -> 0 | AM54: =IFERROR( ( SUMIFS(자금총괄!$Q:$Q, 자금총괄!$B:$B,펀드현황!$C54,자금총괄!$F:$F,$AI$2) /10000 ),"") -> 0
C55: 05Q62 | D55: 코스피솔루션 펀드(채권혼합) | E55: =AVERAGEIFS(#REF!,#REF!,펀드현황!$C55)/100000000 -> #REF! | F55: =IFERROR(VLOOKUP($T55,자금총괄!$B:$E,4,0)/100000000,"") -> 47.948584 | G55: =VLOOKUP($C55,'MOS4110'!$A:$BP,펀드현황!G$2,0) -> 43332 | H55: =VLOOKUP($C55,'MOS4110'!$A:$BP,펀드현황!H$2,0) -> 1024.31 | I55: =VLOOKUP($C55,'MOS4110'!$A:$BP,펀드현황!I$2,0) -> 0.4334 | J55: =VLOOKUP($C55,'MOS4110'!$A:$BP,펀드현황!J$2,0) -> 1.0995 | K55: =VLOOKUP($C55,'MOS4110'!$A:$BP,펀드현황!K$2,0) -> 2.3655 | L55: =VLOOKUP($C55,'MOS4110'!$A:$BP,펀드현황!L$2,0) -> 3.6613 | M55: =VLOOKUP($C55,'MOS4110'!$A:$BP,펀드현황!M$2,0) -> 5.2931 | N55: =VLOOKUP($C55,'MOS4110'!$A:$BP,펀드현황!N$2,0) -> 3.104 | ... P55: =VLOOKUP($C55,'MOS4110'!$A:$BP,펀드현황!P$2,0) -> 9.324 | T55: =C55 -> 05Q62 | V55: =IFERROR( ( SUMIFS(설정해지!$G:$G, 설정해지!$B:$B,펀드현황!$C55,설정해지!$F:$F,"KRW")-SUMIFS(설정해지!$H:$H, 설정해지!$B:$B,펀드현황!$C55,설정해지!$F:$F,"KRW") ) /100000000,"") -> 0.01083986 | W55: =IFERROR( ( SUMIFS(설정해지!$I:$I, 설정해지!$B:$B,펀드현황!$C55,설정해지!$F:$F,"KRW")-SUMIFS(설정해지!$J:$J, 설정해지!$B:$B,펀드현황!$C55,설정해지!$F:$F,"KRW") ) /100000000,"") -> -0.0029737 | X55: =IFERROR( ( SUMIFS(설정해지!$K:$K, 설정해지!$B:$B,펀드현황!$C55,설정해지!$F:$F,"KRW")-SUMIFS(설정해지!$L:$L, 설정해지!$B:$B,펀드현황!$C55,설정해지!$F:$F,"KRW") ) /100000000,"") -> -0.02337805 | Z55: =IFERROR( ( SUMIFS(자금총괄!$G:$G, 자금총괄!$B:$B,펀드현황!$C55,자금총괄!$F:$F,$AB$2) ) /100000000,"") -> 2.968336 | AA55: =Z55/F55 -> 0.061906644 | AB55: =IFERROR( ( SUMIFS(자금총괄!$I:$I, 자금총괄!$B:$B,펀드현황!$C55,자금총괄!$F:$F,$AB$2) ) /100000000,"") -> 2.9653623 | AC55: =IFERROR( ( SUMIFS(자금총괄!$K:$K, 자금총괄!$B:$B,펀드현황!$C55,자금총괄!$F:$F,$AB$2) ) /100000000,"") -> 2.9419842 | AD55: =IFERROR( ( SUMIFS(자금총괄!$M:$M, 자금총괄!$B:$B,펀드현황!$C55,자금총괄!$F:$F,$AB$2) ) /100000000,"") -> 2.9419842 | AE55: =IFERROR( ( SUMIFS(자금총괄!$O:$O, 자금총괄!$B:$B,펀드현황!$C55,자금총괄!$F:$F,$AB$2) ) /100000000,"") -> 2.9419842 | AF55: =IFERROR( ( SUMIFS(자금총괄!$Q:$Q, 자금총괄!$B:$B,펀드현황!$C55,자금총괄!$F:$F,$AB$2) ) /100000000,"") -> 2.9419842 | AH55: =IFERROR( ( SUMIFS(자금총괄!$G:$G, 자금총괄!$B:$B,펀드현황!$C55,자금총괄!$F:$F,$AI$2)/10000 ),"") -> 0 | AI55: =IFERROR( ( SUMIFS(자금총괄!$I:$I, 자금총괄!$B:$B,펀드현황!$C55,자금총괄!$F:$F,$AI$2)/10000 ),"") -> 0 | AJ55: =IFERROR((SUMIFS(자금총괄!$K:$K,자금총괄!$B:$B,펀드현황!$C55,자금총괄!$F:$F,$AI$2)/10000),"") -> 0 | AK55: =IFERROR((SUMIFS(자금총괄!$M:$M,자금총괄!$B:$B,펀드현황!$C55,자금총괄!$F:$F,$AI$2)/10000),"") -> 0 | AL55: =IFERROR( ( SUMIFS(자금총괄!$O:$O, 자금총괄!$B:$B,펀드현황!$C55,자금총괄!$F:$F,$AI$2) /10000 ),"") -> 0 | AM55: =IFERROR( ( SUMIFS(자금총괄!$Q:$Q, 자금총괄!$B:$B,펀드현황!$C55,자금총괄!$F:$F,$AI$2) /10000 ),"") -> 0
C56: 06F77 | D56: ELS지수연계 솔루션 펀드 (해외파생) | E56: =AVERAGEIFS(#REF!,#REF!,펀드현황!$C56)/100000000 -> #REF! | F56: =IFERROR(VLOOKUP($T56,자금총괄!$B:$E,4,0)/100000000,"") -> 74.069077 | G56: =VLOOKUP($C56,'MOS4110'!$A:$BP,펀드현황!G$2,0) -> 41906 | H56: =VLOOKUP($C56,'MOS4110'!$A:$BP,펀드현황!H$2,0) -> 901.72 | I56: =VLOOKUP($C56,'MOS4110'!$A:$BP,펀드현황!I$2,0) -> 4.7306 | J56: =VLOOKUP($C56,'MOS4110'!$A:$BP,펀드현황!J$2,0) -> -2.7103 | K56: =VLOOKUP($C56,'MOS4110'!$A:$BP,펀드현황!K$2,0) -> -3.2001 | L56: =VLOOKUP($C56,'MOS4110'!$A:$BP,펀드현황!L$2,0) -> -7.7836 | M56: =VLOOKUP($C56,'MOS4110'!$A:$BP,펀드현황!M$2,0) -> -15.157 | N56: =VLOOKUP($C56,'MOS4110'!$A:$BP,펀드현황!N$2,0) -> -30.9286 | ... P56: =VLOOKUP($C56,'MOS4110'!$A:$BP,펀드현황!P$2,0) -> -8.3794 | T56: =C56 -> 06F77 | V56: =IFERROR( ( SUMIFS(설정해지!$G:$G, 설정해지!$B:$B,펀드현황!$C56,설정해지!$F:$F,"KRW")-SUMIFS(설정해지!$H:$H, 설정해지!$B:$B,펀드현황!$C56,설정해지!$F:$F,"KRW") ) /100000000,"") -> -0.01415509 | W56: =IFERROR( ( SUMIFS(설정해지!$I:$I, 설정해지!$B:$B,펀드현황!$C56,설정해지!$F:$F,"KRW")-SUMIFS(설정해지!$J:$J, 설정해지!$B:$B,펀드현황!$C56,설정해지!$F:$F,"KRW") ) /100000000,"") -> -4.9174297 | X56: =IFERROR( ( SUMIFS(설정해지!$K:$K, 설정해지!$B:$B,펀드현황!$C56,설정해지!$F:$F,"KRW")-SUMIFS(설정해지!$L:$L, 설정해지!$B:$B,펀드현황!$C56,설정해지!$F:$F,"KRW") ) /100000000,"") -> 0 | Z56: =IFERROR( ( SUMIFS(자금총괄!$G:$G, 자금총괄!$B:$B,펀드현황!$C56,자금총괄!$F:$F,$AB$2) ) /100000000,"") -> 10.632946 | AA56: =Z56/F56 -> 0.14355446 | AB56: =IFERROR( ( SUMIFS(자금총괄!$I:$I, 자금총괄!$B:$B,펀드현황!$C56,자금총괄!$F:$F,$AB$2) ) /100000000,"") -> 5.7155166 | AC56: =IFERROR( ( SUMIFS(자금총괄!$K:$K, 자금총괄!$B:$B,펀드현황!$C56,자금총괄!$F:$F,$AB$2) ) /100000000,"") -> 5.7155166 | AD56: =IFERROR( ( SUMIFS(자금총괄!$M:$M, 자금총괄!$B:$B,펀드현황!$C56,자금총괄!$F:$F,$AB$2) ) /100000000,"") -> 5.6720739 | AE56: =IFERROR( ( SUMIFS(자금총괄!$O:$O, 자금총괄!$B:$B,펀드현황!$C56,자금총괄!$F:$F,$AB$2) ) /100000000,"") -> 5.6720739 | AF56: =IFERROR( ( SUMIFS(자금총괄!$Q:$Q, 자금총괄!$B:$B,펀드현황!$C56,자금총괄!$F:$F,$AB$2) ) /100000000,"") -> 5.6720739 | AH56: =IFERROR( ( SUMIFS(자금총괄!$G:$G, 자금총괄!$B:$B,펀드현황!$C56,자금총괄!$F:$F,$AI$2)/10000 ),"") -> 0 | AI56: =IFERROR( ( SUMIFS(자금총괄!$I:$I, 자금총괄!$B:$B,펀드현황!$C56,자금총괄!$F:$F,$AI$2)/10000 ),"") -> 0 | AJ56: =IFERROR((SUMIFS(자금총괄!$K:$K,자금총괄!$B:$B,펀드현황!$C56,자금총괄!$F:$F,$AI$2)/10000),"") -> 0 | AK56: =IFERROR((SUMIFS(자금총괄!$M:$M,자금총괄!$B:$B,펀드현황!$C56,자금총괄!$F:$F,$AI$2)/10000),"") -> 0 | AL56: =IFERROR( ( SUMIFS(자금총괄!$O:$O, 자금총괄!$B:$B,펀드현황!$C56,자금총괄!$F:$F,$AI$2) /10000 ),"") -> 0 | AM56: =IFERROR( ( SUMIFS(자금총괄!$Q:$Q, 자금총괄!$B:$B,펀드현황!$C56,자금총괄!$F:$F,$AI$2) /10000 ),"") -> 0
C57: 2JM08 | D57: 처브라이프 변액보험 ELS솔루션 (일임) | E57: =AVERAGEIFS(#REF!,#REF!,펀드현황!$C57)/100000000 -> #REF! | F57: =IFERROR(VLOOKUP($T57,자금총괄!$B:$E,4,0)/100000000,"") -> 43.074363 | G57: =VLOOKUP($C57,'MOS4110'!$A:$BP,펀드현황!G$2,0) -> 42248 | H57: =VLOOKUP($C57,'MOS4110'!$A:$BP,펀드현황!H$2,0) -> 797.42 | I57: =VLOOKUP($C57,'MOS4110'!$A:$BP,펀드현황!I$2,0) -> 4.0665 | J57: =VLOOKUP($C57,'MOS4110'!$A:$BP,펀드현황!J$2,0) -> -3.5616 | K57: =VLOOKUP($C57,'MOS4110'!$A:$BP,펀드현황!K$2,0) -> -5.2214 | L57: =VLOOKUP($C57,'MOS4110'!$A:$BP,펀드현황!L$2,0) -> -12.0321 | M57: =VLOOKUP($C57,'MOS4110'!$A:$BP,펀드현황!M$2,0) -> -24.7987 | N57: =VLOOKUP($C57,'MOS4110'!$A:$BP,펀드현황!N$2,0) -> -36.7584 | ... P57: =VLOOKUP($C57,'MOS4110'!$A:$BP,펀드현황!P$2,0) -> -20.258 | T57: =C57 -> 2JM08 | V57: =IFERROR( ( SUMIFS(설정해지!$G:$G, 설정해지!$B:$B,펀드현황!$C57,설정해지!$F:$F,"KRW")-SUMIFS(설정해지!$H:$H, 설정해지!$B:$B,펀드현황!$C57,설정해지!$F:$F,"KRW") ) /100000000,"") -> 0 | W57: =IFERROR( ( SUMIFS(설정해지!$I:$I, 설정해지!$B:$B,펀드현황!$C57,설정해지!$F:$F,"KRW")-SUMIFS(설정해지!$J:$J, 설정해지!$B:$B,펀드현황!$C57,설정해지!$F:$F,"KRW") ) /100000000,"") -> 0 | X57: =IFERROR( ( SUMIFS(설정해지!$K:$K, 설정해지!$B:$B,펀드현황!$C57,설정해지!$F:$F,"KRW")-SUMIFS(설정해지!$L:$L, 설정해지!$B:$B,펀드현황!$C57,설정해지!$F:$F,"KRW") ) /100000000,"") -> 0 | Z57: =IFERROR( ( SUMIFS(자금총괄!$G:$G, 자금총괄!$B:$B,펀드현황!$C57,자금총괄!$F:$F,$AB$2) ) /100000000,"") -> 5.3851098 | AA57: =Z57/F57 -> 0.12501891 | AB57: =IFERROR( ( SUMIFS(자금총괄!$I:$I, 자금총괄!$B:$B,펀드현황!$C57,자금총괄!$F:$F,$AB$2) ) /100000000,"") -> 9.3851098 | AC57: =IFERROR( ( SUMIFS(자금총괄!$K:$K, 자금총괄!$B:$B,펀드현황!$C57,자금총괄!$F:$F,$AB$2) ) /100000000,"") -> 9.3851098 | AD57: =IFERROR( ( SUMIFS(자금총괄!$M:$M, 자금총괄!$B:$B,펀드현황!$C57,자금총괄!$F:$F,$AB$2) ) /100000000,"") -> 9.3851098 | AE57: =IFERROR( ( SUMIFS(자금총괄!$O:$O, 자금총괄!$B:$B,펀드현황!$C57,자금총괄!$F:$F,$AB$2) ) /100000000,"") -> 9.3851098 | AF57: =IFERROR( ( SUMIFS(자금총괄!$Q:$Q, 자금총괄!$B:$B,펀드현황!$C57,자금총괄!$F:$F,$AB$2) ) /100000000,"") -> 9.3851098 | AH57: =IFERROR( ( SUMIFS(자금총괄!$G:$G, 자금총괄!$B:$B,펀드현황!$C57,자금총괄!$F:$F,$AI$2)/10000 ),"") -> 0 | AI57: =IFERROR( ( SUMIFS(자금총괄!$I:$I, 자금총괄!$B:$B,펀드현황!$C57,자금총괄!$F:$F,$AI$2)/10000 ),"") -> 0 | AJ57: =IFERROR((SUMIFS(자금총괄!$K:$K,자금총괄!$B:$B,펀드현황!$C57,자금총괄!$F:$F,$AI$2)/10000),"") -> 0 | AK57: =IFERROR((SUMIFS(자금총괄!$M:$M,자금총괄!$B:$B,펀드현황!$C57,자금총괄!$F:$F,$AI$2)/10000),"") -> 0 | AL57: =IFERROR( ( SUMIFS(자금총괄!$O:$O, 자금총괄!$B:$B,펀드현황!$C57,자금총괄!$F:$F,$AI$2) /10000 ),"") -> 0 | AM57: =IFERROR( ( SUMIFS(자금총괄!$Q:$Q, 자금총괄!$B:$B,펀드현황!$C57,자금총괄!$F:$F,$AI$2) /10000 ),"") -> 0
C58: 2JM66 | D58: ABL생명 ELS 솔루션 (일임) | E58: =AVERAGEIFS(#REF!,#REF!,펀드현황!$C58)/100000000 -> #REF! | F58: =IFERROR(VLOOKUP($T58,자금총괄!$B:$E,4,0)/100000000,"") -> 9.0386383 | G58: =VLOOKUP($C58,'MOS4110'!$A:$BP,펀드현황!G$2,0) -> 43003 | H58: =VLOOKUP($C58,'MOS4110'!$A:$BP,펀드현황!H$2,0) -> 700.09 | I58: =VLOOKUP($C58,'MOS4110'!$A:$BP,펀드현황!I$2,0) -> 3.605 | J58: =VLOOKUP($C58,'MOS4110'!$A:$BP,펀드현황!J$2,0) -> -4.4572 | K58: =VLOOKUP($C58,'MOS4110'!$A:$BP,펀드현황!K$2,0) -> -5.6101 | L58: =VLOOKUP($C58,'MOS4110'!$A:$BP,펀드현황!L$2,0) -> -11.7129 | M58: =VLOOKUP($C58,'MOS4110'!$A:$BP,펀드현황!M$2,0) -> -22.5418 | N58: =VLOOKUP($C58,'MOS4110'!$A:$BP,펀드현황!N$2,0) -> -36.4237 | ... P58: =VLOOKUP($C58,'MOS4110'!$A:$BP,펀드현황!P$2,0) -> -29.991 | T58: =C58 -> 2JM66 | V58: =IFERROR( ( SUMIFS(설정해지!$G:$G, 설정해지!$B:$B,펀드현황!$C58,설정해지!$F:$F,"KRW")-SUMIFS(설정해지!$H:$H, 설정해지!$B:$B,펀드현황!$C58,설정해지!$F:$F,"KRW") ) /100000000,"") -> 0 | W58: =IFERROR( ( SUMIFS(설정해지!$I:$I, 설정해지!$B:$B,펀드현황!$C58,설정해지!$F:$F,"KRW")-SUMIFS(설정해지!$J:$J, 설정해지!$B:$B,펀드현황!$C58,설정해지!$F:$F,"KRW") ) /100000000,"") -> 0 | X58: =IFERROR( ( SUMIFS(설정해지!$K:$K, 설정해지!$B:$B,펀드현황!$C58,설정해지!$F:$F,"KRW")-SUMIFS(설정해지!$L:$L, 설정해지!$B:$B,펀드현황!$C58,설정해지!$F:$F,"KRW") ) /100000000,"") -> 0 | Z58: =IFERROR( ( SUMIFS(자금총괄!$G:$G, 자금총괄!$B:$B,펀드현황!$C58,자금총괄!$F:$F,$AB$2) ) /100000000,"") -> 2.1639496 | AA58: =Z58/F58 -> 0.23941102 | AB58: =IFERROR( ( SUMIFS(자금총괄!$I:$I, 자금총괄!$B:$B,펀드현황!$C58,자금총괄!$F:$F,$AB$2) ) /100000000,"") -> 2.1639496 | AC58: =IFERROR( ( SUMIFS(자금총괄!$K:$K, 자금총괄!$B:$B,펀드현황!$C58,자금총괄!$F:$F,$AB$2) ) /100000000,"") -> 2.1616818 | AD58: =IFERROR( ( SUMIFS(자금총괄!$M:$M, 자금총괄!$B:$B,펀드현황!$C58,자금총괄!$F:$F,$AB$2) ) /100000000,"") -> 2.1616818 | AE58: =IFERROR( ( SUMIFS(자금총괄!$O:$O, 자금총괄!$B:$B,펀드현황!$C58,자금총괄!$F:$F,$AB$2) ) /100000000,"") -> 2.1616818 | AF58: =IFERROR( ( SUMIFS(자금총괄!$Q:$Q, 자금총괄!$B:$B,펀드현황!$C58,자금총괄!$F:$F,$AB$2) ) /100000000,"") -> 2.1616818 | AH58: =IFERROR( ( SUMIFS(자금총괄!$G:$G, 자금총괄!$B:$B,펀드현황!$C58,자금총괄!$F:$F,$AI$2)/10000 ),"") -> 0 | AI58: =IFERROR( ( SUMIFS(자금총괄!$I:$I, 자금총괄!$B:$B,펀드현황!$C58,자금총괄!$F:$F,$AI$2)/10000 ),"") -> 0 | AJ58: =IFERROR((SUMIFS(자금총괄!$K:$K,자금총괄!$B:$B,펀드현황!$C58,자금총괄!$F:$F,$AI$2)/10000),"") -> 0 | AK58: =IFERROR((SUMIFS(자금총괄!$M:$M,자금총괄!$B:$B,펀드현황!$C58,자금총괄!$F:$F,$AI$2)/10000),"") -> 0 | AL58: =IFERROR( ( SUMIFS(자금총괄!$O:$O, 자금총괄!$B:$B,펀드현황!$C58,자금총괄!$F:$F,$AI$2) /10000 ),"") -> 0 | AM58: =IFERROR( ( SUMIFS(자금총괄!$Q:$Q, 자금총괄!$B:$B,펀드현황!$C58,자금총괄!$F:$F,$AI$2) /10000 ),"") -> 0
F59: =IFERROR(VLOOKUP($T59,자금총괄!$B:$E,4,0)/100000000,"") | T59: =C59 -> 0 | V59: =IFERROR( ( SUMIFS(설정해지!$G:$G, 설정해지!$B:$B,펀드현황!$C59,설정해지!$F:$F,"KRW")-SUMIFS(설정해지!$H:$H, 설정해지!$B:$B,펀드현황!$C59,설정해지!$F:$F,"KRW") ) /100000000,"") -> 0 | W59: =IFERROR( ( SUMIFS(설정해지!$I:$I, 설정해지!$B:$B,펀드현황!$C59,설정해지!$F:$F,"KRW")-SUMIFS(설정해지!$J:$J, 설정해지!$B:$B,펀드현황!$C59,설정해지!$F:$F,"KRW") ) /100000000,"") -> 0 | X59: =IFERROR( ( SUMIFS(설정해지!$K:$K, 설정해지!$B:$B,펀드현황!$C59,설정해지!$F:$F,"KRW")-SUMIFS(설정해지!$L:$L, 설정해지!$B:$B,펀드현황!$C59,설정해지!$F:$F,"KRW") ) /100000000,"") -> 0 | Z59: =IFERROR( ( SUMIFS(자금총괄!$G:$G, 자금총괄!$B:$B,펀드현황!$C59,자금총괄!$F:$F,$AB$2) ) /100000000,"") -> 0 | AA59: =Z59/F59 -> #VALUE! | AB59: =IFERROR( ( SUMIFS(자금총괄!$I:$I, 자금총괄!$B:$B,펀드현황!$C59,자금총괄!$F:$F,$AB$2) ) /100000000,"") -> 0 | AC59: =IFERROR( ( SUMIFS(자금총괄!$K:$K, 자금총괄!$B:$B,펀드현황!$C59,자금총괄!$F:$F,$AB$2) ) /100000000,"") -> 0 | AD59: =IFERROR( ( SUMIFS(자금총괄!$M:$M, 자금총괄!$B:$B,펀드현황!$C59,자금총괄!$F:$F,$AB$2) ) /100000000,"") -> 0 | AE59: =IFERROR( ( SUMIFS(자금총괄!$O:$O, 자금총괄!$B:$B,펀드현황!$C59,자금총괄!$F:$F,$AB$2) ) /100000000,"") -> 0 | AF59: =IFERROR( ( SUMIFS(자금총괄!$Q:$Q, 자금총괄!$B:$B,펀드현황!$C59,자금총괄!$F:$F,$AB$2) ) /100000000,"") -> 0 | AH59: =IFERROR( ( SUMIFS(자금총괄!$G:$G, 자금총괄!$B:$B,펀드현황!$C59,자금총괄!$F:$F,$AI$2)/10000 ),"") -> 0 | AI59: =IFERROR( ( SUMIFS(자금총괄!$I:$I, 자금총괄!$B:$B,펀드현황!$C59,자금총괄!$F:$F,$AI$2)/10000 ),"") -> 0 | AJ59: =IFERROR((SUMIFS(자금총괄!$K:$K,자금총괄!$B:$B,펀드현황!$C59,자금총괄!$F:$F,$AI$2)/10000),"") -> 0 | AK59: =IFERROR((SUMIFS(자금총괄!$M:$M,자금총괄!$B:$B,펀드현황!$C59,자금총괄!$F:$F,$AI$2)/10000),"") -> 0 | AL59: =IFERROR( ( SUMIFS(자금총괄!$O:$O, 자금총괄!$B:$B,펀드현황!$C59,자금총괄!$F:$F,$AI$2) /10000 ),"") -> 0 | AM59: =IFERROR( ( SUMIFS(자금총괄!$Q:$Q, 자금총괄!$B:$B,펀드현황!$C59,자금총괄!$F:$F,$AI$2) /10000 ),"") -> 0
D60: 솔루션 합계 | E60: =SUM(E54:E59) -> #REF! | F60: =SUM(F54:F59) -> 305.46467
U61: 설정액 | V61: T0 | W61: T1 | X61: T2
D62: 부서 전체 합계 | E62: =E12+E33+E52+E60 -> #REF! | F62: =F12+F33+F52+F60 -> 20578.474 | U62: 합계 | V62: =SUM(V14:V59) -> -13.117467 | W62: =SUM(W14:W59) -> 2.3178016 | X62: =SUM(X14:X59) -> -36.468557
U63: 포커스 | V63: =SUM(V3:V11) -> 5.5948959 | W63: =SUM(W3:W11) -> 3.5083978 | X63: =SUM(X3:X11) -> -0.89932916
U64: TRP | V64: =SUM(V14:V28) -> -13.345186 | W64: =SUM(W14:W28) -> 7.6721739 | X64: =SUM(X14:X28) -> -35.619231
U65: 자산배분 | V65: =SUM(V38:V51) -> -0.02882553 | W65: =SUM(W38:W51) -> -0.4439809 | X65: =SUM(X38:X51) -> -0.2364041
U66: 솔루션 | V66: =SUM(V54:V59) -> -0.00331523 | W66: =SUM(W54:W59) -> -4.9204034 | X66: =SUM(X54:X59) -> -0.02337805

Sheet 모니터링
AB1: 2JM57 | AC1: 3JM97
AA2: US_Growth | AB2: =SUMIF($Z$9:$Z$30,$AA2,AB$9:AB$30)/70% -> 0.22085714 | AC2: =SUMIF($Z$9:$Z$30,$AA2,AC$9:AC$30)/30% -> 0.19933333
AA3: US_Value | AB3: =SUMIF($Z$9:$Z$30,$AA3,AB$9:AB$30)/70% -> 0.10885714 | AC3: =SUMIF($Z$9:$Z$30,$AA3,AC$9:AC$30)/30% -> 0.097666667
E4: R | F4: =SUMIF($Q$42:$Q$57,$U$38,F9:F24) -> 0 | G4: =SUMIF($Q$42:$Q$57,$U$38,G9:G24) -> 0 | H4: =SUMIF($Q$42:$Q$57,$U$38,H9:H24) -> 0 | I4: =SUMIF($Q$42:$Q$57,$U$38,I9:I24) -> 0 | J4: =SUMIF($Q$42:$Q$57,$U$38,J9:J24) -> 0 | K4: =SUMIF($Q$42:$Q$57,$U$38,K9:K24) -> 0 | L4: =SUMIF($Q$42:$Q$57,$U$38,L9:L24) -> 0 | M4: =SUMIF($Q$42:$Q$57,$U$38,M9:M24) -> 0 | AA4: DM_ex US | AB4: =SUMIF($Z$9:$Z$30,$AA4,AB$9:AB$30)/70% -> 0.18671429 | AC4: =SUMIF($Z$9:$Z$30,$AA4,AC$9:AC$30)/30% -> 0.168
F5: TIF | G5: =#REF! -> #REF! | H5: =#REF! -> #REF! | I5: =#REF! -> #REF! | J5: =#REF! -> #REF! | K5: =#REF! -> #REF! | L5: =#REF! -> #REF! | M5: =#REF! -> #REF! | AA5: EM | AB5: =SUMIF($Z$9:$Z$30,$AA5,AB$9:AB$30)/70% -> 0.083857143 | AC5: =SUMIF($Z$9:$Z$30,$AA5,AC$9:AC$30)/30% -> 0.075666667
F6: 1 | G6: 2 | H6: 3 | I6: 4 | J6: 5 | K6: 6 | L6: 7 | M6: 8 | Q6: 234672 | R6: 244672 | S6: 252672 | T6: 264573 | U6: 264673 | V6: 272573 | W6: 264476 | X6: 127874
F7: TIF | G7: 2030 | H7: 2035 | I7: 2040 | J7: 2045 | K7: 2050 | L7: 2055 | M7: 2060
D8: TICKER | E8: 구분 | F8: 07M02 | G8: 07J66 | H8: 07J71 | I8: 07J76 | J8: 07J81 | K8: 07J86 | L8: 07J91 | M8: 07J96 | Q8: 3JM09 | R8: 3JM08 | S8: 3JM10 | T8: 3JM11 | U8: 3JM12 | V8: 3JM13 | W8: 4JM03 | X8: 4JM04 | AA8: 구분 | AB8: 2JM57 | AC8: 3JM97
C9: US_Growth | D9: VUG US Equity | E9: VANGUARD GROWTH ETF | F9: =IFERROR( AVERAGEIFS(통합명세부!$AJ:$AJ,통합명세부!$F:$F,F$8,통합명세부!$L:$L,$E9)/100,0) -> 0.0538 | G9: =IFERROR( AVERAGEIFS(통합명세부!$AJ:$AJ,통합명세부!$F:$F,G$8,통합명세부!$L:$L,$E9)/100,0) -> 0.0707 | H9: =IFERROR( AVERAGEIFS(통합명세부!$AJ:$AJ,통합명세부!$F:$F,H$8,통합명세부!$L:$L,$E9)/100,0) -> 0.0759 | I9: =IFERROR( AVERAGEIFS(통합명세부!$AJ:$AJ,통합명세부!$F:$F,I$8,통합명세부!$L:$L,$E9)/100,0) -> 0.0844 | J9: =IFERROR( AVERAGEIFS(통합명세부!$AJ:$AJ,통합명세부!$F:$F,J$8,통합명세부!$L:$L,$E9)/100,0) -> 0.0918 | K9: =IFERROR( AVERAGEIFS(통합명세부!$AJ:$AJ,통합명세부!$F:$F,K$8,통합명세부!$L:$L,$E9)/100,0) -> 0.0988 | L9: =IFERROR( AVERAGEIFS(통합명세부!$AJ:$AJ,통합명세부!$F:$F,L$8,통합명세부!$L:$L,$E9)/100,0) -> 0.1044 | M9: =IFERROR( AVERAGEIFS(통합명세부!$AJ:$AJ,통합명세부!$F:$F,M$8,통합명세부!$L:$L,$E9)/100,0) -> 0.109 | O9: EM | P9: KODEX 200 | Q9: =IFERROR( AVERAGEIFS(통합명세부!$AJ:$AJ,통합명세부!$F:$F,Q$8,통합명세부!$L:$L,$P9)/100,0) -> 0.0134 | R9: =IFERROR( AVERAGEIFS(통합명세부!$AJ:$AJ,통합명세부!$F:$F,R$8,통합명세부!$L:$L,$P9)/100,0) -> 0.0134 | S9: =IFERROR( AVERAGEIFS(통합명세부!$AJ:$AJ,통합명세부!$F:$F,S$8,통합명세부!$L:$L,$P9)/100,0) -> 0.0134 | T9: =IFERROR( AVERAGEIFS(통합명세부!$AJ:$AJ,통합명세부!$F:$F,T$8,통합명세부!$L:$L,$P9)/100,0) -> 0.023 | U9: =IFERROR( AVERAGEIFS(통합명세부!$AJ:$AJ,통합명세부!$F:$F,U$8,통합명세부!$L:$L,$P9)/100,0) -> 0.0134 | V9: =IFERROR( AVERAGEIFS(통합명세부!$AJ:$AJ,통합명세부!$F:$F,V$8,통합명세부!$L:$L,$P9)/100,0) -> 0.0229 | W9: =IFERROR( AVERAGEIFS(통합명세부!$AJ:$AJ,통합명세부!$F:$F,W$8,통합명세부!$L:$L,$P9)/100,0) -> 0.0324 | X9: =IFERROR( AVERAGEIFS(통합명세부!$AJ:$AJ,통합명세부!$F:$F,X$8,통합명세부!$L:$L,$P9)/100,0) -> 0.0324 | Z9: US_Growth | AA9: VANGUARD GROWTH ETF | AB9: =IFERROR( AVERAGEIFS(통합명세부!$AJ:$AJ,통합명세부!$F:$F,AB$8,통합명세부!$L:$L,$AA9)/100,0) -> 0.0775 | AC9: =IFERROR( AVERAGEIFS(통합명세부!$AJ:$AJ,통합명세부!$F:$F,AC$8,통합명세부!$L:$L,$AA9)/100,0) -> 0.0301
C10: US_Growth | D10: SPYG US Equity | E10: SPDR S&P 500 Growth | F10: =IFERROR( AVERAGEIFS(통합명세부!$AJ:$AJ,통합명세부!$F:$F,F$8,통합명세부!$L:$L,$E10)/100,0) -> 0.0538 | G10: =IFERROR( AVERAGEIFS(통합명세부!$AJ:$AJ,통합명세부!$F:$F,G$8,통합명세부!$L:$L,$E10)/100,0) -> 0.0707 | H10: =IFERROR( AVERAGEIFS(통합명세부!$AJ:$AJ,통합명세부!$F:$F,H$8,통합명세부!$L:$L,$E10)/100,0) -> 0.076 | I10: =IFERROR( AVERAGEIFS(통합명세부!$AJ:$AJ,통합명세부!$F:$F,I$8,통합명세부!$L:$L,$E10)/100,0) -> 0.0844 | J10: =IFERROR( AVERAGEIFS(통합명세부!$AJ:$AJ,통합명세부!$F:$F,J$8,통합명세부!$L:$L,$E10)/100,0) -> 0.0917 | K10: =IFERROR( AVERAGEIFS(통합명세부!$AJ:$AJ,통합명세부!$F:$F,K$8,통합명세부!$L:$L,$E10)/100,0) -> 0.0988 | L10: =IFERROR( AVERAGEIFS(통합명세부!$AJ:$AJ,통합명세부!$F:$F,L$8,통합명세부!$L:$L,$E10)/100,0) -> 0.1045 | M10: =IFERROR( AVERAGEIFS(통합명세부!$AJ:$AJ,통합명세부!$F:$F,M$8,통합명세부!$L:$L,$E10)/100,0) -> 0.109 | O10: US | P10: SPDR TRUST SERIES 1 | Q10: =IFERROR( AVERAGEIFS(통합명세부!$AJ:$AJ,통합명세부!$F:$F,Q$8,통합명세부!$L:$L,$P10)/100,0) -> 0.0295 | R10: =IFERROR( AVERAGEIFS(통합명세부!$AJ:$AJ,통합명세부!$F:$F,R$8,통합명세부!$L:$L,$P10)/100,0) -> 0.0294 | S10: =IFERROR( AVERAGEIFS(통합명세부!$AJ:$AJ,통합명세부!$F:$F,S$8,통합명세부!$L:$L,$P10)/100,0) -> 0.0293 | T10: =IFERROR( AVERAGEIFS(통합명세부!$AJ:$AJ,통합명세부!$F:$F,T$8,통합명세부!$L:$L,$P10)/100,0) -> 0.0497 | U10: =IFERROR( AVERAGEIFS(통합명세부!$AJ:$AJ,통합명세부!$F:$F,U$8,통합명세부!$L:$L,$P10)/100,0) -> 0.0295 | V10: =IFERROR( AVERAGEIFS(통합명세부!$AJ:$AJ,통합명세부!$F:$F,V$8,통합명세부!$L:$L,$P10)/100,0) -> 0.0495 | W10: =IFERROR( AVERAGEIFS(통합명세부!$AJ:$AJ,통합명세부!$F:$F,W$8,통합명세부!$L:$L,$P10)/100,0) -> 0.0699 | X10: =IFERROR( AVERAGEIFS(통합명세부!$AJ:$AJ,통합명세부!$F:$F,X$8,통합명세부!$L:$L,$P10)/100,0) -> 0.0691 | Z10: US_Growth | AA10: ISHARES EDGE MSCI USA QUALIT | AB10: =IFERROR( AVERAGEIFS(통합명세부!$AJ:$AJ,통합명세부!$F:$F,AB$8,통합명세부!$L:$L,$AA10)/100,0) -> 0.0771 | AC10: =IFERROR( AVERAGEIFS(통합명세부!$AJ:$AJ,통합명세부!$F:$F,AC$8,통합명세부!$L:$L,$AA10)/100,0) -> 0.0297
C11: US_Growth | D11: IWF US Equity | E11: ISHARES RUSSELL 1000 GROWTH | F11: =IFERROR( AVERAGEIFS(통합명세부!$AJ:$AJ,통합명세부!$F:$F,F$8,통합명세부!$L:$L,$E11)/100,0) -> 0.0537 | G11: =IFERROR( AVERAGEIFS(통합명세부!$AJ:$AJ,통합명세부!$F:$F,G$8,통합명세부!$L:$L,$E11)/100,0) -> 0.0707 | H11: =IFERROR( AVERAGEIFS(통합명세부!$AJ:$AJ,통합명세부!$F:$F,H$8,통합명세부!$L:$L,$E11)/100,0) -> 0.0759 | I11: =IFERROR( AVERAGEIFS(통합명세부!$AJ:$AJ,통합명세부!$F:$F,I$8,통합명세부!$L:$L,$E11)/100,0) -> 0.0843 | J11: =IFERROR( AVERAGEIFS(통합명세부!$AJ:$AJ,통합명세부!$F:$F,J$8,통합명세부!$L:$L,$E11)/100,0) -> 0.0917 | K11: =IFERROR( AVERAGEIFS(통합명세부!$AJ:$AJ,통합명세부!$F:$F,K$8,통합명세부!$L:$L,$E11)/100,0) -> 0.0987 | L11: =IFERROR( AVERAGEIFS(통합명세부!$AJ:$AJ,통합명세부!$F:$F,L$8,통합명세부!$L:$L,$E11)/100,0) -> 0.1044 | M11: =IFERROR( AVERAGEIFS(통합명세부!$AJ:$AJ,통합명세부!$F:$F,M$8,통합명세부!$L:$L,$E11)/100,0) -> 0.1089 | O11: US | P11: Global X N S&P 500 COVE CALL ETF | Q11: =IFERROR( AVERAGEIFS(통합명세부!$AJ:$AJ,통합명세부!$F:$F,Q$8,통합명세부!$L:$L,$P11)/100,0) -> 0 | R11: =IFERROR( AVERAGEIFS(통합명세부!$AJ:$AJ,통합명세부!$F:$F,R$8,통합명세부!$L:$L,$P11)/100,0) -> 0 | S11: =IFERROR( AVERAGEIFS(통합명세부!$AJ:$AJ,통합명세부!$F:$F,S$8,통합명세부!$L:$L,$P11)/100,0) -> 0 | T11: =IFERROR( AVERAGEIFS(통합명세부!$AJ:$AJ,통합명세부!$F:$F,T$8,통합명세부!$L:$L,$P11)/100,0) -> 0 | U11: =IFERROR( AVERAGEIFS(통합명세부!$AJ:$AJ,통합명세부!$F:$F,U$8,통합명세부!$L:$L,$P11)/100,0) -> 0 | V11: =IFERROR( AVERAGEIFS(통합명세부!$AJ:$AJ,통합명세부!$F:$F,V$8,통합명세부!$L:$L,$P11)/100,0) -> 0 | W11: =IFERROR( AVERAGEIFS(통합명세부!$AJ:$AJ,통합명세부!$F:$F,W$8,통합명세부!$L:$L,$P11)/100,0) -> 0 | X11: =IFERROR( AVERAGEIFS(통합명세부!$AJ:$AJ,통합명세부!$F:$F,X$8,통합명세부!$L:$L,$P11)/100,0) -> 0 | AA11: iShares Core International Agg | AB11: =IFERROR( AVERAGEIFS(통합명세부!$AJ:$AJ,통합명세부!$F:$F,AB$8,통합명세부!$L:$L,$AA11)/100,0) -> 0.0789 | AC11: =IFERROR( AVERAGEIFS(통합명세부!$AJ:$AJ,통합명세부!$F:$F,AC$8,통합명세부!$L:$L,$AA11)/100,0) -> 0.203
C12: US_Value | D12: VTV US Equity | E12: VANGUARD VALUE ETF | F12: =IFERROR( AVERAGEIFS(통합명세부!$AJ:$AJ,통합명세부!$F:$F,F$8,통합명세부!$L:$L,$E12)/100,0) -> 0.0377 | G12: =IFERROR( AVERAGEIFS(통합명세부!$AJ:$AJ,통합명세부!$F:$F,G$8,통합명세부!$L:$L,$E12)/100,0) -> 0.0498 | H12: =IFERROR( AVERAGEIFS(통합명세부!$AJ:$AJ,통합명세부!$F:$F,H$8,통합명세부!$L:$L,$E12)/100,0) -> 0.0535 | I12: =IFERROR( AVERAGEIFS(통합명세부!$AJ:$AJ,통합명세부!$F:$F,I$8,통합명세부!$L:$L,$E12)/100,0) -> 0.0595 | J12: =IFERROR( AVERAGEIFS(통합명세부!$AJ:$AJ,통합명세부!$F:$F,J$8,통합명세부!$L:$L,$E12)/100,0) -> 0.0645 | K12: =IFERROR( AVERAGEIFS(통합명세부!$AJ:$AJ,통합명세부!$F:$F,K$8,통합명세부!$L:$L,$E12)/100,0) -> 0.0695 | L12: =IFERROR( AVERAGEIFS(통합명세부!$AJ:$AJ,통합명세부!$F:$F,L$8,통합명세부!$L:$L,$E12)/100,0) -> 0.0736 | M12: =IFERROR( AVERAGEIFS(통합명세부!$AJ:$AJ,통합명세부!$F:$F,M$8,통합명세부!$L:$L,$E12)/100,0) -> 0.0767 | P12: ISHARES MSCI ACWI ETF | Q12: =IFERROR( AVERAGEIFS(통합명세부!$AJ:$AJ,통합명세부!$F:$F,Q$8,통합명세부!$L:$L,$P12)/100,0) -> 0 | R12: =IFERROR( AVERAGEIFS(통합명세부!$AJ:$AJ,통합명세부!$F:$F,R$8,통합명세부!$L:$L,$P12)/100,0) -> 0 | S12: =IFERROR( AVERAGEIFS(통합명세부!$AJ:$AJ,통합명세부!$F:$F,S$8,통합명세부!$L:$L,$P12)/100,0) -> 0 | T12: =IFERROR( AVERAGEIFS(통합명세부!$AJ:$AJ,통합명세부!$F:$F,T$8,통합명세부!$L:$L,$P12)/100,0) -> 0 | U12: =IFERROR( AVERAGEIFS(통합명세부!$AJ:$AJ,통합명세부!$F:$F,U$8,통합명세부!$L:$L,$P12)/100,0) -> 0 | V12: =IFERROR( AVERAGEIFS(통합명세부!$AJ:$AJ,통합명세부!$F:$F,V$8,통합명세부!$L:$L,$P12)/100,0) -> 0 | W12: =IFERROR( AVERAGEIFS(통합명세부!$AJ:$AJ,통합명세부!$F:$F,W$8,통합명세부!$L:$L,$P12)/100,0) -> 0 | X12: =IFERROR( AVERAGEIFS(통합명세부!$AJ:$AJ,통합명세부!$F:$F,X$8,통합명세부!$L:$L,$P12)/100,0) -> 0 | AA12: iShares Core U.S. Aggregate Bo | AB12: =IFERROR( AVERAGEIFS(통합명세부!$AJ:$AJ,통합명세부!$F:$F,AB$8,통합명세부!$L:$L,$AA12)/100,0) -> 0.0775 | AC12: =IFERROR( AVERAGEIFS(통합명세부!$AJ:$AJ,통합명세부!$F:$F,AC$8,통합명세부!$L:$L,$AA12)/100,0) -> 0
C13: US_Value | D13: SPYV US Equity | E13: SPDR S&P 500 VALUE ETF | F13: =IFERROR( AVERAGEIFS(통합명세부!$AJ:$AJ,통합명세부!$F:$F,F$8,통합명세부!$L:$L,$E13)/100,0) -> 0.0377 | G13: =IFERROR( AVERAGEIFS(통합명세부!$AJ:$AJ,통합명세부!$F:$F,G$8,통합명세부!$L:$L,$E13)/100,0) -> 0.0498 | H13: =IFERROR( AVERAGEIFS(통합명세부!$AJ:$AJ,통합명세부!$F:$F,H$8,통합명세부!$L:$L,$E13)/100,0) -> 0.0534 | I13: =IFERROR( AVERAGEIFS(통합명세부!$AJ:$AJ,통합명세부!$F:$F,I$8,통합명세부!$L:$L,$E13)/100,0) -> 0.0594 | J13: =IFERROR( AVERAGEIFS(통합명세부!$AJ:$AJ,통합명세부!$F:$F,J$8,통합명세부!$L:$L,$E13)/100,0) -> 0.0645 | K13: =IFERROR( AVERAGEIFS(통합명세부!$AJ:$AJ,통합명세부!$F:$F,K$8,통합명세부!$L:$L,$E13)/100,0) -> 0.0695 | L13: =IFERROR( AVERAGEIFS(통합명세부!$AJ:$AJ,통합명세부!$F:$F,L$8,통합명세부!$L:$L,$E13)/100,0) -> 0.0735 | M13: =IFERROR( AVERAGEIFS(통합명세부!$AJ:$AJ,통합명세부!$F:$F,M$8,통합명세부!$L:$L,$E13)/100,0) -> 0.0766 | P13: VANGUARD FTSE PACIFIC ETF | Q13: =IFERROR( AVERAGEIFS(통합명세부!$AJ:$AJ,통합명세부!$F:$F,Q$8,통합명세부!$L:$L,$P13)/100,0) -> 0 | R13: =IFERROR( AVERAGEIFS(통합명세부!$AJ:$AJ,통합명세부!$F:$F,R$8,통합명세부!$L:$L,$P13)/100,0) -> 0 | S13: =IFERROR( AVERAGEIFS(통합명세부!$AJ:$AJ,통합명세부!$F:$F,S$8,통합명세부!$L:$L,$P13)/100,0) -> 0 | T13: =IFERROR( AVERAGEIFS(통합명세부!$AJ:$AJ,통합명세부!$F:$F,T$8,통합명세부!$L:$L,$P13)/100,0) -> 0 | U13: =IFERROR( AVERAGEIFS(통합명세부!$AJ:$AJ,통합명세부!$F:$F,U$8,통합명세부!$L:$L,$P13)/100,0) -> 0 | V13: =IFERROR( AVERAGEIFS(통합명세부!$AJ:$AJ,통합명세부!$F:$F,V$8,통합명세부!$L:$L,$P13)/100,0) -> 0 | W13: =IFERROR( AVERAGEIFS(통합명세부!$AJ:$AJ,통합명세부!$F:$F,W$8,통합명세부!$L:$L,$P13)/100,0) -> 0 | X13: =IFERROR( AVERAGEIFS(통합명세부!$AJ:$AJ,통합명세부!$F:$F,X$8,통합명세부!$L:$L,$P13)/100,0) -> 0 | Z13: DM_ex US | AA13: Vanguard FTSE Europe ETF | AB13: =IFERROR( AVERAGEIFS(통합명세부!$AJ:$AJ,통합명세부!$F:$F,AB$8,통합명세부!$L:$L,$AA13)/100,0) -> 0.0624 | AC13: =IFERROR( AVERAGEIFS(통합명세부!$AJ:$AJ,통합명세부!$F:$F,AC$8,통합명세부!$L:$L,$AA13)/100,0) -> 0.0241
C14: US_Value | D14: IWD US Equity | E14: ISHARES RUSSELL 1000 VALUE E | F14: =IFERROR( AVERAGEIFS(통합명세부!$AJ:$AJ,통합명세부!$F:$F,F$8,통합명세부!$L:$L,$E14)/100,0) -> 0.0377 | G14: =IFERROR( AVERAGEIFS(통합명세부!$AJ:$AJ,통합명세부!$F:$F,G$8,통합명세부!$L:$L,$E14)/100,0) -> 0.0498 | H14: =IFERROR( AVERAGEIFS(통합명세부!$AJ:$AJ,통합명세부!$F:$F,H$8,통합명세부!$L:$L,$E14)/100,0) -> 0.0535 | I14: =IFERROR( AVERAGEIFS(통합명세부!$AJ:$AJ,통합명세부!$F:$F,I$8,통합명세부!$L:$L,$E14)/100,0) -> 0.0594 | J14: =IFERROR( AVERAGEIFS(통합명세부!$AJ:$AJ,통합명세부!$F:$F,J$8,통합명세부!$L:$L,$E14)/100,0) -> 0.0646 | K14: =IFERROR( AVERAGEIFS(통합명세부!$AJ:$AJ,통합명세부!$F:$F,K$8,통합명세부!$L:$L,$E14)/100,0) -> 0.0695 | L14: =IFERROR( AVERAGEIFS(통합명세부!$AJ:$AJ,통합명세부!$F:$F,L$8,통합명세부!$L:$L,$E14)/100,0) -> 0.0736 | M14: =IFERROR( AVERAGEIFS(통합명세부!$AJ:$AJ,통합명세부!$F:$F,M$8,통합명세부!$L:$L,$E14)/100,0) -> 0.0766 | P14: VANGUARD GROWTH ETF | Q14: =IFERROR( AVERAGEIFS(통합명세부!$AJ:$AJ,통합명세부!$F:$F,Q$8,통합명세부!$L:$L,$P14)/100,0) -> 0.0722 | R14: =IFERROR( AVERAGEIFS(통합명세부!$AJ:$AJ,통합명세부!$F:$F,R$8,통합명세부!$L:$L,$P14)/100,0) -> 0.0722 | S14: =IFERROR( AVERAGEIFS(통합명세부!$AJ:$AJ,통합명세부!$F:$F,S$8,통합명세부!$L:$L,$P14)/100,0) -> 0.0722 | T14: =IFERROR( AVERAGEIFS(통합명세부!$AJ:$AJ,통합명세부!$F:$F,T$8,통합명세부!$L:$L,$P14)/100,0) -> 0.1236 | U14: =IFERROR( AVERAGEIFS(통합명세부!$AJ:$AJ,통합명세부!$F:$F,U$8,통합명세부!$L:$L,$P14)/100,0) -> 0.0722 | V14: =IFERROR( AVERAGEIFS(통합명세부!$AJ:$AJ,통합명세부!$F:$F,V$8,통합명세부!$L:$L,$P14)/100,0) -> 0.1236 | W14: =IFERROR( AVERAGEIFS(통합명세부!$AJ:$AJ,통합명세부!$F:$F,W$8,통합명세부!$L:$L,$P14)/100,0) -> 0.1737 | X14: =IFERROR( AVERAGEIFS(통합명세부!$AJ:$AJ,통합명세부!$F:$F,X$8,통합명세부!$L:$L,$P14)/100,0) -> 0.1737 | Z14: EM | AA14: ISHARES MSCI EMERGING MKT IN | AB14: =IFERROR( AVERAGEIFS(통합명세부!$AJ:$AJ,통합명세부!$F:$F,AB$8,통합명세부!$L:$L,$AA14)/100,0) -> 0.0587 | AC14: =IFERROR( AVERAGEIFS(통합명세부!$AJ:$AJ,통합명세부!$F:$F,AC$8,통합명세부!$L:$L,$AA14)/100,0) -> 0.0227
C15: DM_ex US | D15: VEA US Equity | E15: VANGUARD FTSE DEVELOPED ETF | F15: =IFERROR( AVERAGEIFS(통합명세부!$AJ:$AJ,통합명세부!$F:$F,F$8,통합명세부!$L:$L,$E15)/100,0) -> 0.0473 | G15: =IFERROR( AVERAGEIFS(통합명세부!$AJ:$AJ,통합명세부!$F:$F,G$8,통합명세부!$L:$L,$E15)/100,0) -> 0.0614 | H15: =IFERROR( AVERAGEIFS(통합명세부!$AJ:$AJ,통합명세부!$F:$F,H$8,통합명세부!$L:$L,$E15)/100,0) -> 0.0658 | I15: =IFERROR( AVERAGEIFS(통합명세부!$AJ:$AJ,통합명세부!$F:$F,I$8,통합명세부!$L:$L,$E15)/100,0) -> 0.073 | J15: =IFERROR( AVERAGEIFS(통합명세부!$AJ:$AJ,통합명세부!$F:$F,J$8,통합명세부!$L:$L,$E15)/100,0) -> 0.0796 | K15: =IFERROR( AVERAGEIFS(통합명세부!$AJ:$AJ,통합명세부!$F:$F,K$8,통합명세부!$L:$L,$E15)/100,0) -> 0.0856 | L15: =IFERROR( AVERAGEIFS(통합명세부!$AJ:$AJ,통합명세부!$F:$F,L$8,통합명세부!$L:$L,$E15)/100,0) -> 0.0906 | M15: =IFERROR( AVERAGEIFS(통합명세부!$AJ:$AJ,통합명세부!$F:$F,M$8,통합명세부!$L:$L,$E15)/100,0) -> 0.0944 | P15: Invesco QQQ Trust Series 1 | Q15: =IFERROR( AVERAGEIFS(통합명세부!$AJ:$AJ,통합명세부!$F:$F,Q$8,통합명세부!$L:$L,$P15)/100,0) -> 0.0231 | R15: =IFERROR( AVERAGEIFS(통합명세부!$AJ:$AJ,통합명세부!$F:$F,R$8,통합명세부!$L:$L,$P15)/100,0) -> 0.0233 | S15: =IFERROR( AVERAGEIFS(통합명세부!$AJ:$AJ,통합명세부!$F:$F,S$8,통합명세부!$L:$L,$P15)/100,0) -> 0.0232 | T15: =IFERROR( AVERAGEIFS(통합명세부!$AJ:$AJ,통합명세부!$F:$F,T$8,통합명세부!$L:$L,$P15)/100,0) -> 0.0394 | U15: =IFERROR( AVERAGEIFS(통합명세부!$AJ:$AJ,통합명세부!$F:$F,U$8,통합명세부!$L:$L,$P15)/100,0) -> 0.0234 | V15: =IFERROR( AVERAGEIFS(통합명세부!$AJ:$AJ,통합명세부!$F:$F,V$8,통합명세부!$L:$L,$P15)/100,0) -> 0.0392 | W15: =IFERROR( AVERAGEIFS(통합명세부!$AJ:$AJ,통합명세부!$F:$F,W$8,통합명세부!$L:$L,$P15)/100,0) -> 0.0556 | X15: =IFERROR( AVERAGEIFS(통합명세부!$AJ:$AJ,통합명세부!$F:$F,X$8,통합명세부!$L:$L,$P15)/100,0) -> 0.0547 | Z15: Global | AA15: ISHARES MSCI ACWI ETF | AB15: =IFERROR( AVERAGEIFS(통합명세부!$AJ:$AJ,통합명세부!$F:$F,AB$8,통합명세부!$L:$L,$AA15)/100,0) -> 0.0619 | AC15: =IFERROR( AVERAGEIFS(통합명세부!$AJ:$AJ,통합명세부!$F:$F,AC$8,통합명세부!$L:$L,$AA15)/100,0) -> 0.0238
C16: EM | D16: VWO US Equity | E16: VANGUARD FTSE EMERGING MARKETS | F16: =IFERROR( AVERAGEIFS(통합명세부!$AJ:$AJ,통합명세부!$F:$F,F$8,통합명세부!$L:$L,$E16)/100,0) -> 0.016 | G16: =IFERROR( AVERAGEIFS(통합명세부!$AJ:$AJ,통합명세부!$F:$F,G$8,통합명세부!$L:$L,$E16)/100,0) -> 0.021 | H16: =IFERROR( AVERAGEIFS(통합명세부!$AJ:$AJ,통합명세부!$F:$F,H$8,통합명세부!$L:$L,$E16)/100,0) -> 0.0227 | I16: =IFERROR( AVERAGEIFS(통합명세부!$AJ:$AJ,통합명세부!$F:$F,I$8,통합명세부!$L:$L,$E16)/100,0) -> 0.0252 | J16: =IFERROR( AVERAGEIFS(통합명세부!$AJ:$AJ,통합명세부!$F:$F,J$8,통합명세부!$L:$L,$E16)/100,0) -> 0.0274 | K16: =IFERROR( AVERAGEIFS(통합명세부!$AJ:$AJ,통합명세부!$F:$F,K$8,통합명세부!$L:$L,$E16)/100,0) -> 0.0296 | L16: =IFERROR( AVERAGEIFS(통합명세부!$AJ:$AJ,통합명세부!$F:$F,L$8,통합명세부!$L:$L,$E16)/100,0) -> 0.0314 | M16: =IFERROR( AVERAGEIFS(통합명세부!$AJ:$AJ,통합명세부!$F:$F,M$8,통합명세부!$L:$L,$E16)/100,0) -> 0.0327 | P16: ISHARES PHLX SOX SEMICONDUCT | Q16: =IFERROR( AVERAGEIFS(통합명세부!$AJ:$AJ,통합명세부!$F:$F,Q$8,통합명세부!$L:$L,$P16)/100,0) -> 0.0113 | R16: =IFERROR( AVERAGEIFS(통합명세부!$AJ:$AJ,통합명세부!$F:$F,R$8,통합명세부!$L:$L,$P16)/100,0) -> 0.0112 | S16: =IFERROR( AVERAGEIFS(통합명세부!$AJ:$AJ,통합명세부!$F:$F,S$8,통합명세부!$L:$L,$P16)/100,0) -> 0.0113 | T16: =IFERROR( AVERAGEIFS(통합명세부!$AJ:$AJ,통합명세부!$F:$F,T$8,통합명세부!$L:$L,$P16)/100,0) -> 0.0204 | U16: =IFERROR( AVERAGEIFS(통합명세부!$AJ:$AJ,통합명세부!$F:$F,U$8,통합명세부!$L:$L,$P16)/100,0) -> 0.011 | V16: =IFERROR( AVERAGEIFS(통합명세부!$AJ:$AJ,통합명세부!$F:$F,V$8,통합명세부!$L:$L,$P16)/100,0) -> 0.0204 | W16: =IFERROR( AVERAGEIFS(통합명세부!$AJ:$AJ,통합명세부!$F:$F,W$8,통합명세부!$L:$L,$P16)/100,0) -> 0.0285 | X16: =IFERROR( AVERAGEIFS(통합명세부!$AJ:$AJ,통합명세부!$F:$F,X$8,통합명세부!$L:$L,$P16)/100,0) -> 0.0287 | Z16: US_Value | AA16: VANGUARD MEGA CAP VALUE ETF | AB16: =IFERROR( AVERAGEIFS(통합명세부!$AJ:$AJ,통합명세부!$F:$F,AB$8,통합명세부!$L:$L,$AA16)/100,0) -> 0.0762 | AC16: =IFERROR( AVERAGEIFS(통합명세부!$AJ:$AJ,통합명세부!$F:$F,AC$8,통합명세부!$L:$L,$AA16)/100,0) -> 0.0293
C17: EM | D17: SCHE US Equity | E17: Schwab Emerging Markets Equity ETF | F17: =IFERROR( AVERAGEIFS(통합명세부!$AJ:$AJ,통합명세부!$F:$F,F$8,통합명세부!$L:$L,$E17)/100,0) -> 0.016 | G17: =IFERROR( AVERAGEIFS(통합명세부!$AJ:$AJ,통합명세부!$F:$F,G$8,통합명세부!$L:$L,$E17)/100,0) -> 0.021 | H17: =IFERROR( AVERAGEIFS(통합명세부!$AJ:$AJ,통합명세부!$F:$F,H$8,통합명세부!$L:$L,$E17)/100,0) -> 0.0227 | I17: =IFERROR( AVERAGEIFS(통합명세부!$AJ:$AJ,통합명세부!$F:$F,I$8,통합명세부!$L:$L,$E17)/100,0) -> 0.0253 | J17: =IFERROR( AVERAGEIFS(통합명세부!$AJ:$AJ,통합명세부!$F:$F,J$8,통합명세부!$L:$L,$E17)/100,0) -> 0.0275 | K17: =IFERROR( AVERAGEIFS(통합명세부!$AJ:$AJ,통합명세부!$F:$F,K$8,통합명세부!$L:$L,$E17)/100,0) -> 0.0295 | L17: =IFERROR( AVERAGEIFS(통합명세부!$AJ:$AJ,통합명세부!$F:$F,L$8,통합명세부!$L:$L,$E17)/100,0) -> 0.0314 | M17: =IFERROR( AVERAGEIFS(통합명세부!$AJ:$AJ,통합명세부!$F:$F,M$8,통합명세부!$L:$L,$E17)/100,0) -> 0.0327 | P17: iShares MSCI China ETF | Q17: =IFERROR( AVERAGEIFS(통합명세부!$AJ:$AJ,통합명세부!$F:$F,Q$8,통합명세부!$L:$L,$P17)/100,0) -> 0 | R17: =IFERROR( AVERAGEIFS(통합명세부!$AJ:$AJ,통합명세부!$F:$F,R$8,통합명세부!$L:$L,$P17)/100,0) -> 0 | S17: =IFERROR( AVERAGEIFS(통합명세부!$AJ:$AJ,통합명세부!$F:$F,S$8,통합명세부!$L:$L,$P17)/100,0) -> 0 | T17: =IFERROR( AVERAGEIFS(통합명세부!$AJ:$AJ,통합명세부!$F:$F,T$8,통합명세부!$L:$L,$P17)/100,0) -> 0 | U17: =IFERROR( AVERAGEIFS(통합명세부!$AJ:$AJ,통합명세부!$F:$F,U$8,통합명세부!$L:$L,$P17)/100,0) -> 0 | V17: =IFERROR( AVERAGEIFS(통합명세부!$AJ:$AJ,통합명세부!$F:$F,V$8,통합명세부!$L:$L,$P17)/100,0) -> 0 | W17: =IFERROR( AVERAGEIFS(통합명세부!$AJ:$AJ,통합명세부!$F:$F,W$8,통합명세부!$L:$L,$P17)/100,0) -> 0 | X17: =IFERROR( AVERAGEIFS(통합명세부!$AJ:$AJ,통합명세부!$F:$F,X$8,통합명세부!$L:$L,$P17)/100,0) -> 0 | Z17: US | AA17: VANGUARD S&P 500 ETF | AB17: =IFERROR( AVERAGEIFS(통합명세부!$AJ:$AJ,통합명세부!$F:$F,AB$8,통합명세부!$L:$L,$AA17)/100,0) -> 0 | AC17: =IFERROR( AVERAGEIFS(통합명세부!$AJ:$AJ,통합명세부!$F:$F,AC$8,통합명세부!$L:$L,$AA17)/100,0) -> 0
P18: Consumer Discretionary Select Sector SPDR | Q18: =IFERROR( AVERAGEIFS(통합명세부!$AJ:$AJ,통합명세부!$F:$F,Q$8,통합명세부!$L:$L,$P18)/100,0) -> 0 | R18: =IFERROR( AVERAGEIFS(통합명세부!$AJ:$AJ,통합명세부!$F:$F,R$8,통합명세부!$L:$L,$P18)/100,0) -> 0 | S18: =IFERROR( AVERAGEIFS(통합명세부!$AJ:$AJ,통합명세부!$F:$F,S$8,통합명세부!$L:$L,$P18)/100,0) -> 0 | T18: =IFERROR( AVERAGEIFS(통합명세부!$AJ:$AJ,통합명세부!$F:$F,T$8,통합명세부!$L:$L,$P18)/100,0) -> 0 | U18: =IFERROR( AVERAGEIFS(통합명세부!$AJ:$AJ,통합명세부!$F:$F,U$8,통합명세부!$L:$L,$P18)/100,0) -> 0 | V18: =IFERROR( AVERAGEIFS(통합명세부!$AJ:$AJ,통합명세부!$F:$F,V$8,통합명세부!$L:$L,$P18)/100,0) -> 0 | W18: =IFERROR( AVERAGEIFS(통합명세부!$AJ:$AJ,통합명세부!$F:$F,W$8,통합명세부!$L:$L,$P18)/100,0) -> 0 | X18: =IFERROR( AVERAGEIFS(통합명세부!$AJ:$AJ,통합명세부!$F:$F,X$8,통합명세부!$L:$L,$P18)/100,0) -> 0 | AA18: VANGUARD LONG-TERM CORP BOND | AB18: =IFERROR( AVERAGEIFS(통합명세부!$AJ:$AJ,통합명세부!$F:$F,AB$8,통합명세부!$L:$L,$AA18)/100,0) -> 0.0128 | AC18: =IFERROR( AVERAGEIFS(통합명세부!$AJ:$AJ,통합명세부!$F:$F,AC$8,통합명세부!$L:$L,$AA18)/100,0) -> 0.0334
C19: Bond_KR_Short | D19: 190620 KS Equity | E19: ACE 단기통안채 | F19: =IFERROR( AVERAGEIFS(통합명세부!$AJ:$AJ,통합명세부!$F:$F,F$8,통합명세부!$L:$L,$E19)/100,0) -> 0 | G19: =IFERROR( AVERAGEIFS(통합명세부!$AJ:$AJ,통합명세부!$F:$F,G$8,통합명세부!$L:$L,$E19)/100,0) -> 0 | H19: =IFERROR( AVERAGEIFS(통합명세부!$AJ:$AJ,통합명세부!$F:$F,H$8,통합명세부!$L:$L,$E19)/100,0) -> 0 | I19: =IFERROR( AVERAGEIFS(통합명세부!$AJ:$AJ,통합명세부!$F:$F,I$8,통합명세부!$L:$L,$E19)/100,0) -> 0 | J19: =IFERROR( AVERAGEIFS(통합명세부!$AJ:$AJ,통합명세부!$F:$F,J$8,통합명세부!$L:$L,$E19)/100,0) -> 0 | K19: =IFERROR( AVERAGEIFS(통합명세부!$AJ:$AJ,통합명세부!$F:$F,K$8,통합명세부!$L:$L,$E19)/100,0) -> 0 | L19: =IFERROR( AVERAGEIFS(통합명세부!$AJ:$AJ,통합명세부!$F:$F,L$8,통합명세부!$L:$L,$E19)/100,0) -> 0 | M19: =IFERROR( AVERAGEIFS(통합명세부!$AJ:$AJ,통합명세부!$F:$F,M$8,통합명세부!$L:$L,$E19)/100,0) -> 0 | P19: Global X U.S. Infrasturucture Devolopment ETF | Q19: =IFERROR( AVERAGEIFS(통합명세부!$AJ:$AJ,통합명세부!$F:$F,Q$8,통합명세부!$L:$L,$P19)/100,0) -> 0.0112 | R19: =IFERROR( AVERAGEIFS(통합명세부!$AJ:$AJ,통합명세부!$F:$F,R$8,통합명세부!$L:$L,$P19)/100,0) -> 0.0112 | S19: =IFERROR( AVERAGEIFS(통합명세부!$AJ:$AJ,통합명세부!$F:$F,S$8,통합명세부!$L:$L,$P19)/100,0) -> 0.0112 | T19: =IFERROR( AVERAGEIFS(통합명세부!$AJ:$AJ,통합명세부!$F:$F,T$8,통합명세부!$L:$L,$P19)/100,0) -> 0.0203 | U19: =IFERROR( AVERAGEIFS(통합명세부!$AJ:$AJ,통합명세부!$F:$F,U$8,통합명세부!$L:$L,$P19)/100,0) -> 0.0112 | V19: =IFERROR( AVERAGEIFS(통합명세부!$AJ:$AJ,통합명세부!$F:$F,V$8,통합명세부!$L:$L,$P19)/100,0) -> 0.0203 | W19: =IFERROR( AVERAGEIFS(통합명세부!$AJ:$AJ,통합명세부!$F:$F,W$8,통합명세부!$L:$L,$P19)/100,0) -> 0.0284 | X19: =IFERROR( AVERAGEIFS(통합명세부!$AJ:$AJ,통합명세부!$F:$F,X$8,통합명세부!$L:$L,$P19)/100,0) -> 0.0283 | Z19: DM_ex US | AA19: ISHARES MSCI JAPAN ETF | AB19: =IFERROR( AVERAGEIFS(통합명세부!$AJ:$AJ,통합명세부!$F:$F,AB$8,통합명세부!$L:$L,$AA19)/100,0) -> 0.0346 | AC19: =IFERROR( AVERAGEIFS(통합명세부!$AJ:$AJ,통합명세부!$F:$F,AC$8,통합명세부!$L:$L,$AA19)/100,0) -> 0.0134
C20: Bond_KR_Mid | D20: 385540 KS Equity | E20: KBSTAR 종합채권(A-이상)액티브 | F20: =IFERROR( AVERAGEIFS(통합명세부!$AJ:$AJ,통합명세부!$F:$F,F$8,통합명세부!$L:$L,$E20)/100,0) -> 0.1826 | G20: =IFERROR( AVERAGEIFS(통합명세부!$AJ:$AJ,통합명세부!$F:$F,G$8,통합명세부!$L:$L,$E20)/100,0) -> 0.0825 | H20: =IFERROR( AVERAGEIFS(통합명세부!$AJ:$AJ,통합명세부!$F:$F,H$8,통합명세부!$L:$L,$E20)/100,0) -> 0.0248 | I20: =IFERROR( AVERAGEIFS(통합명세부!$AJ:$AJ,통합명세부!$F:$F,I$8,통합명세부!$L:$L,$E20)/100,0) -> 0 | J20: =IFERROR( AVERAGEIFS(통합명세부!$AJ:$AJ,통합명세부!$F:$F,J$8,통합명세부!$L:$L,$E20)/100,0) -> 0 | K20: =IFERROR( AVERAGEIFS(통합명세부!$AJ:$AJ,통합명세부!$F:$F,K$8,통합명세부!$L:$L,$E20)/100,0) -> 0 | L20: =IFERROR( AVERAGEIFS(통합명세부!$AJ:$AJ,통합명세부!$F:$F,L$8,통합명세부!$L:$L,$E20)/100,0) -> 0 | M20: =IFERROR( AVERAGEIFS(통합명세부!$AJ:$AJ,통합명세부!$F:$F,M$8,통합명세부!$L:$L,$E20)/100,0) -> 0 | P20: VANGUARD LONG-TERM CORP BOND | Q20: =IFERROR( AVERAGEIFS(통합명세부!$AJ:$AJ,통합명세부!$F:$F,Q$8,통합명세부!$L:$L,$P20)/100,0) -> 0 | R20: =IFERROR( AVERAGEIFS(통합명세부!$AJ:$AJ,통합명세부!$F:$F,R$8,통합명세부!$L:$L,$P20)/100,0) -> 0 | S20: =IFERROR( AVERAGEIFS(통합명세부!$AJ:$AJ,통합명세부!$F:$F,S$8,통합명세부!$L:$L,$P20)/100,0) -> 0 | T20: =IFERROR( AVERAGEIFS(통합명세부!$AJ:$AJ,통합명세부!$F:$F,T$8,통합명세부!$L:$L,$P20)/100,0) -> 0 | U20: =IFERROR( AVERAGEIFS(통합명세부!$AJ:$AJ,통합명세부!$F:$F,U$8,통합명세부!$L:$L,$P20)/100,0) -> 0 | V20: =IFERROR( AVERAGEIFS(통합명세부!$AJ:$AJ,통합명세부!$F:$F,V$8,통합명세부!$L:$L,$P20)/100,0) -> 0 | W20: =IFERROR( AVERAGEIFS(통합명세부!$AJ:$AJ,통합명세부!$F:$F,W$8,통합명세부!$L:$L,$P20)/100,0) -> 0 | X20: =IFERROR( AVERAGEIFS(통합명세부!$AJ:$AJ,통합명세부!$F:$F,X$8,통합명세부!$L:$L,$P20)/100,0) -> 0 | AA20: TECHNOLOGY SELECT SECT SPDR | AB20: =IFERROR( AVERAGEIFS(통합명세부!$AJ:$AJ,통합명세부!$F:$F,AB$8,통합명세부!$L:$L,$AA20)/100,0) -> 0.0263 | AC20: =IFERROR( AVERAGEIFS(통합명세부!$AJ:$AJ,통합명세부!$F:$F,AC$8,통합명세부!$L:$L,$AA20)/100,0) -> 0.0101
C21: Bond_KR_Mid | D21: 272910 KS Equity | E21: ACE 중장기국공채액티브 | F21: =IFERROR( AVERAGEIFS(통합명세부!$AJ:$AJ,통합명세부!$F:$F,F$8,통합명세부!$L:$L,$E21)/100,0) -> 0.0277 | G21: =IFERROR( AVERAGEIFS(통합명세부!$AJ:$AJ,통합명세부!$F:$F,G$8,통합명세부!$L:$L,$E21)/100,0) -> 0 | H21: =IFERROR( AVERAGEIFS(통합명세부!$AJ:$AJ,통합명세부!$F:$F,H$8,통합명세부!$L:$L,$E21)/100,0) -> 0 | I21: =IFERROR( AVERAGEIFS(통합명세부!$AJ:$AJ,통합명세부!$F:$F,I$8,통합명세부!$L:$L,$E21)/100,0) -> 0 | J21: =IFERROR( AVERAGEIFS(통합명세부!$AJ:$AJ,통합명세부!$F:$F,J$8,통합명세부!$L:$L,$E21)/100,0) -> 0 | K21: =IFERROR( AVERAGEIFS(통합명세부!$AJ:$AJ,통합명세부!$F:$F,K$8,통합명세부!$L:$L,$E21)/100,0) -> 0 | L21: =IFERROR( AVERAGEIFS(통합명세부!$AJ:$AJ,통합명세부!$F:$F,L$8,통합명세부!$L:$L,$E21)/100,0) -> 0 | M21: =IFERROR( AVERAGEIFS(통합명세부!$AJ:$AJ,통합명세부!$F:$F,M$8,통합명세부!$L:$L,$E21)/100,0) -> 0 | P21: KOSEF 국고채10년 | Q21: =IFERROR( AVERAGEIFS(통합명세부!$AJ:$AJ,통합명세부!$F:$F,Q$8,통합명세부!$L:$L,$P21)/100,0) -> 0.0145 | R21: =IFERROR( AVERAGEIFS(통합명세부!$AJ:$AJ,통합명세부!$F:$F,R$8,통합명세부!$L:$L,$P21)/100,0) -> 0.0145 | S21: =IFERROR( AVERAGEIFS(통합명세부!$AJ:$AJ,통합명세부!$F:$F,S$8,통합명세부!$L:$L,$P21)/100,0) -> 0.0145 | T21: =IFERROR( AVERAGEIFS(통합명세부!$AJ:$AJ,통합명세부!$F:$F,T$8,통합명세부!$L:$L,$P21)/100,0) -> 0.0104 | U21: =IFERROR( AVERAGEIFS(통합명세부!$AJ:$AJ,통합명세부!$F:$F,U$8,통합명세부!$L:$L,$P21)/100,0) -> 0.0145 | V21: =IFERROR( AVERAGEIFS(통합명세부!$AJ:$AJ,통합명세부!$F:$F,V$8,통합명세부!$L:$L,$P21)/100,0) -> 0.0104 | W21: =IFERROR( AVERAGEIFS(통합명세부!$AJ:$AJ,통합명세부!$F:$F,W$8,통합명세부!$L:$L,$P21)/100,0) -> 0.0063 | X21: =IFERROR( AVERAGEIFS(통합명세부!$AJ:$AJ,통합명세부!$F:$F,X$8,통합명세부!$L:$L,$P21)/100,0) -> 0.0031 | Z21: US | AA21: SPDR DJIA TRUST | AB21: =IFERROR( AVERAGEIFS(통합명세부!$AJ:$AJ,통합명세부!$F:$F,AB$8,통합명세부!$L:$L,$AA21)/100,0) -> 0.0194 | AC21: =IFERROR( AVERAGEIFS(통합명세부!$AJ:$AJ,통합명세부!$F:$F,AC$8,통합명세부!$L:$L,$AA21)/100,0) -> 0.0074
C22: Bond_KR_Total | D22: 273130 Ks equity | E22: KODEX 종합채권(AA-이상)액티브 | F22: =IFERROR( AVERAGEIFS(통합명세부!$AJ:$AJ,통합명세부!$F:$F,F$8,통합명세부!$L:$L,$E22)/100,0) -> 0.1829 | G22: =IFERROR( AVERAGEIFS(통합명세부!$AJ:$AJ,통합명세부!$F:$F,G$8,통합명세부!$L:$L,$E22)/100,0) -> 0.1664 | H22: =IFERROR( AVERAGEIFS(통합명세부!$AJ:$AJ,통합명세부!$F:$F,H$8,통합명세부!$L:$L,$E22)/100,0) -> 0.1613 | I22: =IFERROR( AVERAGEIFS(통합명세부!$AJ:$AJ,통합명세부!$F:$F,I$8,통합명세부!$L:$L,$E22)/100,0) -> 0.1035 | J22: =IFERROR( AVERAGEIFS(통합명세부!$AJ:$AJ,통합명세부!$F:$F,J$8,통합명세부!$L:$L,$E22)/100,0) -> 0.0361 | K22: =IFERROR( AVERAGEIFS(통합명세부!$AJ:$AJ,통합명세부!$F:$F,K$8,통합명세부!$L:$L,$E22)/100,0) -> 0 | L22: =IFERROR( AVERAGEIFS(통합명세부!$AJ:$AJ,통합명세부!$F:$F,L$8,통합명세부!$L:$L,$E22)/100,0) -> 0 | M22: =IFERROR( AVERAGEIFS(통합명세부!$AJ:$AJ,통합명세부!$F:$F,M$8,통합명세부!$L:$L,$E22)/100,0) -> 0 | P22: KODEX 종합채권(AA-이상)액티브 | Q22: =IFERROR( AVERAGEIFS(통합명세부!$AJ:$AJ,통합명세부!$F:$F,Q$8,통합명세부!$L:$L,$P22)/100,0) -> 0.4684 | R22: =IFERROR( AVERAGEIFS(통합명세부!$AJ:$AJ,통합명세부!$F:$F,R$8,통합명세부!$L:$L,$P22)/100,0) -> 0.4536 | S22: =IFERROR( AVERAGEIFS(통합명세부!$AJ:$AJ,통합명세부!$F:$F,S$8,통합명세부!$L:$L,$P22)/100,0) -> 0.4703 | T22: =IFERROR( AVERAGEIFS(통합명세부!$AJ:$AJ,통합명세부!$F:$F,T$8,통합명세부!$L:$L,$P22)/100,0) -> 0.3323 | U22: =IFERROR( AVERAGEIFS(통합명세부!$AJ:$AJ,통합명세부!$F:$F,U$8,통합명세부!$L:$L,$P22)/100,0) -> 0.4739 | V22: =IFERROR( AVERAGEIFS(통합명세부!$AJ:$AJ,통합명세부!$F:$F,V$8,통합명세부!$L:$L,$P22)/100,0) -> 0.3454 | W22: =IFERROR( AVERAGEIFS(통합명세부!$AJ:$AJ,통합명세부!$F:$F,W$8,통합명세부!$L:$L,$P22)/100,0) -> 0.1886 | X22: =IFERROR( AVERAGEIFS(통합명세부!$AJ:$AJ,통합명세부!$F:$F,X$8,통합명세부!$L:$L,$P22)/100,0) -> 0.0983 | Z22: DM_ex US | AA22: SPDR EURO STOXX 50 ETF | AB22: =IFERROR( AVERAGEIFS(통합명세부!$AJ:$AJ,통합명세부!$F:$F,AB$8,통합명세부!$L:$L,$AA22)/100,0) -> 0.0337 | AC22: =IFERROR( AVERAGEIFS(통합명세부!$AJ:$AJ,통합명세부!$F:$F,AC$8,통합명세부!$L:$L,$AA22)/100,0) -> 0.0129
C23: Bond_KR_Total | D23: 356540 KS Equity | E23: ACE 종합채권(AA-이상)KIS액티브 | F23: =IFERROR( AVERAGEIFS(통합명세부!$AJ:$AJ,통합명세부!$F:$F,F$8,통합명세부!$L:$L,$E23)/100,0) -> 0.1828 | G23: =IFERROR( AVERAGEIFS(통합명세부!$AJ:$AJ,통합명세부!$F:$F,G$8,통합명세부!$L:$L,$E23)/100,0) -> 0.1826 | H23: =IFERROR( AVERAGEIFS(통합명세부!$AJ:$AJ,통합명세부!$F:$F,H$8,통합명세부!$L:$L,$E23)/100,0) -> 0.182 | I23: =IFERROR( AVERAGEIFS(통합명세부!$AJ:$AJ,통합명세부!$F:$F,I$8,통합명세부!$L:$L,$E23)/100,0) -> 0.1821 | J23: =IFERROR( AVERAGEIFS(통합명세부!$AJ:$AJ,통합명세부!$F:$F,J$8,통합명세부!$L:$L,$E23)/100,0) -> 0.1812 | K23: =IFERROR( AVERAGEIFS(통합명세부!$AJ:$AJ,통합명세부!$F:$F,K$8,통합명세부!$L:$L,$E23)/100,0) -> 0.1616 | L23: =IFERROR( AVERAGEIFS(통합명세부!$AJ:$AJ,통합명세부!$F:$F,L$8,통합명세부!$L:$L,$E23)/100,0) -> 0.1157 | M23: =IFERROR( AVERAGEIFS(통합명세부!$AJ:$AJ,통합명세부!$F:$F,M$8,통합명세부!$L:$L,$E23)/100,0) -> 0.0834 | P23: ACE 종합채권(AA-이상)KIS액티브 | Q23: =IFERROR( AVERAGEIFS(통합명세부!$AJ:$AJ,통합명세부!$F:$F,Q$8,통합명세부!$L:$L,$P23)/100,0) -> 0.2031 | R23: =IFERROR( AVERAGEIFS(통합명세부!$AJ:$AJ,통합명세부!$F:$F,R$8,통합명세부!$L:$L,$P23)/100,0) -> 0.2179 | S23: =IFERROR( AVERAGEIFS(통합명세부!$AJ:$AJ,통합명세부!$F:$F,S$8,통합명세부!$L:$L,$P23)/100,0) -> 0.2012 | T23: =IFERROR( AVERAGEIFS(통합명세부!$AJ:$AJ,통합명세부!$F:$F,T$8,통합명세부!$L:$L,$P23)/100,0) -> 0.1467 | U23: =IFERROR( AVERAGEIFS(통합명세부!$AJ:$AJ,통합명세부!$F:$F,U$8,통합명세부!$L:$L,$P23)/100,0) -> 0.1979 | V23: =IFERROR( AVERAGEIFS(통합명세부!$AJ:$AJ,통합명세부!$F:$F,V$8,통합명세부!$L:$L,$P23)/100,0) -> 0.1334 | W23: =IFERROR( AVERAGEIFS(통합명세부!$AJ:$AJ,통합명세부!$F:$F,W$8,통합명세부!$L:$L,$P23)/100,0) -> 0.1032 | X23: =IFERROR( AVERAGEIFS(통합명세부!$AJ:$AJ,통합명세부!$F:$F,X$8,통합명세부!$L:$L,$P23)/100,0) -> 0.0476 | AA23: WISDOMTREE FLOATING RATE TRE | AB23: =IFERROR( AVERAGEIFS(통합명세부!$AJ:$AJ,통합명세부!$F:$F,AB$8,통합명세부!$L:$L,$AA23)/100,0) -> 0.0078 | AC23: =IFERROR( AVERAGEIFS(통합명세부!$AJ:$AJ,통합명세부!$F:$F,AC$8,통합명세부!$L:$L,$AA23)/100,0) -> 0.0205
C24: Bond_KR_Long | D24: 365780 KS Equity | E24: ACE 국고채10년 | F24: =IFERROR( AVERAGEIFS(통합명세부!$AJ:$AJ,통합명세부!$F:$F,F$8,통합명세부!$L:$L,$E24)/100,0) -> 0.0278 | G24: =IFERROR( AVERAGEIFS(통합명세부!$AJ:$AJ,통합명세부!$F:$F,G$8,통합명세부!$L:$L,$E24)/100,0) -> 0.0565 | H24: =IFERROR( AVERAGEIFS(통합명세부!$AJ:$AJ,통합명세부!$F:$F,H$8,통합명세부!$L:$L,$E24)/100,0) -> 0.0841 | I24: =IFERROR( AVERAGEIFS(통합명세부!$AJ:$AJ,통합명세부!$F:$F,I$8,통합명세부!$L:$L,$E24)/100,0) -> 0.1102 | J24: =IFERROR( AVERAGEIFS(통합명세부!$AJ:$AJ,통합명세부!$F:$F,J$8,통합명세부!$L:$L,$E24)/100,0) -> 0.1235 | K24: =IFERROR( AVERAGEIFS(통합명세부!$AJ:$AJ,통합명세부!$F:$F,K$8,통합명세부!$L:$L,$E24)/100,0) -> 0.1306 | L24: =IFERROR( AVERAGEIFS(통합명세부!$AJ:$AJ,통합명세부!$F:$F,L$8,통합명세부!$L:$L,$E24)/100,0) -> 0.1362 | M24: =IFERROR( AVERAGEIFS(통합명세부!$AJ:$AJ,통합명세부!$F:$F,M$8,통합명세부!$L:$L,$E24)/100,0) -> 0.1372 | P24: KODEX 국고채30년액티브 | Q24: =IFERROR( AVERAGEIFS(통합명세부!$AJ:$AJ,통합명세부!$F:$F,Q$8,통합명세부!$L:$L,$P24)/100,0) -> 0.0145 | R24: =IFERROR( AVERAGEIFS(통합명세부!$AJ:$AJ,통합명세부!$F:$F,R$8,통합명세부!$L:$L,$P24)/100,0) -> 0.0145 | S24: =IFERROR( AVERAGEIFS(통합명세부!$AJ:$AJ,통합명세부!$F:$F,S$8,통합명세부!$L:$L,$P24)/100,0) -> 0.0145 | T24: =IFERROR( AVERAGEIFS(통합명세부!$AJ:$AJ,통합명세부!$F:$F,T$8,통합명세부!$L:$L,$P24)/100,0) -> 0.0104 | U24: =IFERROR( AVERAGEIFS(통합명세부!$AJ:$AJ,통합명세부!$F:$F,U$8,통합명세부!$L:$L,$P24)/100,0) -> 0.0145 | V24: =IFERROR( AVERAGEIFS(통합명세부!$AJ:$AJ,통합명세부!$F:$F,V$8,통합명세부!$L:$L,$P24)/100,0) -> 0.0104 | W24: =IFERROR( AVERAGEIFS(통합명세부!$AJ:$AJ,통합명세부!$F:$F,W$8,통합명세부!$L:$L,$P24)/100,0) -> 0.0063 | X24: =IFERROR( AVERAGEIFS(통합명세부!$AJ:$AJ,통합명세부!$F:$F,X$8,통합명세부!$L:$L,$P24)/100,0) -> 0.0031 | AA24: ISHARES JP MORGAN EM BOND FD | AB24: =IFERROR( AVERAGEIFS(통합명세부!$AJ:$AJ,통합명세부!$F:$F,AB$8,통합명세부!$L:$L,$AA24)/100,0) -> 0.0171 | AC24: =IFERROR( AVERAGEIFS(통합명세부!$AJ:$AJ,통합명세부!$F:$F,AC$8,통합명세부!$L:$L,$AA24)/100,0) -> 0
AA25: SPDR Portfolio S&P 500 High Di | AB25: =IFERROR( AVERAGEIFS(통합명세부!$AJ:$AJ,통합명세부!$F:$F,AB$8,통합명세부!$L:$L,$AA25)/100,0) -> 0 | AC25: =IFERROR( AVERAGEIFS(통합명세부!$AJ:$AJ,통합명세부!$F:$F,AC$8,통합명세부!$L:$L,$AA25)/100,0) -> 0
AA26: ISHARES MBS ETF | AB26: =IFERROR( AVERAGEIFS(통합명세부!$AJ:$AJ,통합명세부!$F:$F,AB$8,통합명세부!$L:$L,$AA26)/100,0) -> 0.0149 | AC26: =IFERROR( AVERAGEIFS(통합명세부!$AJ:$AJ,통합명세부!$F:$F,AC$8,통합명세부!$L:$L,$AA26)/100,0) -> 0.0391
AA27: VANECK VECTORS GOLD MINERS ETF | AB27: =IFERROR( AVERAGEIFS(통합명세부!$AJ:$AJ,통합명세부!$F:$F,AB$8,통합명세부!$L:$L,$AA27)/100,0) -> 0 | AC27: =IFERROR( AVERAGEIFS(통합명세부!$AJ:$AJ,통합명세부!$F:$F,AC$8,통합명세부!$L:$L,$AA27)/100,0) -> 0
AA28: ISHARES IBOXX INV GR CORP BD | AB28: =IFERROR( AVERAGEIFS(통합명세부!$AJ:$AJ,통합명세부!$F:$F,AB$8,통합명세부!$L:$L,$AA28)/100,0) -> 0.0149 | AC28: =IFERROR( AVERAGEIFS(통합명세부!$AJ:$AJ,통합명세부!$F:$F,AC$8,통합명세부!$L:$L,$AA28)/100,0) -> 0.0391
AA29: ISHARES PHLX SOX SEMICONDUCT | AB29: =IFERROR( AVERAGEIFS(통합명세부!$AJ:$AJ,통합명세부!$F:$F,AB$8,통합명세부!$L:$L,$AA29)/100,0) -> 0.0201 | AC29: =IFERROR( AVERAGEIFS(통합명세부!$AJ:$AJ,통합명세부!$F:$F,AC$8,통합명세부!$L:$L,$AA29)/100,0) -> 0.0077
AA30: USD DEPOSIT | AB30: =IFERROR( AVERAGEIFS(통합명세부!$AJ:$AJ,통합명세부!$F:$F,AB$8,통합명세부!$L:$L,$AA30)/100,0) -> 0.0219 | AC30: =IFERROR( AVERAGEIFS(통합명세부!$AJ:$AJ,통합명세부!$F:$F,AC$8,통합명세부!$L:$L,$AA30)/100,0) -> 0.0216

Sheet 자금총괄
A1: Unnamed: 0 | B1: 펀드 | C1: 펀드명 | D1: NAV | E1: Unnamed: 4 | F1: 통화 | G1: T0 (02.28, 수) | H1: Unnamed: 7 | I1: T1 (02.29, 목) | J1: Unnamed: 9 | K1: T2 (03.04, 월) | L1: Unnamed: 11 | M1: T3 (03.05, 화) | N1: Unnamed: 13 | O1: T4 (03.06, 수) | P1: Unnamed: 15 | Q1: T5 (03.07, 목) | R1: Unnamed: 17 | S1: T6 (03.08, 금) | T1: Unnamed: 19 | U1: T7 (03.11, 월) | V1: Unnamed: 21 | W1: T8 (03.12, 화) | X1: Unnamed: 23 | Y1: T9 (03.13, 수) | Z1: Unnamed: 25 | AA1: T10 (03.14, 목) | AB1: Unnamed: 27 | AC1: T11 (03.15, 금) | AD1: Unnamed: 29 | AE1: T12 (03.18, 월) | AF1: Unnamed: 31 | AG1: T13 (03.19, 화) | AH1: Unnamed: 33 | AI1: T14 (03.20, 수) | AJ1: Unnamed: 35 | AK1: Unnamed: 36
B2: 펀드 | C2: 펀드명 | D2: 전일 | E2: 당일 | F2: 통화 | G2: 자금 | H2: 비중 | I2: 자금 | J2: 비중 | K2: 자금 | L2: 비중 | M2: 자금 | N2: 비중 | O2: 자금 | P2: 비중 | Q2: 자금 | R2: 비중 | S2: 자금 | T2: 비중 | U2: 자금 | V2: 비중 | W2: 자금 | X2: 비중 | Y2: 자금 | Z2: 비중 | AA2: 자금 | AB2: 비중 | AC2: 자금 | AD2: 비중 | AE2: 자금 | AF2: 비중 | AG2: 자금 | AH2: 비중 | AI2: 자금 | AJ2: 비중
A3: 1 | B3: 03V94 | C3: 한국투자글로벌채권솔루션증권모투자신탁(채권-재간접형) | D3: 14206867597 | E3: 14205941288 | F3: KRW | G3: 114643385 | H3: 0.8 | I3: 360773253 | J3: 2.53 | K3: 348972862 | L3: 2.45 | M3: 333935753 | N3: 2.35 | O3: 324002296 | P3: 2.28 | Q3: 296871265 | R3: 2.08 | S3: 295569016 | T3: 2.08 | U3: 295569016 | V3: 2.08 | W3: 295569016 | X3: 2.08 | Y3: 295569016 | Z3: 2.08 | AA3: 295569016 | AB3: 2.08 | AC3: 295518876 | AD3: 2.08 | AE3: 295518876 | AF3: 2.08 | AG3: 295518876 | AH3: 2.08 | AI3: 295518876 | AJ3: 2.08
A4: 2 | B4: 03V94 | C4: 한국투자글로벌채권솔루션증권모투자신탁(채권-재간접형) | D4: 14206867597 | E4: 14205941288 | F4: USD | G4: 284132.39 | H4: 2.66 | I4: 115270.04 | J4: 1.08 | K4: 115270.04 | L4: 1.08 | M4: 115270.04 | N4: 1.08 | O4: 115270.04 | P4: 1.08 | Q4: 115270.04 | R4: 1.08 | S4: 115270.04 | T4: 1.08 | U4: 115270.04 | V4: 1.08 | W4: 115270.04 | X4: 1.08 | Y4: 115270.04 | Z4: 1.08 | AA4: 115270.04 | AB4: 1.08 | AC4: 115270.04 | AD4: 1.08 | AE4: 115270.04 | AF4: 1.08 | AG4: 115270.04 | AH4: 1.08 | AI4: 115270.04 | AJ4: 1.08
A5: 3 | B5: 03V95 | C5: 한국투자글로벌주식솔루션증권모투자신탁(주식-재간접형) | D5: 5365519257 | E5: 5366270522 | F5: KRW | G5: 45504635 | H5: 0.84 | I5: 223569270 | J5: 4.16 | K5: 211256443 | L5: 3.93 | M5: 191063367 | N5: 3.56 | O5: 182140857 | P5: 3.39 | Q5: 146371885 | R5: 2.72 | S5: 146107795 | T5: 2.72 | U5: 146107795 | V5: 2.72 | W5: 146107795 | X5: 2.72 | Y5: 146107795 | Z5: 2.72 | AA5: 146107795 | AB5: 2.72 | AC5: 146089435 | AD5: 2.72 | AE5: 146089435 | AF5: 2.72 | AG5: 146089435 | AH5: 2.72 | AI5: 146089435 | AJ5: 2.72
A6: 4 | B6: 03V95 | C6: 한국투자글로벌주식솔루션증권모투자신탁(주식-재간접형) | D6: 5365519257 | E6: 5366270522 | F6: USD | G6: 262355.09 | H6: 6.5 | I6: 135176.49 | J6: 3.35 | K6: 135176.49 | L6: 3.35 | M6: 135176.49 | N6: 3.35 | O6: 135176.49 | P6: 3.35 | Q6: 135176.49 | R6: 3.35 | S6: 135176.49 | T6: 3.35 | U6: 135176.49 | V6: 3.35 | W6: 135176.49 | X6: 3.35 | Y6: 135176.49 | Z6: 3.35 | AA6: 135176.49 | AB6: 3.35 | AC6: 135176.49 | AD6: 3.35 | AE6: 135176.49 | AF6: 3.35 | AG6: 135176.49 | AH6: 3.35 | AI6: 135176.49 | AJ6: 3.35
A7: 5 | B7: 05C02 | C7: 한국투자TDF알아서증권투자신탁(채권혼합-재간접형)(모) | D7: 177672468215 | E7: 177568601898 | F7: KRW | G7: 4729607318 | H7: 2.66 | I7: 4651712774 | J7: 2.61 | K7: 4532233625 | L7: 2.55 | M7: 4424950967 | N7: 2.49 | O7: 4312679738 | P7: 2.42 | Q7: 45625416967 | R7: 25.69 | S7: 45464661796 | T7: 25.6 | U7: 45241657788 | V7: 25.47 | W7: 45051947948 | X7: 25.37 | Y7: 45051947948 | Z7: 25.37 | AA7: 45051947948 | AB7: 25.37 | AC7: 45051468998 | AD7: 25.37 | AE7: 45051468998 | AF7: 25.37 | AG7: 45051468998 | AH7: 25.37 | AI7: 45051468998 | AJ7: 25.37
A8: 6 | B8: 05C02 | C8: 한국투자TDF알아서증권투자신탁(채권혼합-재간접형)(모) | D8: 177672468215 | E8: 177568601898 | F8: USD | G8: 769.67 | H8: 0 | I8: 769.67 | J8: 0 | K8: 769.67 | L8: 0 | M8: 769.67 | N8: 0 | O8: 769.67 | P8: 0 | Q8: -32009230 | R8: -23.99 | S8: -32009230 | T8: -23.99 | U8: -32009230 | V8: -23.99 | W8: -32009230 | X8: -23.99 | Y8: -32009230 | Z8: -23.99 | AA8: -32009230 | AB8: -23.99 | AC8: -32009230 | AD8: -23.99 | AE8: -32009230 | AF8: -23.99 | AG8: -32009230 | AH8: -23.99 | AI8: -32009230 | AJ8: -23.99
A9: 7 | B9: 05C14 | C9: 한국투자TDF알아서2020증권모투자신탁(채권혼합-재간접형) | D9: 79725351953 | E9: 79652980661 | F9: KRW | G9: 1610565567 | H9: 2.02 | I9: 1510299971 | J9: 1.89 | K9: 1446906896 | L9: 1.81 | M9: 1352356202 | N9: 1.69 | O9: 1202634487 | P9: 1.5 | Q9: 18362740295 | R9: 23.05 | S9: 18272520530 | T9: 22.94 | U9: 18169782768 | V9: 22.81 | W9: 18145003530 | X9: 22.78 | Y9: 18145003530 | Z9: 22.78 | AA9: 18517109530 | AB9: 23.24 | AC9: 18516869280 | AD9: 23.24 | AE9: 18516869280 | AF9: 23.24 | AG9: 18516869280 | AH9: 23.24 | AI9: 18516869280 | AJ9: 23.24
A10: 8 | B10: 05C14 | C10: 한국투자TDF알아서2020증권모투자신탁(채권혼합-재간접형) | D10: 79725351953 | E10: 79652980661 | F10: USD | G10: 4975.33 | H10: 0 | I10: 4975.33 | J10: 0 | K10: 4975.33 | L10: 0 | M10: 4975.33 | N10: 0 | O10: 4975.33 | P10: 0 | Q10: -13315025 | R10: -22.24 | S10: -13315025 | T10: -22.24 | U10: -13315025 | V10: -22.24 | W10: -13315025 | X10: -22.24 | Y10: -13315025 | Z10: -22.24 | AA10: -13595025 | AB10: -22.71 | AC10: -13595025 | AD10: -22.71 | AE10: -13595025 | AF10: -22.71 | AG10: -13595025 | AH10: -22.71 | AI10: -13595025 | AJ10: -22.71
A11: 9 | B11: 05C16 | C11: 한국투자TDF알아서2020증권자투자신탁(채권혼합-재간접형)(모) | D11: 63497526514 | E11: 63428725943 | F11: KRW | G11: 829818524 | H11: 1.3 | I11: 833231150 | J11: 1.31 | K11: 751508214 | L11: 1.18 | M11: 754262118 | N11: 1.18 | O11: 758525054 | P11: 1.19 | Q11: 761697054 | R11: 1.2 | S11: 764159388 | T11: 1.2 | U11: 767135606 | V11: 1.2 | W11: 767837608 | X11: 1.21 | Y11: 767837608 | Z11: 1.21 | AA11: 767837608 | AB11: 1.21 | AC11: 767837608 | AD11: 1.21 | AE11: 767837608 | AF11: 1.21 | AG11: 767837608 | AH11: 1.21 | AI11: 767837608 | AJ11: 1.21
A12: 10 | B12: 05C30 | C12: 한국투자TDF알아서2025증권투자신탁(주식혼합-재간접형)(모) | D12: 136690481003 | E12: 136704200425 | F12: KRW | G12: 3879300019 | H12: 2.83 | I12: 3847124436 | J12: 2.81 | K12: 3480638381 | L12: 2.54 | M12: 3442308917 | N12: 2.51 | O12: 3072690907 | P12: 2.24 | Q12: 32971285509 | R12: 24.11 | S12: 32883128214 | T12: 24.05 | U12: 32775250444 | V12: 23.97 | W12: 32702381370 | X12: 23.92 | Y12: 32702381370 | Z12: 23.92 | AA12: 32702381370 | AB12: 23.92 | AC12: 32702013670 | AD12: 23.92 | AE12: 32702013670 | AF12: 23.92 | AG12: 32702013670 | AH12: 23.92 | AI12: 32702013670 | AJ12: 23.92
